Workbook
Name CHK_TOL: InpC!$F$101
Name SMU: InpC!$F$103
Name LIVE_RESULTS: Track!$H$8:$H$69
Name TRACK_ACTIVE: Track!$H$5
Name TRK_COMMENT: Track!$H$77:$H$78
Name unit: InpC!$F$102

Sheet Cover
B2: TrainStat Project Finance Model: complete
B3: Mastering Infrastructure and Project Finance Boot Camp | Lagos Business School | 14 to 22 October 2026
B4: bongo.ai | MIPF | Prof Bongo Adi | +234 706 164 8699 | badi@lbs.edu.ng | bongo.adi@fulbrightmail.org
B7: MODEL STATUS | C7: =IF(FinStat!F80+FinStat!F83+FinStat!F86+Time!F120+IF(ABS(Constr!F55)>CHK_TOL,1,0)+IF(SUMPRODUCT(ABS(Constr!J48:Q48))>CHK_TOL,1,0)=0,"ALL CHECKS PASSED","CHECK ERRORS: see FinStat and Constr") -> ALL CHECKS PASSED
B8: Active scenario | C8: =InpC!F3 -> Base
B9: Scenario definitions | C9: Base: inflation 7% falling to 3%, fare US$7.15, O&M as contracted. Downside: fare -10% and O&M +10%. Upside: fare +10%.
B10: Debt sizing | C10: =IF(ABS(Sculpt!F32)<1,"Debt drawn equals debt sized","RE-RUN GOAL SEEK: debt drawn less debt sized = "&TEXT(Sculpt!F32,"#,##0")) -> Debt drawn equals debt sized
B11: CONTENTS
B12: Dashboard | C12: Key results, annual summary and charts
B13: InpC | C13: Constants and scenario switch (yellow = typed assumption)
B14: InpS | C14: Time-series inputs: trains, arrivals, occupancy, repayment profiles, extra funding
B15: Time | C15: Timeline, flags and integrity checks
B16: Esc | C16: Inflation and escalation factors
B17: Constr | C17: Construction period: spend, fees, interest during construction, sources and uses, opening balances
B18: OpRev | C18: Demand and operating revenue, cash received, receivables
B19: OpCost | C19: Operating cost, cash paid, payables
B20: Tax | C20: Tax depreciation, tax paid, tax expense, deferred tax
B21: NCA | C21: Capital expenditure, depreciation, asset balance
B22: Debt | C22: Senior debt: repayment profile, interest, balance
B23: Sculpt | C23: Debt capacity, sizing and sculpted repayment
... B30: Track | C30: Scenario log: live results and stored runs
B33: COLOUR CODE
B34: Yellow fill | C34: Typed assumption (input)
B35: Blue font | C35: Link pulled in from another row or sheet
B36: Red font | C36: Key result row used by other sheets
B37: Black font | C37: Intermediate calculation
B40: HOW TO RUN
B41: 1. Choose the scenario in InpC!F3 (drop-down). Everything recalculates.
B42: 2. Change assumptions only in InpC (constants) and InpS (time series).
B43: 3. Confirm the status line above says ALL CHECKS PASSED.
B44: 4. To store a run: copy Track!H8:H69, paste values into M, N or O (Paste Special, Values).
B45: 5. After changing price, cost, tenor or DSCR inputs: Goal Seek Sculpt!F32 to 0 by changing the active scenario's gearing cell on InpC row 72 (J72 Base, K72 Downside, L72 Upside); then set the facility on InpC row 131 to ROUNDUP(Sculpt!F29, 0) for that scenario and repeat both until stable (the facility drives the fees, which drive the project cost).
B47: CHANGE LOG (v1.0, 8 October 2026)
B48: 1. Ghost formulas removed: seven sheets carried about 1,238,318 formulas and formats out to column XFD (the sheet edge), far beyond the 84-column timeline (J to CO). Trimming them cuts the file from about 6.0 MB to 0.4 MB and makes recalculation take seconds instead of many minutes. The unused scratch sheet 'Temp' (about 50,000 formulas) was removed.
B49: 2. Defined names LIVE_RESULTS, TRACK_ACTIVE and TRK_COMMENT repaired (they pointed at deleted cells); name 'unit' re-pointed from an external link to InpC!F102; sheet-level names on Track that pointed at an external workbook removed; Time print area extended to column CO; external link removed.
B50: 3. Typos corrected: Scenario, arrival, Investment, Accounting, available, period, NPV of ...
B51: 4. Stray zeros removed (Tax C28, C35; InpC row 45; InpS J74).
B52: 5. Total and check ranges extended to column CO (they stopped at BY, BV or CQ): the three FinStat checks now cover every column, Time!H79 now counts the post-forecast flag.
... B64: 17. Conventions retained and documented in the Prompt Book: all sponsor funding is dated at COD in Val (equity is actually paid in during construction, so the blended IRR is measured from COD); tax losses are refunded in cash (no loss carry-forward); the model has no DSRA draw and no dividend lock-up.

Sheet Dashboard
B2: TrainStat: dashboard | F2: ="Scenario: "&InpC!F3 -> Scenario: Base | K2: =Cover!C7 -> ALL CHECKS PASSED
B5: Shareholder NPV ($000s) | E5: Shareholder IRR (XIRR) | J5: Minimum DSCR | O5: Total CFADS ($000s)
B6: =Val!F41 -> 28243.56 | E6: =Val!F51 -> 0.43033599 | J6: =Ratios!F13 -> 2.2966072 | O6: =Track!H10 -> 591529.28
B9: Senior debt at close ($000s) | E9: Project cost at COD ($000s) | J9: Gearing at COD | O9: LLCR at COD
B10: =Debt!F11 -> 72154.225 | E10: =Constr!F52 -> 101067.8 | J10: =Constr!F53/Constr!F52 -> 0.71391903 | O10: =Ratios!F22 -> 2.3998574
B14: ANNUAL SUMMARY ($000s)
B15: Financial year | C15: 2022 | D15: 2023 | E15: 2024 | F15: 2025 | G15: 2026 | H15: 2027 | I15: 2028 | J15: 2029 | K15: 2030 | L15: 2031 | M15: 2032 | N15: 2033 | O15: 2034 | P15: 2035 | Q15: 2036 | R15: 2037 | S15: 2038 | T15: 2039 | U15: 2040 | V15: 2041
B16: Operating revenue | C16: =SUMIFS(FinStat!$J$9:$CO$9,FinStat!$J$4:$CO$4,C$15) -> 62837.028 | D16: =SUMIFS(FinStat!$J$9:$CO$9,FinStat!$J$4:$CO$4,D$15) -> 66458.897 | E16: =SUMIFS(FinStat!$J$9:$CO$9,FinStat!$J$4:$CO$4,E$15) -> 70598.708 | F16: =SUMIFS(FinStat!$J$9:$CO$9,FinStat!$J$4:$CO$4,F$15) -> 72981.116 | G16: =SUMIFS(FinStat!$J$9:$CO$9,FinStat!$J$4:$CO$4,G$15) -> 76493.107 | H16: =SUMIFS(FinStat!$J$9:$CO$9,FinStat!$J$4:$CO$4,H$15) -> 80130.149 | I16: =SUMIFS(FinStat!$J$9:$CO$9,FinStat!$J$4:$CO$4,I$15) -> 83218.707 | J16: =SUMIFS(FinStat!$J$9:$CO$9,FinStat!$J$4:$CO$4,J$15) -> 87879.262 | ... V16: =SUMIFS(FinStat!$J$9:$CO$9,FinStat!$J$4:$CO$4,V$15) -> 133493.04
B17: Operating cost | C17: =SUMIFS(FinStat!$J$10:$CO$10,FinStat!$J$4:$CO$4,C$15) -> -40792.852 | D17: =SUMIFS(FinStat!$J$10:$CO$10,FinStat!$J$4:$CO$4,D$15) -> -43322.487 | E17: =SUMIFS(FinStat!$J$10:$CO$10,FinStat!$J$4:$CO$4,E$15) -> -45216.961 | F17: =SUMIFS(FinStat!$J$10:$CO$10,FinStat!$J$4:$CO$4,F$15) -> -46742.444 | G17: =SUMIFS(FinStat!$J$10:$CO$10,FinStat!$J$4:$CO$4,G$15) -> -48144.717 | H17: =SUMIFS(FinStat!$J$10:$CO$10,FinStat!$J$4:$CO$4,H$15) -> -49589.058 | I17: =SUMIFS(FinStat!$J$10:$CO$10,FinStat!$J$4:$CO$4,I$15) -> -51076.73 | J17: =SUMIFS(FinStat!$J$10:$CO$10,FinStat!$J$4:$CO$4,J$15) -> -52609.032 | ... V17: =SUMIFS(FinStat!$J$10:$CO$10,FinStat!$J$4:$CO$4,V$15) -> -76522.488
B18: EBITDA | C18: =SUMIFS(FinStat!$J$11:$CO$11,FinStat!$J$4:$CO$4,C$15) -> 22044.177 | D18: =SUMIFS(FinStat!$J$11:$CO$11,FinStat!$J$4:$CO$4,D$15) -> 23136.41 | E18: =SUMIFS(FinStat!$J$11:$CO$11,FinStat!$J$4:$CO$4,E$15) -> 25381.748 | F18: =SUMIFS(FinStat!$J$11:$CO$11,FinStat!$J$4:$CO$4,F$15) -> 26238.672 | G18: =SUMIFS(FinStat!$J$11:$CO$11,FinStat!$J$4:$CO$4,G$15) -> 28348.39 | H18: =SUMIFS(FinStat!$J$11:$CO$11,FinStat!$J$4:$CO$4,H$15) -> 30541.091 | I18: =SUMIFS(FinStat!$J$11:$CO$11,FinStat!$J$4:$CO$4,I$15) -> 32141.977 | J18: =SUMIFS(FinStat!$J$11:$CO$11,FinStat!$J$4:$CO$4,J$15) -> 35270.229 | ... V18: =SUMIFS(FinStat!$J$11:$CO$11,FinStat!$J$4:$CO$4,V$15) -> 56970.556
B19: CFADS | C19: =SUMIFS(FinStat!$J$39:$CO$39,FinStat!$J$4:$CO$4,C$15) -> 22641.77 | D19: =SUMIFS(FinStat!$J$39:$CO$39,FinStat!$J$4:$CO$4,D$15) -> 20599.828 | E19: =SUMIFS(FinStat!$J$39:$CO$39,FinStat!$J$4:$CO$4,E$15) -> 22274.917 | F19: =SUMIFS(FinStat!$J$39:$CO$39,FinStat!$J$4:$CO$4,F$15) -> 21693.19 | G19: =SUMIFS(FinStat!$J$39:$CO$39,FinStat!$J$4:$CO$4,G$15) -> 22880.839 | H19: =SUMIFS(FinStat!$J$39:$CO$39,FinStat!$J$4:$CO$4,H$15) -> 24514.231 | I19: =SUMIFS(FinStat!$J$39:$CO$39,FinStat!$J$4:$CO$4,I$15) -> 24415.303 | J19: =SUMIFS(FinStat!$J$39:$CO$39,FinStat!$J$4:$CO$4,J$15) -> 26326.737 | ... V19: =SUMIFS(FinStat!$J$39:$CO$39,FinStat!$J$4:$CO$4,V$15) -> 40576.132
B20: Senior debt service | C20: =SUMIFS(FinStat!$J$94:$CO$94,FinStat!$J$4:$CO$4,C$15) -> 9204.8079 | D20: =SUMIFS(FinStat!$J$94:$CO$94,FinStat!$J$4:$CO$4,D$15) -> 8337.4416 | E20: =SUMIFS(FinStat!$J$94:$CO$94,FinStat!$J$4:$CO$4,E$15) -> 9116.7282 | F20: =SUMIFS(FinStat!$J$94:$CO$94,FinStat!$J$4:$CO$4,F$15) -> 8906.0985 | G20: =SUMIFS(FinStat!$J$94:$CO$94,FinStat!$J$4:$CO$4,G$15) -> 9481.041 | H20: =SUMIFS(FinStat!$J$94:$CO$94,FinStat!$J$4:$CO$4,H$15) -> 10264.804 | I20: =SUMIFS(FinStat!$J$94:$CO$94,FinStat!$J$4:$CO$4,I$15) -> 10285.635 | J20: =SUMIFS(FinStat!$J$94:$CO$94,FinStat!$J$4:$CO$4,J$15) -> 11211.035 | ... V20: =SUMIFS(FinStat!$J$94:$CO$94,FinStat!$J$4:$CO$4,V$15) -> 5.9938227e-13
B21: Dividends | C21: =-SUMIFS(FinStat!$J$51:$CO$51,FinStat!$J$4:$CO$4,C$15) -> 6208.8704 | D21: =-SUMIFS(FinStat!$J$51:$CO$51,FinStat!$J$4:$CO$4,D$15) -> 7184.2923 | E21: =-SUMIFS(FinStat!$J$51:$CO$51,FinStat!$J$4:$CO$4,E$15) -> 8658.7429 | F21: =-SUMIFS(FinStat!$J$51:$CO$51,FinStat!$J$4:$CO$4,F$15) -> 9370.148 | G21: =-SUMIFS(FinStat!$J$51:$CO$51,FinStat!$J$4:$CO$4,G$15) -> 10884.216 | H21: =-SUMIFS(FinStat!$J$51:$CO$51,FinStat!$J$4:$CO$4,H$15) -> 12582.612 | I21: =-SUMIFS(FinStat!$J$51:$CO$51,FinStat!$J$4:$CO$4,I$15) -> 13973.428 | J21: =-SUMIFS(FinStat!$J$51:$CO$51,FinStat!$J$4:$CO$4,J$15) -> 16701.545 | ... V21: =-SUMIFS(FinStat!$J$51:$CO$51,FinStat!$J$4:$CO$4,V$15) -> 38068.623
B22: DSCR (CFADS / debt service) | C22: =IF(ABS(C20)>CHK_TOL,C19/C20,0) -> 2.4597765 | D22: =IF(ABS(D20)>CHK_TOL,D19/D20,0) -> 2.4707613 | E22: =IF(ABS(E20)>CHK_TOL,E19/E20,0) -> 2.4433016 | F22: =IF(ABS(F20)>CHK_TOL,F19/F20,0) -> 2.435768 | G22: =IF(ABS(G20)>CHK_TOL,G19/G20,0) -> 2.4133256 | H22: =IF(ABS(H20)>CHK_TOL,H19/H20,0) -> 2.3881832 | I22: =IF(ABS(I20)>CHK_TOL,I19/I20,0) -> 2.3737284 | J22: =IF(ABS(J20)>CHK_TOL,J19/J20,0) -> 2.3482878 | ... V22: =IF(ABS(V20)>CHK_TOL,V19/V20,0) -> 0

Sheet InpC
A1: =RIGHT(CELL("filename", A1), LEN(CELL("filename", A1)) - SEARCH("]", CELL("filename", A1)))
E3: Scenario name | F3: Base | J3: Base | K3: Downside | L3: Upside | N3: Scenario definitions
E4: Scenario switch | F4: =MATCH(F3,I3:M3,0) -> 2 | N4: Base: inflation 7% falling to 3%; fare 7.15; O&M as contracted
F5: Constant | G5: Unit | N5: Downside: Base with fare -10% (6.435) and O&M +10%
N6: Upside: Base with fare +10% (7.865)
A7: TIME
E9: First date of time rulers | F9: {=INDEX(I9:M9,$F$4)} -> 44378 | G9: date | J9: 44378 | K9: 44378 | L9: 44378
E10: Acquisition / initial balance date | F10: {=INDEX(I10:M10,$F$4)} -> 44561 | G10: date | J10: 44561 | K10: 44561 | L10: 44561
E11: Length of forecast period | F11: {=INDEX(I11:M11,$F$4)} -> 20 | G11: years | J11: 20 | K11: 20 | L11: 20
E12: Months per model period | F12: {=INDEX(I12:M12,$F$4)} -> 3 | G12: months | J12: 3 | K12: 3 | L12: 3
A14: ESCALATION
E16: Start of the inflation year | F16: {=INDEX(I16:M16,$F$4)} -> % p.a | J16: % p.a | K16: % p.a | L16: % p.a
E17: 44256 | F17: {=INDEX(I17:M17,$F$4)} -> 0.07 | G17: % p.a | J17: 0.07 | K17: 0.07 | L17: 0.07
E18: 44621 | F18: {=INDEX(I18:M18,$F$4)} -> 0.06 | G18: % p.a | J18: 0.06 | K18: 0.06 | L18: 0.06
E19: 44986 | F19: {=INDEX(I19:M19,$F$4)} -> 0.05 | G19: % p.a | J19: 0.05 | K19: 0.05 | L19: 0.05
E20: 45352 | F20: {=INDEX(I20:M20,$F$4)} -> 0.04 | G20: % p.a | J20: 0.04 | K20: 0.04 | L20: 0.04
E21: 45717 | F21: {=INDEX(I21:M21,$F$4)} -> 0.03 | G21: % p.a | J21: 0.03 | K21: 0.03 | L21: 0.03
E23: CPI index at acquisition date | F23: {=INDEX(I23:M23,$F$4)} -> 145 | G23: index | J23: 145 | K23: 145 | L23: 145
E25: CPI index at handling signature date | F25: {=INDEX(I25:M25,$F$4)} -> 120 | G25: index | J25: 120 | K25: 120 | L25: 120
E27: CPI index at O&M signature date | F27: {=INDEX(I27:M27,$F$4)} -> 132 | G27: index | J27: 132 | K27: 132 | L27: 132
A29: OPERATING REVENUE
E31: Train capacity - domestic | F31: {=INDEX(I31:M31,$F$4)} -> 350 | G31: seats | J31: 350 | K31: 350 | L31: 350
E33: Train capacity - international | F33: {=INDEX(I33:M33,$F$4)} -> 150 | G33: seats | J33: 150 | K33: 150 | L33: 150
E35: Average fare per passenger | F35: {=INDEX(I35:M35,$F$4)} -> 7.15 | G35: USD/pax | J35: 7.15 | K35: 6.435 | L35: 7.865
E37: Account receivables days | F37: {=INDEX(I37:M37,$F$4)} -> 25 | G37: days | J37: 25 | K37: 25 | L37: 25
A40: OPERATING COST
E42: Handling cost- fixed per annum | F42: {=INDEX(I42:M42,$F$4)} -> 4500 | G42: $ 000s | J42: 4500 | K42: 4500 | L42: 4500
E44: Handling cost - variable | F44: {=INDEX(I44:M44,$F$4)} -> 550 | G44: USD/arrival | J44: 550 | K44: 550 | L44: 550
E46: O&M cost - sensitivity | F46: {=INDEX(I46:M46,$F$4)} -> 0 | G46: (1 + X%) | J46: 0 | K46: 0.1 | L46: 0
E48: O&M cost- fixed per annum | F48: {=INDEX(I48:M48,$F$4)} -> 3300 | G48: =SMU -> $ 000s | J48: 3300 | K48: 3300 | L48: 3300
E50: Account payables days | F50: {=INDEX(I50:M50,$F$4)} -> 35 | G50: days | J50: 35 | K50: 35 | L50: 35
A53: NON CURRENT ASSET
E55: Investment / addition date | F55: {=INDEX(I55:M55,$F$4)} -> $000s | J55: $000s | K55: $000s | L55: $000s
E56: 45291 | F56: {=INDEX(I56:M56,$F$4)} -> 2000 | G56: $ 000s | J56: 2000 | K56: 2000 | L56: 2000
E57: 45657 | F57: {=INDEX(I57:M57,$F$4)} -> 1000 | G57: $ 000s | J57: 1000 | K57: 1000 | L57: 1000
E58: 46022 | F58: {=INDEX(I58:M58,$F$4)} -> 1500 | G58: $ 000s | J58: 1500 | K58: 1500 | L58: 1500
E59: 46387 | F59: {=INDEX(I59:M59,$F$4)} -> 1000 | G59: $ 000s | J59: 1000 | K59: 1000 | L59: 1000
E60: 46752 | F60: {=INDEX(I60:M60,$F$4)} -> 500 | G60: $ 000s | J60: 500 | K60: 500 | L60: 500
E61: 47118 | F61: {=INDEX(I61:M61,$F$4)} -> 1000 | G61: $ 000s | J61: 1000 | K61: 1000 | L61: 1000
E62: 47483 | F62: {=INDEX(I62:M62,$F$4)} -> 1000 | G62: $ 000s | J62: 1000 | K62: 1000 | L62: 1000
E64: Non current asset - initial balance | F64: {=INDEX(I64:M64,$F$4)} -> 101067.8 | G64: $ 000s | J64: =Constr!$F$52 -> 101067.8 | K64: =Constr!$F$52 -> 101067.8 | L64: =Constr!$F$52 -> 101067.8 | N64: Linked to Constr!F52: capitalised project cost (hard cost + fees + interest during construction)
E65: Useful life of NCA at acquisition | F65: {=INDEX(I65:M65,$F$4)} -> 15 | G65: years | J65: 15 | K65: 15 | L65: 15
E67: Useful life -capex | F67: {=INDEX(I67:M67,$F$4)} -> 5 | G67: yrs | J67: 5 | K67: 5 | L67: 5
A70: SENIOR DEBT
E72: % of NCA financed with debt | F72: {=INDEX(I72:M72,$F$4)} -> 0.71391903 | G72: % | J72: 0.71391903 | K72: 0.54182425 | L72: 0.75 | N72: Solved per scenario with Goal Seek: Sculpt!F32 (debt drawn less debt sized) = 0 by changing the active scenario's cell
E74: Senior debt principal repayment profile selection | F74: {=INDEX(I74:M74,$F$4)} -> 4 | G74: switch | J74: 4 | K74: 4 | L74: 4
E77: All in annual senior debt interest rate | F77: {=INDEX(I77:M77,$F$4)} -> 0.065 | G77: % | J77: 0.065 | K77: 0.065 | L77: 0.065
E79: Day count convention | F79: {=INDEX(I79:M79,$F$4)} -> 360 | G79: days | J79: 360 | K79: 360 | L79: 360
A82: TAX
E84: Tax depreciation rate | F84: {=INDEX(I84:M84,$F$4)} -> 0.05 | G84: % TWDV | J84: 0.05 | K84: 0.05 | L84: 0.05
E86: Corporation tax rate | F86: {=INDEX(I86:M86,$F$4)} -> 0.3 | G86: % | J86: 0.3 | K86: 0.3 | L86: 0.3
A88: VALUATION
E90: Shareholders valuation date | F90: {=INDEX(I90:M90,$F$4)} -> 44561 | G90: date | J90: 44561 | K90: 44561 | L90: 44561
E91: Days in shareholder discount year | F91: {=INDEX(I91:M91,$F$4)} -> 365 | G91: days | J91: 365 | K91: 365 | L91: 365
E93: Shareholder required rate of return per annum | F93: {=INDEX(I93:M93,$F$4)} -> 0.2525 | G93: % p.a | J93: 0.2525 | K93: 0.2525 | L93: 0.2525
A96: MODEL CONSTANTS - DO NOT CHANGE
E98: Financial year end month number | F98: 12 | G98: month #
E99: No of periods in a year | F99: 4 | G99: periods
E100: First modelling column financial year number | F100: 2021 | G100: year #
E101: Model check tolerance level | F101: 0.001 | G101: tolerance
E102: Unit in thousand | F102: 1000 | G102: units
E103: Standard measure unit | F103: $ 000s | G103: SMU
A105: TIMELINE LABEL
E106: Pre-forecast period | F106: Pre-fcst | G106: label
E107: Financial close | F107: Fin close | G107: label
E108: Forecast period | F108: Forecast | G108: label
E109: Post-operations period | F109: Post-fcst | G109: label
A111: CONSTRUCTION AND FUNDING
E113: Construction period | F113: {=INDEX(I113:M113,$F$4)} -> 8 | G113: quarters | J113: 8 | K113: 8 | L113: 8
E115: Total construction cost (hard cost) | F115: {=INDEX(I115:M115,$F$4)} -> 94850 | G115: $ 000s | J115: 94850 | K115: 94850 | L115: 94850
E117: Construction spend profile (quarter number and share of cost)
E118: 1 | F118: {=INDEX(I118:M118,$F$4)} -> 0.05 | G118: % of cost | J118: 0.05 | K118: 0.05 | L118: 0.05
E119: 2 | F119: {=INDEX(I119:M119,$F$4)} -> 0.1 | G119: % of cost | J119: 0.1 | K119: 0.1 | L119: 0.1
E120: 3 | F120: {=INDEX(I120:M120,$F$4)} -> 0.15 | G120: % of cost | J120: 0.15 | K120: 0.15 | L120: 0.15
E121: 4 | F121: {=INDEX(I121:M121,$F$4)} -> 0.2 | G121: % of cost | J121: 0.2 | K121: 0.2 | L121: 0.2
E122: 5 | F122: {=INDEX(I122:M122,$F$4)} -> 0.2 | G122: % of cost | J122: 0.2 | K122: 0.2 | L122: 0.2
E123: 6 | F123: {=INDEX(I123:M123,$F$4)} -> 0.15 | G123: % of cost | J123: 0.15 | K123: 0.15 | L123: 0.15
E124: 7 | F124: {=INDEX(I124:M124,$F$4)} -> 0.1 | G124: % of cost | J124: 0.1 | K124: 0.1 | L124: 0.1
E125: 8 | F125: {=INDEX(I125:M125,$F$4)} -> 0.05 | G125: % of cost | J125: 0.05 | K125: 0.05 | L125: 0.05
E127: Upfront fee (% of facility) | F127: {=INDEX(I127:M127,$F$4)} -> 0.02 | G127: % | J127: 0.02 | K127: 0.02 | L127: 0.02
E129: Commitment fee (% p.a. on undrawn facility) | F129: {=INDEX(I129:M129,$F$4)} -> 0.0075 | G129: % p.a | J129: 0.0075 | K129: 0.0075 | L129: 0.0075
E131: Senior debt facility (commitment) | F131: {=INDEX(I131:M131,$F$4)} -> 72155 | G131: $ 000s | J131: 72155 | K131: 53911 | L131: 76053
E133: Drawdown method (1 pro-rata, 2 equity first) | F133: {=INDEX(I133:M133,$F$4)} -> 1 | G133: switch | J133: 1 | K133: 1 | L133: 1
E135: Equity commitment (used by method 2) | F135: {=INDEX(I135:M135,$F$4)} -> 40000 | G135: $ 000s | J135: 40000 | K135: 40000 | L135: 40000
A137: SENIOR DEBT SIZING
E139: Senior debt tenor | F139: {=INDEX(I139:M139,$F$4)} -> 40 | G139: quarters | J139: 40 | K139: 40 | L139: 40
E140: Target DSCR for sculpting | F140: {=INDEX(I140:M140,$F$4)} -> 2.25 | G140: x | J140: 2.25 | K140: 2.25 | L140: 2.25
E141: Maximum gearing (debt / total uses) | F141: {=INDEX(I141:M141,$F$4)} -> 0.75 | G141: % | J141: 0.75 | K141: 0.75 | L141: 0.75
E143: DSRA cover (periods of debt service) | F143: {=INDEX(I143:M143,$F$4)} -> 2 | G143: periods | J143: 2 | K143: 2 | L143: 2
A145: SHAREHOLDER LOAN
E147: Shareholder loan share of sponsor funding | F147: {=INDEX(I147:M147,$F$4)} -> 0.6 | G147: % | J147: 0.6 | K147: 0.6 | L147: 0.6
E148: Shareholder loan interest rate | F148: {=INDEX(I148:M148,$F$4)} -> 0.1 | G148: % p.a | J148: 0.1 | K148: 0.1 | L148: 0.1

Sheet InpS
A1: =RIGHT(CELL("filename", A1), LEN(CELL("filename", A1)) - SEARCH("]", CELL("filename", A1)))
E2: Model period ending | J2: 44469 | K2: 44561 | L2: 44651 | M2: 44742 | N2: 44834 | O2: 44926 | P2: 45016 | Q2: 45107 | R2: 45199 | S2: 45291 | T2: 45382 | U2: 45473 | V2: 45565 | W2: 45657 | X2: 45747 | Y2: 45838 | Z2: 45930 | AA2: 46022 | AB2: 46112 | AC2: 46203 | AD2: 46295 | AE2: 46387 | AF2: 46477 | AG2: 46568 | AH2: 46660 | AI2: 46752 | AJ2: 46843 | AK2: 46934 | AL2: 47026 | AM2: 47118 | AN2: 47208 | AO2: 47299 | AP2: 47391 | AQ2: 47483 | AR2: 47573 | AS2: 47664 | AT2: 47756 | AU2: 47848 | AV2: 47938 | AW2: 48029 | AX2: 48121 | AY2: 48213 | AZ2: 48304 | BA2: 48395 | BB2: 48487 | BC2: 48579 | BD2: 48669 | BE2: 48760 | BF2: 48852 | BG2: 48944 | BH2: 49034 | BI2: 49125 | BJ2: 49217 | BK2: 49309 | BL2: 49399 | BM2: 49490 | BN2: 49582 | BO2: 49674 | BP2: 49765 | BQ2: 49856 | BR2: 49948 | BS2: 50040 | BT2: 50130 | BU2: 50221 | BV2: 50313 | BW2: 50405 | BX2: 50495 | BY2: 50586 | BZ2: 50678 | CA2: 50770 | CB2: 50860 | CC2: 50951 | CD2: 51043 | CE2: 51135 | CF2: 51226 | CG2: 51317 | CH2: 51409 | CI2: 51501 | CJ2: 51591 | CK2: 51682 | CL2: 51774 | CM2: 51866 | CN2: 51956 | CO2: 52047
E3: Timeline label | J3: Pre-fcst | K3: Fin close | L3: Forecast | M3: Forecast | N3: Forecast | O3: Forecast | P3: Forecast | Q3: Forecast | R3: Forecast | S3: Forecast | T3: Forecast | U3: Forecast | V3: Forecast | W3: Forecast | X3: Forecast | Y3: Forecast | Z3: Forecast | AA3: Forecast | AB3: Forecast | AC3: Forecast | AD3: Forecast | AE3: Forecast | AF3: Forecast | AG3: Forecast | AH3: Forecast | AI3: Forecast | AJ3: Forecast | AK3: Forecast | AL3: Forecast | AM3: Forecast | AN3: Forecast | AO3: Forecast | AP3: Forecast | AQ3: Forecast | AR3: Forecast | AS3: Forecast | AT3: Forecast | AU3: Forecast | AV3: Forecast | AW3: Forecast | AX3: Forecast | AY3: Forecast | AZ3: Forecast | BA3: Forecast | BB3: Forecast | BC3: Forecast | BD3: Forecast | BE3: Forecast | BF3: Forecast | BG3: Forecast | BH3: Forecast | BI3: Forecast | BJ3: Forecast | BK3: Forecast | BL3: Forecast | BM3: Forecast | BN3: Forecast | BO3: Forecast | BP3: Forecast | BQ3: Forecast | BR3: Forecast | BS3: Forecast | BT3: Forecast | BU3: Forecast | BV3: Forecast | BW3: Forecast | BX3: Forecast | BY3: Forecast | BZ3: Forecast | CA3: Forecast | CB3: Forecast | CC3: Forecast | CD3: Forecast | CE3: Forecast | CF3: Forecast | CG3: Forecast | CH3: Forecast | CI3: Forecast | CJ3: Forecast | CK3: Forecast | CL3: Forecast | CM3: Forecast | CN3: Post-fcst | CO3: Post-fcst
E4: Financial year ending | J4: 2021 | K4: 2021 | L4: 2022 | M4: 2022 | N4: 2022 | O4: 2022 | P4: 2023 | Q4: 2023 | R4: 2023 | S4: 2023 | T4: 2024 | U4: 2024 | V4: 2024 | W4: 2024 | X4: 2025 | Y4: 2025 | Z4: 2025 | AA4: 2025 | AB4: 2026 | AC4: 2026 | AD4: 2026 | AE4: 2026 | AF4: 2027 | AG4: 2027 | AH4: 2027 | AI4: 2027 | AJ4: 2028 | AK4: 2028 | AL4: 2028 | AM4: 2028 | AN4: 2029 | AO4: 2029 | AP4: 2029 | AQ4: 2029 | AR4: 2030 | AS4: 2030 | AT4: 2030 | AU4: 2030 | AV4: 2031 | AW4: 2031 | AX4: 2031 | AY4: 2031 | AZ4: 2032 | BA4: 2032 | BB4: 2032 | BC4: 2032 | BD4: 2033 | BE4: 2033 | BF4: 2033 | BG4: 2033 | BH4: 2034 | BI4: 2034 | BJ4: 2034 | BK4: 2034 | BL4: 2035 | BM4: 2035 | BN4: 2035 | BO4: 2035 | BP4: 2036 | BQ4: 2036 | BR4: 2036 | BS4: 2036 | BT4: 2037 | BU4: 2037 | BV4: 2037 | BW4: 2037 | BX4: 2038 | BY4: 2038 | BZ4: 2038 | CA4: 2038 | CB4: 2039 | CC4: 2039 | CD4: 2039 | CE4: 2039 | CF4: 2040 | CG4: 2040 | CH4: 2040 | CI4: 2040 | CJ4: 2041 | CK4: 2041 | CL4: 2041 | CM4: 2041 | CN4: 2042 | CO4: 2042
E5: Model column counter | F5: Constant | G5: Unit | H5: Total | J5: 1 | K5: 2 | L5: 3 | M5: 4 | N5: 5 | O5: 6 | P5: 7 | Q5: 8 | R5: 9 | S5: 10 | T5: 11 | U5: 12 | V5: 13 | W5: 14 | X5: 15 | Y5: 16 | Z5: 17 | AA5: 18 | AB5: 19 | AC5: 20 | AD5: 21 | AE5: 22 | AF5: 23 | AG5: 24 | AH5: 25 | AI5: 26 | AJ5: 27 | AK5: 28 | AL5: 29 | AM5: 30 | AN5: 31 | AO5: 32 | AP5: 33 | AQ5: 34 | AR5: 35 | AS5: 36 | AT5: 37 | AU5: 38 | AV5: 39 | AW5: 40 | AX5: 41 | AY5: 42 | AZ5: 43 | BA5: 44 | BB5: 45 | BC5: 46 | BD5: 47 | BE5: 48 | BF5: 49 | BG5: 50 | BH5: 51 | BI5: 52 | BJ5: 53 | BK5: 54 | BL5: 55 | BM5: 56 | BN5: 57 | BO5: 58 | BP5: 59 | BQ5: 60 | BR5: 61 | BS5: 62 | BT5: 63 | BU5: 64 | BV5: 65 | BW5: 66 | BX5: 67 | BY5: 68 | BZ5: 69 | CA5: 70 | CB5: 71 | CC5: 72 | CD5: 73 | CE5: 74 | CF5: 75 | CG5: 76 | CH5: 77 | CI5: 78 | CJ5: 79 | CK5: 80 | CL5: 81 | CM5: 82 | CN5: 83 | CO5: 84
A7: OPERATING REVENUE
E8: Trains - domestic | G8: trains | H8: =SUM(J8:CO8) -> 2520 | J8: 30 | K8: 30 | L8: 30 | M8: 30 | N8: 30 | O8: 30 | P8: 30 | Q8: 30 | R8: 30 | S8: 30 | T8: 30 | U8: 30 | V8: 30 | W8: 30 | X8: 30 | Y8: 30 | Z8: 30 | AA8: 30 | AB8: 30 | AC8: 30 | AD8: 30 | AE8: 30 | AF8: 30 | AG8: 30 | AH8: 30 | AI8: 30 | AJ8: 30 | AK8: 30 | AL8: 30 | AM8: 30 | AN8: 30 | AO8: 30 | AP8: 30 | AQ8: 30 | AR8: 30 | AS8: 30 | AT8: 30 | AU8: 30 | AV8: 30 | AW8: 30 | AX8: 30 | AY8: 30 | AZ8: 30 | BA8: 30 | BB8: 30 | BC8: 30 | BD8: 30 | BE8: 30 | BF8: 30 | BG8: 30 | BH8: 30 | BI8: 30 | BJ8: 30 | BK8: 30 | BL8: 30 | BM8: 30 | BN8: 30 | BO8: 30 | BP8: 30 | BQ8: 30 | BR8: 30 | BS8: 30 | BT8: 30 | BU8: 30 | BV8: 30 | BW8: 30 | BX8: 30 | BY8: 30 | BZ8: 30 | CA8: 30 | CB8: 30 | CC8: 30 | CD8: 30 | CE8: 30 | CF8: 30 | CG8: 30 | CH8: 30 | CI8: 30 | CJ8: 30 | CK8: 30 | CL8: 30 | CM8: 30 | CN8: 30 | CO8: 30
E9: Trains - international | G9: trains | H9: =SUM(J9:CO9) -> 1326 | J9: 10 | K9: 12 | L9: 12 | M9: 14 | N9: 14 | O9: 16 | P9: 16 | Q9: 16 | R9: 16 | S9: 16 | T9: 16 | U9: 16 | V9: 16 | W9: 16 | X9: 16 | Y9: 16 | Z9: 16 | AA9: 16 | AB9: 16 | AC9: 16 | AD9: 16 | AE9: 16 | AF9: 16 | AG9: 16 | AH9: 16 | AI9: 16 | AJ9: 16 | AK9: 16 | AL9: 16 | AM9: 16 | AN9: 16 | AO9: 16 | AP9: 16 | AQ9: 16 | AR9: 16 | AS9: 16 | AT9: 16 | AU9: 16 | AV9: 16 | AW9: 16 | AX9: 16 | AY9: 16 | AZ9: 16 | BA9: 16 | BB9: 16 | BC9: 16 | BD9: 16 | BE9: 16 | BF9: 16 | BG9: 16 | BH9: 16 | BI9: 16 | BJ9: 16 | BK9: 16 | BL9: 16 | BM9: 16 | BN9: 16 | BO9: 16 | BP9: 16 | BQ9: 16 | BR9: 16 | BS9: 16 | BT9: 16 | BU9: 16 | BV9: 16 | BW9: 16 | BX9: 16 | BY9: 16 | BZ9: 16 | CA9: 16 | CB9: 16 | CC9: 16 | CD9: 16 | CE9: 16 | CF9: 16 | CG9: 16 | CH9: 16 | CI9: 16 | CJ9: 16 | CK9: 16 | CL9: 16 | CM9: 16 | CN9: 16 | CO9: 16
E11: Arrivals per train - domestic | G11: arrivals / train | J11: 370 | K11: 350 | L11: 370 | M11: 350 | N11: 370 | O11: 350 | P11: 370 | Q11: 350 | R11: 370 | S11: 350 | T11: 370 | U11: 350 | V11: 370 | W11: 350 | X11: 370 | Y11: 350 | Z11: 370 | AA11: 350 | AB11: 370 | AC11: 350 | AD11: 370 | AE11: 350 | AF11: 370 | AG11: 350 | AH11: 370 | AI11: 350 | AJ11: 370 | AK11: 350 | AL11: 370 | AM11: 350 | AN11: 370 | AO11: 350 | AP11: 370 | AQ11: 350 | AR11: 370 | AS11: 350 | AT11: 370 | AU11: 350 | AV11: 370 | AW11: 350 | AX11: 370 | AY11: 350 | AZ11: 370 | BA11: 350 | BB11: 370 | BC11: 350 | BD11: 370 | BE11: 350 | BF11: 370 | BG11: 350 | BH11: 350 | BI11: 370 | BJ11: 350 | BK11: 370 | BL11: 350 | BM11: 370 | BN11: 350 | BO11: 370 | BP11: 350 | BQ11: 350 | BR11: 370 | BS11: 350 | BT11: 370 | BU11: 350 | BV11: 370 | BW11: 370 | BX11: 370 | BY11: 370 | BZ11: 370 | CA11: 370 | CB11: 370 | CC11: 370 | CD11: 370 | CE11: 370 | CF11: 370 | CG11: 370 | CH11: 370 | CI11: 370 | CJ11: 370 | CK11: 370 | CL11: 370 | CM11: 370 | CN11: 370 | CO11: 370
E12: Arrivals per train - international | G12: arrivals / train | J12: 34 | K12: 34 | L12: 34 | M12: 44 | N12: 44 | O12: 44 | P12: 44 | Q12: 44 | R12: 44 | S12: 44 | T12: 44 | U12: 44 | V12: 44 | W12: 44 | X12: 44 | Y12: 44 | Z12: 44 | AA12: 44 | AB12: 44 | AC12: 44 | AD12: 44 | AE12: 44 | AF12: 44 | AG12: 44 | AH12: 44 | AI12: 44 | AJ12: 44 | AK12: 44 | AL12: 44 | AM12: 44 | AN12: 44 | AO12: 44 | AP12: 44 | AQ12: 44 | AR12: 44 | AS12: 44 | AT12: 44 | AU12: 44 | AV12: 44 | AW12: 44 | AX12: 44 | AY12: 44 | AZ12: 44 | BA12: 44 | BB12: 44 | BC12: 44 | BD12: 44 | BE12: 44 | BF12: 44 | BG12: 44 | BH12: 44 | BI12: 44 | BJ12: 44 | BK12: 44 | BL12: 44 | BM12: 44 | BN12: 44 | BO12: 44 | BP12: 44 | BQ12: 44 | BR12: 44 | BS12: 44 | BT12: 44 | BU12: 44 | BV12: 44 | BW12: 44 | BX12: 44 | BY12: 44 | BZ12: 44 | CA12: 44 | CB12: 44 | CC12: 44 | CD12: 44 | CE12: 44 | CF12: 44 | CG12: 44 | CH12: 44 | CI12: 44 | CJ12: 44 | CK12: 44 | CL12: 44 | CM12: 44 | CN12: 44 | CO12: 44
E14: Occupancy - domestic | G14: % | J14: 0.55 | K14: 0.55 | L14: 0.55 | M14: 0.55 | N14: 0.55 | O14: 0.55 | P14: 0.55 | Q14: 0.55 | R14: 0.55 | S14: 0.55 | T14: 0.56 | U14: 0.56 | V14: 0.56 | W14: 0.56 | X14: 0.56 | Y14: 0.56 | Z14: 0.56 | AA14: 0.56 | AB14: 0.56 | AC14: 0.56 | AD14: 0.58 | AE14: 0.58 | AF14: 0.58 | AG14: 0.58 | AH14: 0.58 | AI14: 0.58 | AJ14: 0.58 | AK14: 0.58 | AL14: 0.58 | AM14: 0.6 | AN14: 0.6 | AO14: 0.6 | AP14: 0.6 | AQ14: 0.6 | AR14: 0.6 | AS14: 0.6 | AT14: 0.6 | AU14: 0.6 | AV14: 0.6 | AW14: 0.6 | AX14: 0.62 | AY14: 0.62 | AZ14: 0.62 | BA14: 0.62 | BB14: 0.62 | BC14: 0.62 | BD14: 0.62 | BE14: 0.62 | BF14: 0.62 | BG14: 0.62 | BH14: 0.62 | BI14: 0.62 | BJ14: 0.62 | BK14: 0.62 | BL14: 0.62 | BM14: 0.62 | BN14: 0.62 | BO14: 0.62 | BP14: 0.62 | BQ14: 0.62 | BR14: 0.62 | BS14: 0.62 | BT14: 0.62 | BU14: 0.62 | BV14: 0.62 | BW14: 0.62 | BX14: 0.62 | BY14: 0.62 | BZ14: 0.62 | CA14: 0.62 | CB14: 0.62 | CC14: 0.62 | CD14: 0.62 | CE14: 0.62 | CF14: 0.62 | CG14: 0.62 | CH14: 0.62 | CI14: 0.62 | CJ14: 0.62 | CK14: 0.62 | CL14: 0.62 | CM14: 0.62 | CN14: 0.62 | CO14: 0.62
E15: Occupancy - international | G15: % | J15: 0.45 | K15: 0.45 | L15: 0.45 | M15: 0.45 | N15: 0.45 | O15: 0.45 | P15: 0.45 | Q15: 0.45 | R15: 0.45 | S15: 0.45 | T15: 0.45 | U15: 0.45 | V15: 0.45 | W15: 0.45 | X15: 0.45 | Y15: 0.45 | Z15: 0.45 | AA15: 0.45 | AB15: 0.45 | AC15: 0.45 | AD15: 0.45 | AE15: 0.45 | AF15: 0.45 | AG15: 0.45 | AH15: 0.45 | AI15: 0.45 | AJ15: 0.45 | AK15: 0.45 | AL15: 0.45 | AM15: 0.45 | AN15: 0.45 | AO15: 0.45 | AP15: 0.45 | AQ15: 0.45 | AR15: 0.45 | AS15: 0.45 | AT15: 0.45 | AU15: 0.45 | AV15: 0.45 | AW15: 0.45 | AX15: 0.55 | AY15: 0.55 | AZ15: 0.55 | BA15: 0.55 | BB15: 0.55 | BC15: 0.55 | BD15: 0.55 | BE15: 0.55 | BF15: 0.55 | BG15: 0.55 | BH15: 0.55 | BI15: 0.55 | BJ15: 0.55 | BK15: 0.55 | BL15: 0.55 | BM15: 0.55 | BN15: 0.55 | BO15: 0.55 | BP15: 0.55 | BQ15: 0.55 | BR15: 0.55 | BS15: 0.55 | BT15: 0.55 | BU15: 0.55 | BV15: 0.55 | BW15: 0.55 | BX15: 0.55 | BY15: 0.55 | BZ15: 0.55 | CA15: 0.55 | CB15: 0.55 | CC15: 0.55 | CD15: 0.55 | CE15: 0.55 | CF15: 0.55 | CG15: 0.55 | CH15: 0.55 | CI15: 0.55 | CJ15: 0.55 | CK15: 0.55 | CL15: 0.55 | CM15: 0.55 | CN15: 0.55 | CO15: 0.55
A17: SENIOR DEBT
E18: Senior debt profile 1 - 7.5 years | G18: % | H18: =SUM(J18:CO18) -> 1 | O18: 0.033333333 | P18: 0.033333333 | Q18: 0.033333333 | R18: 0.033333333 | S18: 0.033333333 | T18: 0.033333333 | U18: 0.033333333 | V18: 0.033333333 | W18: 0.033333333 | X18: 0.033333333 | Y18: 0.033333333 | Z18: 0.033333333 | AA18: 0.033333333 | AB18: 0.033333333 | AC18: 0.033333333 | AD18: 0.033333333 | AE18: 0.033333333 | AF18: 0.033333333 | AG18: 0.033333333 | AH18: 0.033333333 | AI18: 0.033333333 | AJ18: 0.033333333 | AK18: 0.033333333 | AL18: 0.033333333 | AM18: 0.033333333 | AN18: 0.033333333 | AO18: 0.033333333 | AP18: 0.033333333 | AQ18: 0.033333333 | AR18: 0.033333333
E19: Senior debt profile 2 - 10 years | G19: % | H19: =SUM(J19:CO19) -> 1 | O19: 0.025 | P19: 0.025 | Q19: 0.025 | R19: 0.025 | S19: 0.025 | T19: 0.025 | U19: 0.025 | V19: 0.025 | W19: 0.025 | X19: 0.025 | Y19: 0.025 | Z19: 0.025 | AA19: 0.025 | AB19: 0.025 | AC19: 0.025 | AD19: 0.025 | AE19: 0.025 | AF19: 0.025 | AG19: 0.025 | AH19: 0.025 | AI19: 0.025 | AJ19: 0.025 | AK19: 0.025 | AL19: 0.025 | AM19: 0.025 | AN19: 0.025 | AO19: 0.025 | AP19: 0.025 | AQ19: 0.025 | AR19: 0.025 | AS19: 0.025 | AT19: 0.025 | AU19: 0.025 | AV19: 0.025 | AW19: 0.025 | AX19: 0.025 | AY19: 0.025 | AZ19: 0.025 | BA19: 0.025 | BB19: 0.025
E20: Senior debt profile 3 - 15 years | G20: % | H20: =SUM(J20:CO20) -> 1 | O20: 0.016666667 | P20: 0.016666667 | Q20: 0.016666667 | R20: 0.016666667 | S20: 0.016666667 | T20: 0.016666667 | U20: 0.016666667 | V20: 0.016666667 | W20: 0.016666667 | X20: 0.016666667 | Y20: 0.016666667 | Z20: 0.016666667 | AA20: 0.016666667 | AB20: 0.016666667 | AC20: 0.016666667 | AD20: 0.016666667 | AE20: 0.016666667 | AF20: 0.016666667 | AG20: 0.016666667 | AH20: 0.016666667 | AI20: 0.016666667 | AJ20: 0.016666667 | AK20: 0.016666667 | AL20: 0.016666667 | AM20: 0.016666667 | AN20: 0.016666667 | AO20: 0.016666667 | AP20: 0.016666667 | AQ20: 0.016666667 | AR20: 0.016666667 | AS20: 0.016666667 | AT20: 0.016666667 | AU20: 0.016666667 | AV20: 0.016666667 | AW20: 0.016666667 | AX20: 0.016666667 | AY20: 0.016666667 | AZ20: 0.016666667 | BA20: 0.016666667 | BB20: 0.016666667 | BC20: 0.016666667 | BD20: 0.016666667 | BE20: 0.016666667 | BF20: 0.016666667 | BG20: 0.016666667 | BH20: 0.016666667 | BI20: 0.016666667 | BJ20: 0.016666667 | BK20: 0.016666667 | BL20: 0.016666667 | BM20: 0.016666667 | BN20: 0.016666667 | BO20: 0.016666667 | BP20: 0.016666667 | BQ20: 0.016666667 | BR20: 0.016666667 | BS20: 0.016666667 | BT20: 0.016666667 | BU20: 0.016666667 | BV20: 0.016666667
A21: ADDITIONAL FUNDING (after financial close)
E22: Senior debt - additional drawdown | G22: $ 000s | H22: =SUM(J22:CO22) -> 0 | J22: 0 | K22: 0 | L22: 0 | M22: 0 | N22: 0 | O22: 0 | P22: 0 | Q22: 0 | R22: 0 | S22: 0 | T22: 0 | U22: 0 | V22: 0 | W22: 0 | X22: 0 | Y22: 0 | Z22: 0 | AA22: 0 | AB22: 0 | AC22: 0 | AD22: 0 | AE22: 0 | AF22: 0 | AG22: 0 | AH22: 0 | AI22: 0 | AJ22: 0 | AK22: 0 | AL22: 0 | AM22: 0 | AN22: 0 | AO22: 0 | AP22: 0 | AQ22: 0 | AR22: 0 | AS22: 0 | AT22: 0 | AU22: 0 | AV22: 0 | AW22: 0 | AX22: 0 | AY22: 0 | AZ22: 0 | BA22: 0 | BB22: 0 | BC22: 0 | BD22: 0 | BE22: 0 | BF22: 0 | BG22: 0 | BH22: 0 | BI22: 0 | BJ22: 0 | BK22: 0 | BL22: 0 | BM22: 0 | BN22: 0 | BO22: 0 | BP22: 0 | BQ22: 0 | BR22: 0 | BS22: 0 | BT22: 0 | BU22: 0 | BV22: 0 | BW22: 0 | BX22: 0 | BY22: 0 | BZ22: 0 | CA22: 0 | CB22: 0 | CC22: 0 | CD22: 0 | CE22: 0 | CF22: 0 | CG22: 0 | CH22: 0 | CI22: 0 | CJ22: 0 | CK22: 0 | CL22: 0 | CM22: 0 | CN22: 0 | CO22: 0
E23: Share capital - additional injection | G23: $ 000s | H23: =SUM(J23:CO23) -> 0 | J23: 0 | K23: 0 | L23: 0 | M23: 0 | N23: 0 | O23: 0 | P23: 0 | Q23: 0 | R23: 0 | S23: 0 | T23: 0 | U23: 0 | V23: 0 | W23: 0 | X23: 0 | Y23: 0 | Z23: 0 | AA23: 0 | AB23: 0 | AC23: 0 | AD23: 0 | AE23: 0 | AF23: 0 | AG23: 0 | AH23: 0 | AI23: 0 | AJ23: 0 | AK23: 0 | AL23: 0 | AM23: 0 | AN23: 0 | AO23: 0 | AP23: 0 | AQ23: 0 | AR23: 0 | AS23: 0 | AT23: 0 | AU23: 0 | AV23: 0 | AW23: 0 | AX23: 0 | AY23: 0 | AZ23: 0 | BA23: 0 | BB23: 0 | BC23: 0 | BD23: 0 | BE23: 0 | BF23: 0 | BG23: 0 | BH23: 0 | BI23: 0 | BJ23: 0 | BK23: 0 | BL23: 0 | BM23: 0 | BN23: 0 | BO23: 0 | BP23: 0 | BQ23: 0 | BR23: 0 | BS23: 0 | BT23: 0 | BU23: 0 | BV23: 0 | BW23: 0 | BX23: 0 | BY23: 0 | BZ23: 0 | CA23: 0 | CB23: 0 | CC23: 0 | CD23: 0 | CE23: 0 | CF23: 0 | CG23: 0 | CH23: 0 | CI23: 0 | CJ23: 0 | CK23: 0 | CL23: 0 | CM23: 0 | CN23: 0 | CO23: 0

Sheet Time
A1: =RIGHT(CELL("filename", A1), LEN(CELL("filename", A1)) - SEARCH("]", CELL("filename", A1)))
E2: =Time!E$25 -> Model period ending | J2: =Time!J$25 -> 44469 | K2: =Time!K$25 -> 44561 | L2: =Time!L$25 -> 44651 | M2: =Time!M$25 -> 44742 | N2: =Time!N$25 -> 44834 | O2: =Time!O$25 -> 44926 | P2: =Time!P$25 -> 45016 | Q2: =Time!Q$25 -> 45107 | ... CO2: =Time!CO$25 -> 52047
E3: =Time!E$111 -> Timeline label | J3: =Time!J$111 -> Pre-fcst | K3: =Time!K$111 -> Fin close | L3: =Time!L$111 -> Forecast | M3: =Time!M$111 -> Forecast | N3: =Time!N$111 -> Forecast | O3: =Time!O$111 -> Forecast | P3: =Time!P$111 -> Forecast | Q3: =Time!Q$111 -> Forecast | ... CO3: =Time!CO$111 -> Post-fcst
E4: =Time!E$37 -> Financial year ending | J4: =Time!J$37 -> 2021 | K4: =Time!K$37 -> 2021 | L4: =Time!L$37 -> 2022 | M4: =Time!M$37 -> 2022 | N4: =Time!N$37 -> 2022 | O4: =Time!O$37 -> 2022 | P4: =Time!P$37 -> 2023 | Q4: =Time!Q$37 -> 2023 | ... CO4: =Time!CO$37 -> 2042
E5: =Time!E$10 -> Model column counter | F5: Constant | G5: Unit | H5: Total | J5: =Time!J$10 -> 1 | K5: =Time!K$10 -> 2 | L5: =Time!L$10 -> 3 | M5: =Time!M$10 -> 4 | N5: =Time!N$10 -> 5 | O5: =Time!O$10 -> 6 | P5: =Time!P$10 -> 7 | Q5: =Time!Q$10 -> 8 | ... CO5: =Time!CO$10 -> 84
A7: TIME RULER
B9: First model column flag
E10: Model column counter | G10: counter | J10: =I10 + 1 -> 1 | K10: =J10 + 1 -> 2 | L10: =K10 + 1 -> 3 | M10: =L10 + 1 -> 4 | N10: =M10 + 1 -> 5 | O10: =N10 + 1 -> 6 | P10: =O10 + 1 -> 7 | Q10: =P10 + 1 -> 8 | ... CO10: =CN10 + 1 -> 84
E11: Model column total | F11: =MAX(J10:CO10) -> 84 | G11: columns
E13: =E$10 -> Model column counter | F13: =F$10 -> 0 | G13: =G$10 -> counter | H13: =H$10 -> 0 | I13: =I$10 -> 0 | J13: =J$10 -> 1 | K13: =K$10 -> 2 | L13: =L$10 -> 3 | ... CO13: =CO$10 -> 84
E14: First model column flag | G14: flag | H14: =SUM(J14:CO14) -> 1 | J14: =IF(J13 = 1, 1, 0) -> 1 | K14: =IF(K13 = 1, 1, 0) -> 0 | L14: =IF(L13 = 1, 1, 0) -> 0 | M14: =IF(M13 = 1, 1, 0) -> 0 | N14: =IF(N13 = 1, 1, 0) -> 0 | O14: =IF(O13 = 1, 1, 0) -> 0 | P14: =IF(P13 = 1, 1, 0) -> 0 | Q14: =IF(Q13 = 1, 1, 0) -> 0 | ... CO14: =IF(CO13 = 1, 1, 0) -> 0
B16: Model period beginning
E17: =InpC!E$9 -> First date of time rulers | F17: =InpC!F$9 -> 44378 | G17: =InpC!G$9 -> date
E18: =InpC!E$12 -> Months per model period | F18: =InpC!F$12 -> 3 | G18: =InpC!G$12 -> months
E19: =E$14 -> First model column flag | F19: =F$14 -> 0 | G19: =G$14 -> flag | H19: =H$14 -> 1 | I19: =I$14 -> 0 | J19: =J$14 -> 1 | K19: =K$14 -> 0 | L19: =L$14 -> 0 | ... CO19: =CO$14 -> 0
E20: Model period beginning | G20: date | J20: =IF(J19 = 1, $F17, DATE(YEAR(I20), MONTH(I20) + $F18, DAY(1))) -> 44378 | K20: =IF(K19 = 1, $F17, DATE(YEAR(J20), MONTH(J20) + $F18, DAY(1))) -> 44470 | L20: =IF(L19 = 1, $F17, DATE(YEAR(K20), MONTH(K20) + $F18, DAY(1))) -> 44562 | M20: =IF(M19 = 1, $F17, DATE(YEAR(L20), MONTH(L20) + $F18, DAY(1))) -> 44652 | N20: =IF(N19 = 1, $F17, DATE(YEAR(M20), MONTH(M20) + $F18, DAY(1))) -> 44743 | O20: =IF(O19 = 1, $F17, DATE(YEAR(N20), MONTH(N20) + $F18, DAY(1))) -> 44835 | P20: =IF(P19 = 1, $F17, DATE(YEAR(O20), MONTH(O20) + $F18, DAY(1))) -> 44927 | Q20: =IF(Q19 = 1, $F17, DATE(YEAR(P20), MONTH(P20) + $F18, DAY(1))) -> 45017 | ... CO20: =IF(CO19 = 1, $F17, DATE(YEAR(CN20), MONTH(CN20) + $F18, DAY(1))) -> 51957
B22: Model period ending
E23: =InpC!E$12 -> Months per model period | F23: =InpC!F$12 -> 3 | G23: =InpC!G$12 -> months
E24: =E$20 -> Model period beginning | F24: =F$20 -> 0 | G24: =G$20 -> date | H24: =H$20 -> 0 | I24: =I$20 -> 0 | J24: =J$20 -> 44378 | K24: =K$20 -> 44470 | L24: =L$20 -> 44562 | ... CO24: =CO$20 -> 51957
E25: Model period ending | G25: date | J25: =DATE(YEAR(J24), MONTH(J24) + $F23, DAY(J24) -1) -> 44469 | K25: =DATE(YEAR(K24), MONTH(K24) + $F23, DAY(K24) -1) -> 44561 | L25: =DATE(YEAR(L24), MONTH(L24) + $F23, DAY(L24) -1) -> 44651 | M25: =DATE(YEAR(M24), MONTH(M24) + $F23, DAY(M24) -1) -> 44742 | N25: =DATE(YEAR(N24), MONTH(N24) + $F23, DAY(N24) -1) -> 44834 | O25: =DATE(YEAR(O24), MONTH(O24) + $F23, DAY(O24) -1) -> 44926 | P25: =DATE(YEAR(P24), MONTH(P24) + $F23, DAY(P24) -1) -> 45016 | Q25: =DATE(YEAR(Q24), MONTH(Q24) + $F23, DAY(Q24) -1) -> 45107 | ... CO25: =DATE(YEAR(CO24), MONTH(CO24) + $F23, DAY(CO24) -1) -> 52047
B27: Days in model period
E28: =E$25 -> Model period ending | F28: =F$25 -> 0 | G28: =G$25 -> date | H28: =H$25 -> 0 | I28: =I$25 -> 0 | J28: =J$25 -> 44469 | K28: =K$25 -> 44561 | L28: =L$25 -> 44651 | ... CO28: =CO$25 -> 52047
D29: less | E29: =E$20 -> Model period beginning | F29: =F$20 -> 0 | G29: =G$20 -> date | H29: =H$20 -> 0 | I29: =I$20 -> 0 | J29: =J$20 -> 44378 | K29: =K$20 -> 44470 | L29: =L$20 -> 44562 | ... CO29: =CO$20 -> 51957
E30: Days in model period | G30: days | J30: =J28-J29+1 -> 92 | K30: =K28-K29+1 -> 92 | L30: =L28-L29+1 -> 90 | M30: =M28-M29+1 -> 91 | N30: =N28-N29+1 -> 92 | O30: =O28-O29+1 -> 92 | P30: =P28-P29+1 -> 90 | Q30: =Q28-Q29+1 -> 91 | ... CO30: =CO28-CO29+1 -> 91
B32: Financial year ending
E33: =InpC!E$100 -> First modelling column financial year number | F33: =InpC!F$100 -> 2021 | G33: =InpC!G$100 -> year #
E34: =InpC!E$98 -> Financial year end month number | F34: =InpC!F$98 -> 12 | G34: =InpC!G$98 -> month #
E35: =E$25 -> Model period ending | F35: =F$25 -> 0 | G35: =G$25 -> date | H35: =H$25 -> 0 | I35: =I$25 -> 0 | J35: =J$25 -> 44469 | K35: =K$25 -> 44561 | L35: =L$25 -> 44651 | ... CO35: =CO$25 -> 52047
E36: =E$14 -> First model column flag | F36: =F$14 -> 0 | G36: =G$14 -> flag | H36: =H$14 -> 1 | I36: =I$14 -> 0 | J36: =J$14 -> 1 | K36: =K$14 -> 0 | L36: =L$14 -> 0 | ... CO36: =CO$14 -> 0
E37: Financial year ending | G37: year # | J37: =IF(J36 = 1, $F33, IF(J35 > (DATE(I37, $F34 + 1, 1) - 1), I37 + 1, I37)) -> 2021 | K37: =IF(K36 = 1, $F33, IF(K35 > (DATE(J37, $F34 + 1, 1) - 1), J37 + 1, J37)) -> 2021 | L37: =IF(L36 = 1, $F33, IF(L35 > (DATE(K37, $F34 + 1, 1) - 1), K37 + 1, K37)) -> 2022 | M37: =IF(M36 = 1, $F33, IF(M35 > (DATE(L37, $F34 + 1, 1) - 1), L37 + 1, L37)) -> 2022 | N37: =IF(N36 = 1, $F33, IF(N35 > (DATE(M37, $F34 + 1, 1) - 1), M37 + 1, M37)) -> 2022 | O37: =IF(O36 = 1, $F33, IF(O35 > (DATE(N37, $F34 + 1, 1) - 1), N37 + 1, N37)) -> 2022 | P37: =IF(P36 = 1, $F33, IF(P35 > (DATE(O37, $F34 + 1, 1) - 1), O37 + 1, O37)) -> 2023 | Q37: =IF(Q36 = 1, $F33, IF(Q35 > (DATE(P37, $F34 + 1, 1) - 1), P37 + 1, P37)) -> 2023 | ... CO37: =IF(CO36 = 1, $F33, IF(CO35 > (DATE(CN37, $F34 + 1, 1) - 1), CN37 + 1, CN37)) -> 2042
A40: FLAGS
B42: Acquisition / initial balance date flag
E43: =InpC!E$10 -> Acquisition / initial balance date | F43: =InpC!F$10 -> 44561 | G43: =InpC!G$10 -> date
E44: =E$25 -> Model period ending | F44: =F$25 -> 0 | G44: =G$25 -> date | H44: =H$25 -> 0 | I44: =I$25 -> 0 | J44: =J$25 -> 44469 | K44: =K$25 -> 44561 | L44: =L$25 -> 44651 | ... CO44: =CO$25 -> 52047
E45: Acquisition / initial balance date flag | G45: flag | H45: =SUM(J45:CO45) -> 1 | J45: =IF(J44 = $F43, 1, 0) -> 0 | K45: =IF(K44 = $F43, 1, 0) -> 1 | L45: =IF(L44 = $F43, 1, 0) -> 0 | M45: =IF(M44 = $F43, 1, 0) -> 0 | N45: =IF(N44 = $F43, 1, 0) -> 0 | O45: =IF(O44 = $F43, 1, 0) -> 0 | P45: =IF(P44 = $F43, 1, 0) -> 0 | Q45: =IF(Q44 = $F43, 1, 0) -> 0 | ... CO45: =IF(CO44 = $F43, 1, 0) -> 0
B47: First forecast period flag
E48: =InpC!E$10 -> Acquisition / initial balance date | F48: =InpC!F$10 -> 44561 | G48: =InpC!G$10 -> date
E49: First forecast period start date | F49: =F48 + 1 -> 44562 | G49: date
E51: =E$49 -> First forecast period start date | F51: =F$49 -> 44562 | G51: =G$49 -> date
E52: =E$25 -> Model period ending | F52: =F$25 -> 0 | G52: =G$25 -> date | H52: =H$25 -> 0 | I52: =I$25 -> 0 | J52: =J$25 -> 44469 | K52: =K$25 -> 44561 | L52: =L$25 -> 44651 | ... CO52: =CO$25 -> 52047
E53: First forecast period flag | G53: flag | H53: =SUM(J53:CO53) -> 1 | J53: =IF(AND(I52 < $F51, J52 >= $F51), 1, 0) -> 0 | K53: =IF(AND(J52 < $F51, K52 >= $F51), 1, 0) -> 0 | L53: =IF(AND(K52 < $F51, L52 >= $F51), 1, 0) -> 1 | M53: =IF(AND(L52 < $F51, M52 >= $F51), 1, 0) -> 0 | N53: =IF(AND(M52 < $F51, N52 >= $F51), 1, 0) -> 0 | O53: =IF(AND(N52 < $F51, O52 >= $F51), 1, 0) -> 0 | P53: =IF(AND(O52 < $F51, P52 >= $F51), 1, 0) -> 0 | Q53: =IF(AND(P52 < $F51, Q52 >= $F51), 1, 0) -> 0 | ... CO53: =IF(AND(CN52 < $F51, CO52 >= $F51), 1, 0) -> 0
B55: Pre-forecast period flag
E56: =InpC!E$10 -> Acquisition / initial balance date | F56: =InpC!F$10 -> 44561 | G56: =InpC!G$10 -> date
E57: =E$25 -> Model period ending | F57: =F$25 -> 0 | G57: =G$25 -> date | H57: =H$25 -> 0 | I57: =I$25 -> 0 | J57: =J$25 -> 44469 | K57: =K$25 -> 44561 | L57: =L$25 -> 44651 | ... CO57: =CO$25 -> 52047
E58: Pre-forecast period flag | G58: flag | H58: =SUM(J58:CO58) -> 2 | J58: =IF(J57 <= $F56, 1, 0) -> 1 | K58: =IF(K57 <= $F56, 1, 0) -> 1 | L58: =IF(L57 <= $F56, 1, 0) -> 0 | M58: =IF(M57 <= $F56, 1, 0) -> 0 | N58: =IF(N57 <= $F56, 1, 0) -> 0 | O58: =IF(O57 <= $F56, 1, 0) -> 0 | P58: =IF(P57 <= $F56, 1, 0) -> 0 | Q58: =IF(Q57 <= $F56, 1, 0) -> 0 | ... CO58: =IF(CO57 <= $F56, 1, 0) -> 0
E59: Pre-forecast period total | F59: =SUM(J58:CO58) -> 2 | G59: columns
B61: Forecast period flag
E62: =InpC!E$10 -> Acquisition / initial balance date | F62: =InpC!F$10 -> 44561 | G62: =InpC!G$10 -> date
E63: =InpC!E$11 -> Length of forecast period | F63: =InpC!F$11 -> 20 | G63: =InpC!G$11 -> years
E64: Last forecast date | F64: =EOMONTH(F62,F63 * 12) -> 51866 | G64: date
E66: =InpC!E$10 -> Acquisition / initial balance date | F66: =InpC!F$10 -> 44561 | G66: =InpC!G$10 -> date
E67: =E$64 -> Last forecast date | F67: =F$64 -> 51866 | G67: =G$64 -> date
E68: =E$25 -> Model period ending | F68: =F$25 -> 0 | G68: =G$25 -> date | H68: =H$25 -> 0 | I68: =I$25 -> 0 | J68: =J$25 -> 44469 | K68: =K$25 -> 44561 | L68: =L$25 -> 44651 | ... CO68: =CO$25 -> 52047
E69: Forecast period flag | G69: flag | H69: =SUM(J69:CO69) -> 80 | J69: =IF(AND(J68 > $F66, J68 <= $F67), 1, 0) -> 0 | K69: =IF(AND(K68 > $F66, K68 <= $F67), 1, 0) -> 0 | L69: =IF(AND(L68 > $F66, L68 <= $F67), 1, 0) -> 1 | M69: =IF(AND(M68 > $F66, M68 <= $F67), 1, 0) -> 1 | N69: =IF(AND(N68 > $F66, N68 <= $F67), 1, 0) -> 1 | O69: =IF(AND(O68 > $F66, O68 <= $F67), 1, 0) -> 1 | P69: =IF(AND(P68 > $F66, P68 <= $F67), 1, 0) -> 1 | Q69: =IF(AND(Q68 > $F66, Q68 <= $F67), 1, 0) -> 1 | ... CO69: =IF(AND(CO68 > $F66, CO68 <= $F67), 1, 0) -> 0
E70: Forecast period total | F70: =SUM(J69:CO69) -> 80 | G70: columns
B72: Last forecast period flag
E73: =E$64 -> Last forecast date | F73: =F$64 -> 51866 | G73: =G$64 -> date
E74: =E$25 -> Model period ending | F74: =F$25 -> 0 | G74: =G$25 -> date | H74: =H$25 -> 0 | I74: =I$25 -> 0 | J74: =J$25 -> 44469 | K74: =K$25 -> 44561 | L74: =L$25 -> 44651 | ... CO74: =CO$25 -> 52047
E75: Last forecast period flag | G75: flag | H75: =SUM(J75:CO75) -> 1 | J75: 0 | K75: =IF(K74 = $F73, 1, 0) -> 0 | L75: =IF(L74 = $F73, 1, 0) -> 0 | M75: =IF(M74 = $F73, 1, 0) -> 0 | N75: =IF(N74 = $F73, 1, 0) -> 0 | O75: =IF(O74 = $F73, 1, 0) -> 0 | P75: =IF(P74 = $F73, 1, 0) -> 0 | Q75: =IF(Q74 = $F73, 1, 0) -> 0 | R75: =IF(R74 = $F73, 1, 0) -> 0 | ... CO75: =IF(CO74 = $F73, 1, 0) -> 0
B77: 1st post forecast period flag
E78: =E$75 -> Last forecast period flag | F78: =F$75 -> 0 | G78: =G$75 -> flag | H78: =H$75 -> 1 | I78: =I$75 -> 0 | J78: =J$75 -> 0 | K78: =K$75 -> 0 | L78: =L$75 -> 0 | ... CO78: =CO$75 -> 0
E79: 1st post forecast period flag | G79: flag | H79: =SUM(J79:CO79) -> 1 | J79: =I78 -> 0 | K79: =J78 -> 0 | L79: =K78 -> 0 | M79: =L78 -> 0 | N79: =M78 -> 0 | O79: =N78 -> 0 | P79: =O78 -> 0 | Q79: =P78 -> 0 | ... CO79: =CN78 -> 0
B81: Post forecast period flag
E82: =E$79 -> 1st post forecast period flag | F82: =F$79 -> 0 | G82: =G$79 -> flag | H82: =H$79 -> 1 | I82: =I$79 -> 0 | J82: =J$79 -> 0 | K82: =K$79 -> 0 | L82: =L$79 -> 0 | ... CO82: =CO$79 -> 0
E83: Post forecast period flag | G83: flag | H83: =SUM(J83:CO83) -> 2 | J83: =I83 + J82 -> 0 | K83: =J83 + K82 -> 0 | L83: =K83 + L82 -> 0 | M83: =L83 + M82 -> 0 | N83: =M83 + N82 -> 0 | O83: =N83 + O82 -> 0 | P83: =O83 + P82 -> 0 | Q83: =P83 + Q82 -> 0 | ... CO83: =CN83 + CO82 -> 1
E84: Post forecast period total | F84: =SUM(J83:CO83) -> 2 | G84: columns
B86: Depreciation period flag
E87: =InpC!E$10 -> Acquisition / initial balance date | F87: =InpC!F$10 -> 44561 | G87: =InpC!G$10 -> date
E88: =InpC!E$65 -> Useful life of NCA at acquisition | F88: =InpC!F$65 -> 15 | G88: =InpC!G$65 -> years
E89: =InpC!E$98 -> Financial year end month number | F89: =InpC!F$98 -> 12 | G89: =InpC!G$98 -> month #
E90: Last depreciation period date | F90: =EOMONTH(F87, F88 * F89) -> 50040 | G90: date
E92: =InpC!E$10 -> Acquisition / initial balance date | F92: =InpC!F$10 -> 44561 | G92: =InpC!G$10 -> date
E93: =E$90 -> Last depreciation period date | F93: =F$90 -> 50040 | G93: =G$90 -> date
E94: =E$25 -> Model period ending | F94: =F$25 -> 0 | G94: =G$25 -> date | H94: =H$25 -> 0 | I94: =I$25 -> 0 | J94: =J$25 -> 44469 | K94: =K$25 -> 44561 | L94: =L$25 -> 44651 | ... CO94: =CO$25 -> 52047
E95: Depreciation period flag | G95: flag | H95: =SUM(J95:CO95) -> 60 | J95: =IF(AND(J94 > $F92, J94 <= $F93), 1, 0) -> 0 | K95: =IF(AND(K94 > $F92, K94 <= $F93), 1, 0) -> 0 | L95: =IF(AND(L94 > $F92, L94 <= $F93), 1, 0) -> 1 | M95: =IF(AND(M94 > $F92, M94 <= $F93), 1, 0) -> 1 | N95: =IF(AND(N94 > $F92, N94 <= $F93), 1, 0) -> 1 | O95: =IF(AND(O94 > $F92, O94 <= $F93), 1, 0) -> 1 | P95: =IF(AND(P94 > $F92, P94 <= $F93), 1, 0) -> 1 | Q95: =IF(AND(Q94 > $F92, Q94 <= $F93), 1, 0) -> 1 | ... CO95: =IF(AND(CO94 > $F92, CO94 <= $F93), 1, 0) -> 0
B98: Timeline label
C99: Timeline label counter
E100: =E$14 -> First model column flag | F100: =F$14 -> 0 | G100: =G$14 -> flag | H100: =H$14 -> 1 | I100: =I$14 -> 0 | J100: =J$14 -> 1 | K100: =K$14 -> 0 | L100: =L$14 -> 0 | ... CO100: =CO$14 -> 0
E101: =E$45 -> Acquisition / initial balance date flag | F101: =F$45 -> 0 | G101: =G$45 -> flag | H101: =H$45 -> 1 | I101: =I$45 -> 0 | J101: =J$45 -> 0 | K101: =K$45 -> 1 | L101: =L$45 -> 0 | ... CO101: =CO$45 -> 0
E102: =E$53 -> First forecast period flag | F102: =F$53 -> 0 | G102: =G$53 -> flag | H102: =H$53 -> 1 | I102: =I$53 -> 0 | J102: =J$53 -> 0 | K102: =K$53 -> 0 | L102: =L$53 -> 1 | ... CO102: =CO$53 -> 0
E103: =E$79 -> 1st post forecast period flag | F103: =F$79 -> 0 | G103: =G$79 -> flag | H103: =H$79 -> 1 | I103: =I$79 -> 0 | J103: =J$79 -> 0 | K103: =K$79 -> 0 | L103: =L$79 -> 0 | ... CO103: =CO$79 -> 0
E104: Timeline label counter | G104: counter | J104: =I104 + MAX(J100:J103) -> 1 | K104: =J104 + MAX(K100:K103) -> 2 | L104: =K104 + MAX(L100:L103) -> 3 | M104: =L104 + MAX(M100:M103) -> 3 | N104: =M104 + MAX(N100:N103) -> 3 | O104: =N104 + MAX(O100:O103) -> 3 | P104: =O104 + MAX(P100:P103) -> 3 | Q104: =P104 + MAX(Q100:Q103) -> 3 | ... CO104: =CN104 + MAX(CO100:CO103) -> 4
E106: =InpC!E$106 -> Pre-forecast period | F106: =InpC!F$106 -> Pre-fcst | G106: =InpC!G$106 -> label
E107: =InpC!E$107 -> Financial close | F107: =InpC!F$107 -> Fin close | G107: =InpC!G$107 -> label
E108: =InpC!E$108 -> Forecast period | F108: =InpC!F$108 -> Forecast | G108: =InpC!G$108 -> label
E109: =InpC!E$109 -> Post-operations period | F109: =InpC!F$109 -> Post-fcst | G109: =InpC!G$109 -> label
E110: =E$104 -> Timeline label counter | F110: =F$104 -> 0 | G110: =G$104 -> counter | H110: =H$104 -> 0 | I110: =I$104 -> 0 | J110: =J$104 -> 1 | K110: =K$104 -> 2 | L110: =L$104 -> 3 | ... CO110: =CO$104 -> 4
E111: Timeline label | G111: label | J111: =INDEX($F106:$F109, J110) -> Pre-fcst | K111: =INDEX($F106:$F109, K110) -> Fin close | L111: =INDEX($F106:$F109, L110) -> Forecast | M111: =INDEX($F106:$F109, M110) -> Forecast | N111: =INDEX($F106:$F109, N110) -> Forecast | O111: =INDEX($F106:$F109, O110) -> Forecast | P111: =INDEX($F106:$F109, P110) -> Forecast | Q111: =INDEX($F106:$F109, Q110) -> Forecast | ... CO111: =INDEX($F106:$F109, CO110) -> Post-fcst
A114: MODELLING PERIOD CHECK
E116: =E$11 -> Model column total | F116: =F$11 -> 84 | G116: =G$11 -> columns
D117: less | E117: =E$59 -> Pre-forecast period total | F117: =F$59 -> 2 | G117: =G$59 -> columns
D118: less | E118: =E$70 -> Forecast period total | F118: =F$70 -> 80 | G118: =G$70 -> columns
D119: less | E119: =E$84 -> Post forecast period total | F119: =F$84 -> 2 | G119: =G$84 -> columns
E120: Modelling period check | F120: =IF(F116 - SUM(F117:F119) <> 0, 1, 0) -> 0 | G120: check

Sheet Esc
A1: =RIGHT(CELL("filename", A1), LEN(CELL("filename", A1)) - SEARCH("]", CELL("filename", A1)))
E2: =Time!E$25 -> Model period ending | J2: =Time!J$25 -> 44469 | K2: =Time!K$25 -> 44561 | L2: =Time!L$25 -> 44651 | M2: =Time!M$25 -> 44742 | N2: =Time!N$25 -> 44834 | O2: =Time!O$25 -> 44926 | P2: =Time!P$25 -> 45016 | Q2: =Time!Q$25 -> 45107 | ... CO2: =Time!CO$25 -> 52047
E3: =Time!E$111 -> Timeline label | J3: =Time!J$111 -> Pre-fcst | K3: =Time!K$111 -> Fin close | L3: =Time!L$111 -> Forecast | M3: =Time!M$111 -> Forecast | N3: =Time!N$111 -> Forecast | O3: =Time!O$111 -> Forecast | P3: =Time!P$111 -> Forecast | Q3: =Time!Q$111 -> Forecast | ... CO3: =Time!CO$111 -> Post-fcst
E4: =Time!E$37 -> Financial year ending | J4: =Time!J$37 -> 2021 | K4: =Time!K$37 -> 2021 | L4: =Time!L$37 -> 2022 | M4: =Time!M$37 -> 2022 | N4: =Time!N$37 -> 2022 | O4: =Time!O$37 -> 2022 | P4: =Time!P$37 -> 2023 | Q4: =Time!Q$37 -> 2023 | ... CO4: =Time!CO$37 -> 2042
E5: =Time!E$10 -> Model column counter | F5: Constant | G5: Unit | H5: Total | J5: =Time!J$10 -> 1 | K5: =Time!K$10 -> 2 | L5: =Time!L$10 -> 3 | M5: =Time!M$10 -> 4 | N5: =Time!N$10 -> 5 | O5: =Time!O$10 -> 6 | P5: =Time!P$10 -> 7 | Q5: =Time!Q$10 -> 8 | ... CO5: =Time!CO$10 -> 84
A7: ESCALATION
C9: CPI inflation rate
E10: =InpC!E$16 -> Start of the inflation year | F10: =InpC!F$16 -> % p.a | G10: =InpC!G$16 -> 0
E11: =InpC!E$17 -> 44256 | F11: =InpC!F$17 -> 0.07 | G11: =InpC!G$17 -> % p.a
E12: =InpC!E$18 -> 44621 | F12: =InpC!F$18 -> 0.06 | G12: =InpC!G$18 -> % p.a
E13: =InpC!E$19 -> 44986 | F13: =InpC!F$19 -> 0.05 | G13: =InpC!G$19 -> % p.a
E14: =InpC!E$20 -> 45352 | F14: =InpC!F$20 -> 0.04 | G14: =InpC!G$20 -> % p.a
E15: =InpC!E$21 -> 45717 | F15: =InpC!F$21 -> 0.03 | G15: =InpC!G$21 -> % p.a
E16: =Time!E$25 -> Model period ending | F16: =Time!F$25 -> 0 | G16: =Time!G$25 -> date | H16: =Time!H$25 -> 0 | I16: =Time!I$25 -> 0 | J16: =Time!J$25 -> 44469 | K16: =Time!K$25 -> 44561 | L16: =Time!L$25 -> 44651 | ... CO16: =Time!CO$25 -> 52047
E17: CPI inflation rate p.a | G17: % pa. | J17: =VLOOKUP(J16, $E11:$F15,2,TRUE) -> 0.07 | K17: =VLOOKUP(K16, $E11:$F15,2,TRUE) -> 0.07 | L17: =VLOOKUP(L16, $E11:$F15,2,TRUE) -> 0.06 | M17: =VLOOKUP(M16, $E11:$F15,2,TRUE) -> 0.06 | N17: =VLOOKUP(N16, $E11:$F15,2,TRUE) -> 0.06 | O17: =VLOOKUP(O16, $E11:$F15,2,TRUE) -> 0.06 | P17: =VLOOKUP(P16, $E11:$F15,2,TRUE) -> 0.05 | Q17: =VLOOKUP(Q16, $E11:$F15,2,TRUE) -> 0.05 | ... CO17: =VLOOKUP(CO16, $E11:$F15,2,TRUE) -> 0.03
E19: =InpC!E$99 -> No of periods in a year | F19: =InpC!F$99 -> 4 | G19: =InpC!G$99 -> periods
E20: =E$17 -> CPI inflation rate p.a | F20: =F$17 -> 0 | G20: =G$17 -> % pa. | H20: =H$17 -> 0 | I20: =I$17 -> 0 | J20: =J$17 -> 0.07 | K20: =K$17 -> 0.07 | L20: =L$17 -> 0.06 | ... CO20: =CO$17 -> 0.03
E21: Periodic CPI inflation rate | G21: %pq | J21: =(1 + J20) ^ (1 / $F19) -1 -> 0.017058525 | K21: =(1 + K20) ^ (1 / $F19) -1 -> 0.017058525 | L21: =(1 + L20) ^ (1 / $F19) -1 -> 0.014673846 | M21: =(1 + M20) ^ (1 / $F19) -1 -> 0.014673846 | N21: =(1 + N20) ^ (1 / $F19) -1 -> 0.014673846 | O21: =(1 + O20) ^ (1 / $F19) -1 -> 0.014673846 | P21: =(1 + P20) ^ (1 / $F19) -1 -> 0.012272234 | Q21: =(1 + Q20) ^ (1 / $F19) -1 -> 0.012272234 | ... CO21: =(1 + CO20) ^ (1 / $F19) -1 -> 0.0074170718
B23: CPI escalation factor
E24: =E$21 -> Periodic CPI inflation rate | F24: =F$21 -> 0 | G24: =G$21 -> %pq | H24: =H$21 -> 0 | I24: =I$21 -> 0 | J24: =J$21 -> 0.017058525 | K24: =K$21 -> 0.017058525 | L24: =L$21 -> 0.014673846 | ... CO24: =CO$21 -> 0.0074170718
E25: =Time!E$45 -> Acquisition / initial balance date flag | F25: =Time!F$45 -> 0 | G25: =Time!G$45 -> flag | H25: =Time!H$45 -> 1 | I25: =Time!I$45 -> 0 | J25: =Time!J$45 -> 0 | K25: =Time!K$45 -> 1 | L25: =Time!L$45 -> 0 | ... CO25: =Time!CO$45 -> 0
E26: CPI escalation factor | G26: factor | J26: =IF(J25 = 1, 1, I26 * ( 1 + J24)) -> 0 | K26: =IF(K25 = 1, 1, J26 * ( 1 + K24)) -> 1 | L26: =IF(L25 = 1, 1, K26 * ( 1 + L24)) -> 1.0146738 | M26: =IF(M25 = 1, 1, L26 * ( 1 + M24)) -> 1.029563 | N26: =IF(N25 = 1, 1, M26 * ( 1 + N24)) -> 1.0446707 | O26: =IF(O25 = 1, 1, N26 * ( 1 + O24)) -> 1.06 | P26: =IF(P25 = 1, 1, O26 * ( 1 + P24)) -> 1.0730086 | Q26: =IF(Q25 = 1, 1, P26 * ( 1 + Q24)) -> 1.0861768 | ... CO26: =IF(CO25 = 1, 1, CN26 * ( 1 + CO24)) -> 1.9416902
B28: Handling escalation factor
E29: =InpC!E$23 -> CPI index at acquisition date | F29: =InpC!F$23 -> 145 | G29: =InpC!G$23 -> index
E30: =InpC!E$25 -> CPI index at handling signature date | F30: =InpC!F$25 -> 120 | G30: =InpC!G$25 -> index
E31: =E$26 -> CPI escalation factor | F31: =F$26 -> 0 | G31: =G$26 -> factor | H31: =H$26 -> 0 | I31: =I$26 -> 0 | J31: =J$26 -> 0 | K31: =K$26 -> 1 | L31: =L$26 -> 1.0146738 | ... CO31: =CO$26 -> 1.9416902
E32: Handling escalation factor | G32: factor | J32: =$F29 / $F30 * J31 -> 0 | K32: =$F29 / $F30 * K31 -> 1.2083333 | L32: =$F29 / $F30 * L31 -> 1.2260642 | M32: =$F29 / $F30 * M31 -> 1.2440553 | N32: =$F29 / $F30 * N31 -> 1.2623104 | O32: =$F29 / $F30 * O31 -> 1.2808333 | P32: =$F29 / $F30 * P31 -> 1.296552 | Q32: =$F29 / $F30 * Q31 -> 1.3124636 | ... CO32: =$F29 / $F30 * CO31 -> 2.346209
B34: O&M escalation factor
E35: =InpC!E$23 -> CPI index at acquisition date | F35: =InpC!F$23 -> 145 | G35: =InpC!G$23 -> index
E36: =InpC!E$27 -> CPI index at O&M signature date | F36: =InpC!F$27 -> 132 | G36: =InpC!G$27 -> index
E37: =E$26 -> CPI escalation factor | F37: =F$26 -> 0 | G37: =G$26 -> factor | H37: =H$26 -> 0 | I37: =I$26 -> 0 | J37: =J$26 -> 0 | K37: =K$26 -> 1 | L37: =L$26 -> 1.0146738 | ... CO37: =CO$26 -> 1.9416902
E38: O&M escalation factor | G38: factor | J38: =$F35 / $F36 * J37 -> 0 | K38: =$F35 / $F36 * K37 -> 1.0984848 | L38: =$F35 / $F36 * L37 -> 1.1146038 | M38: =$F35 / $F36 * M37 -> 1.1309594 | N38: =$F35 / $F36 * N37 -> 1.1475549 | O38: =$F35 / $F36 * O37 -> 1.1643939 | P38: =$F35 / $F36 * P37 -> 1.1786837 | Q38: =$F35 / $F36 * Q37 -> 1.1931487 | ... CO38: =$F35 / $F36 * CO37 -> 2.1329173

Sheet Constr
A1: =RIGHT(CELL("filename", A1), LEN(CELL("filename", A1)) - SEARCH("]", CELL("filename", A1)))
E2: Construction period ending | J2: =J13 -> 43921 | K2: =K13 -> 44012 | L2: =L13 -> 44104 | M2: =M13 -> 44196 | N2: =N13 -> 44286 | O2: =O13 -> 44377 | P2: =P13 -> 44469 | Q2: =Q13 -> 44561
E3: Phase | J3: Construction | K3: Construction | L3: Construction | M3: Construction | N3: Construction | O3: Construction | P3: Construction | Q3: Construction
E4: Financial year | J4: =YEAR(J13) -> 2020 | K4: =YEAR(K13) -> 2020 | L4: =YEAR(L13) -> 2020 | M4: =YEAR(M13) -> 2020 | N4: =YEAR(N13) -> 2021 | O4: =YEAR(O13) -> 2021 | P4: =YEAR(P13) -> 2021 | Q4: =YEAR(Q13) -> 2021
E5: Construction quarter counter | F5: Constant | G5: Unit | H5: Total | J5: 1 | K5: =J5+1 -> 2 | L5: =K5+1 -> 3 | M5: =L5+1 -> 4 | N5: =M5+1 -> 5 | O5: =N5+1 -> 6 | P5: =O5+1 -> 7 | Q5: =P5+1 -> 8
A7: CONSTRUCTION TIMELINE
E9: =InpC!E$10 -> Acquisition / initial balance date | F9: =InpC!F$10 -> 44561 | G9: =InpC!G$10 -> date
E10: =InpC!E$12 -> Months per model period | F10: =InpC!F$12 -> 3 | G10: =InpC!G$12 -> months
E11: =InpC!E$113 -> Construction period | F11: =InpC!F$113 -> 8 | G11: =InpC!G$113 -> quarters
E13: Construction period ending | G13: date | J13: =EOMONTH($F$9,-$F$10*($F$11-J$5)) -> 43921 | K13: =EOMONTH($F$9,-$F$10*($F$11-K$5)) -> 44012 | L13: =EOMONTH($F$9,-$F$10*($F$11-L$5)) -> 44104 | M13: =EOMONTH($F$9,-$F$10*($F$11-M$5)) -> 44196 | N13: =EOMONTH($F$9,-$F$10*($F$11-N$5)) -> 44286 | O13: =EOMONTH($F$9,-$F$10*($F$11-O$5)) -> 44377 | P13: =EOMONTH($F$9,-$F$10*($F$11-P$5)) -> 44469 | Q13: =EOMONTH($F$9,-$F$10*($F$11-Q$5)) -> 44561
E14: Days in construction period | G14: days | H14: =SUM(J14:Q14) -> 731 | J14: =J13-EOMONTH(J13,-$F$10) -> 91 | K14: =K13-EOMONTH(K13,-$F$10) -> 91 | L14: =L13-EOMONTH(L13,-$F$10) -> 92 | M14: =M13-EOMONTH(M13,-$F$10) -> 92 | N14: =N13-EOMONTH(N13,-$F$10) -> 90 | O14: =O13-EOMONTH(O13,-$F$10) -> 91 | P14: =P13-EOMONTH(P13,-$F$10) -> 92 | Q14: =Q13-EOMONTH(Q13,-$F$10) -> 92
A16: CONSTRUCTION COST
E17: =InpC!E$115 -> Total construction cost (hard cost) | F17: =InpC!F$115 -> 94850 | G17: =InpC!G$115 -> $ 000s
E18: Spend profile | G18: % | H18: =SUM(J18:Q18) -> 1 | J18: =INDEX(InpC!$F$118:$F$125,J$5) -> 0.05 | K18: =INDEX(InpC!$F$118:$F$125,K$5) -> 0.1 | L18: =INDEX(InpC!$F$118:$F$125,L$5) -> 0.15 | M18: =INDEX(InpC!$F$118:$F$125,M$5) -> 0.2 | N18: =INDEX(InpC!$F$118:$F$125,N$5) -> 0.2 | O18: =INDEX(InpC!$F$118:$F$125,O$5) -> 0.15 | P18: =INDEX(InpC!$F$118:$F$125,P$5) -> 0.1 | Q18: =INDEX(InpC!$F$118:$F$125,Q$5) -> 0.05
E19: Construction cost spend | G19: $ 000s | H19: =SUM(J19:Q19) -> 94850 | J19: =$F$17*J18 -> 4742.5 | K19: =$F$17*K18 -> 9485 | L19: =$F$17*L18 -> 14227.5 | M19: =$F$17*M18 -> 18970 | N19: =$F$17*N18 -> 18970 | O19: =$F$17*O18 -> 14227.5 | P19: =$F$17*P18 -> 9485 | Q19: =$F$17*Q18 -> 4742.5
A21: FEES
E22: =InpC!E$127 -> Upfront fee (% of facility) | F22: =InpC!F$127 -> 0.02 | G22: =InpC!G$127 -> %
E23: =InpC!E$131 -> Senior debt facility (commitment) | F23: =InpC!F$131 -> 72155 | G23: =InpC!G$131 -> $ 000s
E24: =InpC!E$129 -> Commitment fee (% p.a. on undrawn facility) | F24: =InpC!F$129 -> 0.0075 | G24: =InpC!G$129 -> % p.a
E25: Upfront fee | G25: $ 000s | H25: =SUM(J25:Q25) -> 1443.1 | J25: =IF(J$5=1,$F$22*$F$23,0) -> 1443.1 | K25: =IF(K$5=1,$F$22*$F$23,0) -> 0 | L25: =IF(L$5=1,$F$22*$F$23,0) -> 0 | M25: =IF(M$5=1,$F$22*$F$23,0) -> 0 | N25: =IF(N$5=1,$F$22*$F$23,0) -> 0 | O25: =IF(O$5=1,$F$22*$F$23,0) -> 0 | P25: =IF(P$5=1,$F$22*$F$23,0) -> 0 | Q25: =IF(Q$5=1,$F$22*$F$23,0) -> 0
A27: INTEREST AND COMMITMENT FEE DURING CONSTRUCTION
E28: =InpC!E$77 -> All in annual senior debt interest rate | F28: =InpC!F$77 -> 0.065 | G28: =InpC!G$77 -> %
E29: =InpC!E$79 -> Day count convention | F29: =InpC!F$79 -> 360 | G29: =InpC!G$79 -> days
E30: Senior debt balance BEG | G30: $ 000s | J30: =I49 -> 0 | K30: =J49 -> 4513.6773 | L30: =K49 -> 11429.696 | M30: =L49 -> 21805.616 | N30: =M49 -> 35676.148 | O30: =N49 -> 49681.908 | P30: =O49 -> 60452.381 | Q30: =P49 -> 67956.82
E31: Interest during construction (IDC) | G31: $ 000s | H31: =SUM(J31:Q31) -> 4155.2959 | J31: =J30*$F$28/$F$29*J14 -> 0 | K31: =K30*$F$28/$F$29*K14 -> 74.162225 | L31: =L30*$F$28/$F$29*L14 -> 189.85994 | M31: =M30*$F$28/$F$29*M14 -> 362.21552 | N31: =N30*$F$28/$F$29*N14 -> 579.73741 | O31: =O30*$F$28/$F$29*O14 -> 816.30135 | P31: =P30*$F$28/$F$29*P14 -> 1004.1812 | Q31: =Q30*$F$28/$F$29*Q14 -> 1128.8383
E32: Commitment fee | G32: $ 000s | H32: =SUM(J32:Q32) -> 619.4033 | J32: =($F$23-J30)*$F$24/$F$29*J14 -> 136.79385 | K32: =($F$23-K30)*$F$24/$F$29*K14 -> 128.23667 | L32: =($F$23-L30)*$F$24/$F$29*L14 -> 116.39017 | M32: =($F$23-M30)*$F$24/$F$29*M14 -> 96.502985 | N32: =($F$23-N30)*$F$24/$F$29*N14 -> 68.397847 | O32: =($F$23-O30)*$F$24/$F$29*O14 -> 42.605237 | P32: =($F$23-P30)*$F$24/$F$29*P14 -> 22.43002 | Q32: =($F$23-Q30)*$F$24/$F$29*Q14 -> 8.0465115
A34: USES OF FUNDS
E35: =E$19 -> Construction cost spend | G35: $ 000s | H35: =SUM(J35:Q35) -> 94850 | J35: =J19 -> 4742.5 | K35: =K19 -> 9485 | L35: =L19 -> 14227.5 | M35: =M19 -> 18970 | N35: =N19 -> 18970 | O35: =O19 -> 14227.5 | P35: =P19 -> 9485 | Q35: =Q19 -> 4742.5
E36: =E$25 -> Upfront fee | G36: $ 000s | H36: =SUM(J36:Q36) -> 1443.1 | J36: =J25 -> 1443.1 | K36: =K25 -> 0 | L36: =L25 -> 0 | M36: =M25 -> 0 | N36: =N25 -> 0 | O36: =O25 -> 0 | P36: =P25 -> 0 | Q36: =Q25 -> 0
E37: =E$31 -> Interest during construction (IDC) | G37: $ 000s | H37: =SUM(J37:Q37) -> 4155.2959 | J37: =J31 -> 0 | K37: =K31 -> 74.162225 | L37: =L31 -> 189.85994 | M37: =M31 -> 362.21552 | N37: =N31 -> 579.73741 | O37: =O31 -> 816.30135 | P37: =P31 -> 1004.1812 | Q37: =Q31 -> 1128.8383
E38: =E$32 -> Commitment fee | G38: $ 000s | H38: =SUM(J38:Q38) -> 619.4033 | J38: =J32 -> 136.79385 | K38: =K32 -> 128.23667 | L38: =L32 -> 116.39017 | M38: =M32 -> 96.502985 | N38: =N32 -> 68.397847 | O38: =O32 -> 42.605237 | P38: =P32 -> 22.43002 | Q38: =Q32 -> 8.0465115
E39: Total uses of funds | G39: $ 000s | H39: =SUM(J39:Q39) -> 101067.8 | J39: =SUM(J35:J38) -> 6322.3939 | K39: =SUM(K35:K38) -> 9687.3989 | L39: =SUM(L35:L38) -> 14533.75 | M39: =SUM(M35:M38) -> 19428.719 | N39: =SUM(N35:N38) -> 19618.135 | O39: =SUM(O35:O38) -> 15086.407 | P39: =SUM(P35:P38) -> 10511.611 | Q39: =SUM(Q35:Q38) -> 5879.3848
A41: SOURCES OF FUNDS
E42: =InpC!E$72 -> % of NCA financed with debt | F42: =InpC!F$72 -> 0.71391903 | G42: =InpC!G$72 -> %
E43: =InpC!E$133 -> Drawdown method (1 pro-rata, 2 equity first) | F43: =InpC!F$133 -> 1 | G43: =InpC!G$133 -> switch
E44: =InpC!E$135 -> Equity commitment (used by method 2) | F44: =InpC!F$135 -> 40000 | G44: =InpC!G$135 -> $ 000s
E45: Equity drawdown | G45: $ 000s | H45: =SUM(J45:Q45) -> 28913.574 | J45: =IF($F$43=1,J39*(1-$F$42),MIN(J39,$F$44-SUM($I45:I45))) -> 1808.7166 | K45: =IF($F$43=1,K39*(1-$F$42),MIN(K39,$F$44-SUM($I45:J45))) -> 2771.3805 | L45: =IF($F$43=1,L39*(1-$F$42),MIN(L39,$F$44-SUM($I45:K45))) -> 4157.8294 | M45: =IF($F$43=1,M39*(1-$F$42),MIN(M39,$F$44-SUM($I45:L45))) -> 5558.1867 | N45: =IF($F$43=1,N39*(1-$F$42),MIN(N39,$F$44-SUM($I45:M45))) -> 5612.3752 | O45: =IF($F$43=1,O39*(1-$F$42),MIN(O39,$F$44-SUM($I45:N45))) -> 4315.9339 | P45: =IF($F$43=1,P39*(1-$F$42),MIN(P39,$F$44-SUM($I45:O45))) -> 3007.172 | Q45: =IF($F$43=1,Q39*(1-$F$42),MIN(Q39,$F$44-SUM($I45:P45))) -> 1681.9801
E46: Senior debt drawdown | G46: $ 000s | H46: =SUM(J46:Q46) -> 72154.225 | J46: =J39-J45 -> 4513.6773 | K46: =K39-K45 -> 6916.0184 | L46: =L39-L45 -> 10375.921 | M46: =M39-M45 -> 13870.532 | N46: =N39-N45 -> 14005.76 | O46: =O39-O45 -> 10770.473 | P46: =P39-P45 -> 7504.4393 | Q46: =Q39-Q45 -> 4197.4047
E47: Total sources of funds | G47: $ 000s | H47: =SUM(J47:Q47) -> 101067.8 | J47: =J45+J46 -> 6322.3939 | K47: =K45+K46 -> 9687.3989 | L47: =L45+L46 -> 14533.75 | M47: =M45+M46 -> 19428.719 | N47: =N45+N46 -> 19618.135 | O47: =O45+O46 -> 15086.407 | P47: =P45+P46 -> 10511.611 | Q47: =Q45+Q46 -> 5879.3848
E48: Sources less uses (check) | G48: check | H48: =SUM(J48:Q48) -> 0 | J48: =J47-J39 -> 0 | K48: =K47-K39 -> 0 | L48: =L47-L39 -> 0 | M48: =M47-M39 -> 0 | N48: =N47-N39 -> 0 | O48: =O47-O39 -> 0 | P48: =P47-P39 -> 0 | Q48: =Q47-Q39 -> 0
E49: Senior debt balance END | G49: $ 000s | J49: =J30+J46 -> 4513.6773 | K49: =K30+K46 -> 11429.696 | L49: =L30+L46 -> 21805.616 | M49: =M30+M46 -> 35676.148 | N49: =N30+N46 -> 49681.908 | O49: =O30+O46 -> 60452.381 | P49: =P30+P46 -> 67956.82 | Q49: =Q30+Q46 -> 72154.225
A51: OPENING BALANCES AT COD (financial close)
E52: Capitalised project cost at COD | F52: =H39 -> 101067.8 | G52: $ 000s
E53: Senior debt at COD | F53: =Q49 -> 72154.225 | G53: $ 000s
E54: Sponsor funding at COD (equity) | F54: =H45 -> 28913.574 | G54: $ 000s
E55: Check: cost less debt less equity | F55: =F52-F53-F54 -> 1.4551915e-11 | G55: check

Sheet OpRev
A1: =RIGHT(CELL("filename", A1), LEN(CELL("filename", A1)) - SEARCH("]", CELL("filename", A1)))
E2: =Time!E$25 -> Model period ending | J2: =Time!J$25 -> 44469 | K2: =Time!K$25 -> 44561 | L2: =Time!L$25 -> 44651 | M2: =Time!M$25 -> 44742 | N2: =Time!N$25 -> 44834 | O2: =Time!O$25 -> 44926 | P2: =Time!P$25 -> 45016 | Q2: =Time!Q$25 -> 45107 | ... CO2: =Time!CO$25 -> 52047
E3: =Time!E$111 -> Timeline label | J3: =Time!J$111 -> Pre-fcst | K3: =Time!K$111 -> Fin close | L3: =Time!L$111 -> Forecast | M3: =Time!M$111 -> Forecast | N3: =Time!N$111 -> Forecast | O3: =Time!O$111 -> Forecast | P3: =Time!P$111 -> Forecast | Q3: =Time!Q$111 -> Forecast | ... CO3: =Time!CO$111 -> Post-fcst
E4: =Time!E$37 -> Financial year ending | J4: =Time!J$37 -> 2021 | K4: =Time!K$37 -> 2021 | L4: =Time!L$37 -> 2022 | M4: =Time!M$37 -> 2022 | N4: =Time!N$37 -> 2022 | O4: =Time!O$37 -> 2022 | P4: =Time!P$37 -> 2023 | Q4: =Time!Q$37 -> 2023 | ... CO4: =Time!CO$37 -> 2042
E5: =Time!E$10 -> Model column counter | F5: Constant | G5: Unit | H5: Total | J5: =Time!J$10 -> 1 | K5: =Time!K$10 -> 2 | L5: =Time!L$10 -> 3 | M5: =Time!M$10 -> 4 | N5: =Time!N$10 -> 5 | O5: =Time!O$10 -> 6 | P5: =Time!P$10 -> 7 | Q5: =Time!Q$10 -> 8 | ... CO5: =Time!CO$10 -> 84
A7: OPERATING REVENUE
B9: DEMAND FORECAST
E11: =InpS!E$8 -> Trains - domestic | F11: =InpS!F$8 -> 0 | G11: =InpS!G$8 -> trains | H11: =InpS!H$8 -> 2520 | I11: =InpS!I$8 -> 0 | J11: =InpS!J$8 -> 30 | K11: =InpS!K$8 -> 30 | L11: =InpS!L$8 -> 30 | ... CO11: =InpS!CO$8 -> 30
E12: =InpS!E$9 -> Trains - international | F12: =InpS!F$9 -> 0 | G12: =InpS!G$9 -> trains | H12: =InpS!H$9 -> 1326 | I12: =InpS!I$9 -> 0 | J12: =InpS!J$9 -> 10 | K12: =InpS!K$9 -> 12 | L12: =InpS!L$9 -> 12 | ... CO12: =InpS!CO$9 -> 16
E14: =InpS!E$11 -> Arrivals per train - domestic | F14: =InpS!F$11 -> 0 | G14: =InpS!G$11 -> arrivals / train | H14: =InpS!H$11 -> 0 | I14: =InpS!I$11 -> 0 | J14: =InpS!J$11 -> 370 | K14: =InpS!K$11 -> 350 | L14: =InpS!L$11 -> 370 | ... CO14: =InpS!CO$11 -> 370
E15: =InpS!E$12 -> Arrivals per train - international | F15: =InpS!F$12 -> 0 | G15: =InpS!G$12 -> arrivals / train | H15: =InpS!H$12 -> 0 | I15: =InpS!I$12 -> 0 | J15: =InpS!J$12 -> 34 | K15: =InpS!K$12 -> 34 | L15: =InpS!L$12 -> 34 | ... CO15: =InpS!CO$12 -> 44
E17: =Time!E$69 -> Forecast period flag | F17: =Time!F$69 -> 0 | G17: =Time!G$69 -> flag | H17: =Time!H$69 -> 80 | I17: =Time!I$69 -> 0 | J17: =Time!J$69 -> 0 | K17: =Time!K$69 -> 0 | L17: =Time!L$69 -> 1 | ... CO17: =Time!CO$69 -> 0
E19: Arrivals - Domestic | G19: arrivals | H19: =SUM(J19:CO19) -> 868800 | J19: =IF(J$17 = 1, J11 * J14, 0) -> 0 | K19: =IF(K$17 = 1, K11 * K14, 0) -> 0 | L19: =IF(L$17 = 1, L11 * L14, 0) -> 11100 | M19: =IF(M$17 = 1, M11 * M14, 0) -> 10500 | N19: =IF(N$17 = 1, N11 * N14, 0) -> 11100 | O19: =IF(O$17 = 1, O11 * O14, 0) -> 10500 | P19: =IF(P$17 = 1, P11 * P14, 0) -> 11100 | Q19: =IF(Q$17 = 1, Q11 * Q14, 0) -> 10500 | ... CO19: =IF(CO$17 = 1, CO11 * CO14, 0) -> 0
E20: Arrivals - International | G20: arrivals | H20: =SUM(J20:CO20) -> 55848 | J20: =IF(J$17 = 1, J12 * J15, 0) -> 0 | K20: =IF(K$17 = 1, K12 * K15, 0) -> 0 | L20: =IF(L$17 = 1, L12 * L15, 0) -> 408 | M20: =IF(M$17 = 1, M12 * M15, 0) -> 616 | N20: =IF(N$17 = 1, N12 * N15, 0) -> 616 | O20: =IF(O$17 = 1, O12 * O15, 0) -> 704 | P20: =IF(P$17 = 1, P12 * P15, 0) -> 704 | Q20: =IF(Q$17 = 1, Q12 * Q15, 0) -> 704 | ... CO20: =IF(CO$17 = 1, CO12 * CO15, 0) -> 0
E21: Arrivals | G21: arrivals | H21: =SUM(J21:CO21) -> 924648 | J21: =SUM(J19:J20) -> 0 | K21: =SUM(K19:K20) -> 0 | L21: =SUM(L19:L20) -> 11508 | M21: =SUM(M19:M20) -> 11116 | N21: =SUM(N19:N20) -> 11716 | O21: =SUM(O19:O20) -> 11204 | P21: =SUM(P19:P20) -> 11804 | Q21: =SUM(Q19:Q20) -> 11204 | ... CO21: =SUM(CO19:CO20) -> 0
E23: =InpC!E$31 -> Train capacity - domestic | F23: =InpC!F$31 -> 350 | G23: =InpC!G$31 -> seats
E24: =InpC!E$33 -> Train capacity - international | F24: =InpC!F$33 -> 150 | G24: =InpC!G$33 -> seats
E26: =InpS!E$14 -> Occupancy - domestic | F26: =InpS!F$14 -> 0 | G26: =InpS!G$14 -> % | H26: =InpS!H$14 -> 0 | I26: =InpS!I$14 -> 0 | J26: =InpS!J$14 -> 0.55 | K26: =InpS!K$14 -> 0.55 | L26: =InpS!L$14 -> 0.55 | ... CO26: =InpS!CO$14 -> 0.62
E27: =InpS!E$15 -> Occupancy - international | F27: =InpS!F$15 -> 0 | G27: =InpS!G$15 -> % | H27: =InpS!H$15 -> 0 | I27: =InpS!I$15 -> 0 | J27: =InpS!J$15 -> 0.45 | K27: =InpS!K$15 -> 0.45 | L27: =InpS!L$15 -> 0.45 | ... CO27: =InpS!CO$15 -> 0.55
E29: =E$19 -> Arrivals - Domestic | F29: =F$19 -> 0 | G29: =G$19 -> arrivals | H29: =H$19 -> 868800 | I29: =I$19 -> 0 | J29: =J$19 -> 0 | K29: =K$19 -> 0 | L29: =L$19 -> 11100 | ... CO29: =CO$19 -> 0
E30: =E$20 -> Arrivals - International | F30: =F$20 -> 0 | G30: =G$20 -> arrivals | H30: =H$20 -> 55848 | I30: =I$20 -> 0 | J30: =J$20 -> 0 | K30: =K$20 -> 0 | L30: =L$20 -> 408 | ... CO30: =CO$20 -> 0
E32: Passengers - domestic | G32: pax | H32: =SUM(J32:CO32) -> 181950300 | J32: =$F23 * J26 * J29 -> 0 | K32: =$F23 * K26 * K29 -> 0 | L32: =$F23 * L26 * L29 -> 2136750 | M32: =$F23 * M26 * M29 -> 2021250 | N32: =$F23 * N26 * N29 -> 2136750 | O32: =$F23 * O26 * O29 -> 2021250 | P32: =$F23 * P26 * P29 -> 2136750 | Q32: =$F23 * Q26 * Q29 -> 2021250 | ... CO32: =$F23 * CO26 * CO29 -> 0
E33: Passengers - international | G33: pax | H33: =SUM(J33:CO33) -> 4213260 | J33: =$F24 * J27 * J30 -> 0 | K33: =$F24 * K27 * K30 -> 0 | L33: =$F24 * L27 * L30 -> 27540 | M33: =$F24 * M27 * M30 -> 41580 | N33: =$F24 * N27 * N30 -> 41580 | O33: =$F24 * O27 * O30 -> 47520 | P33: =$F24 * P27 * P30 -> 47520 | Q33: =$F24 * Q27 * Q30 -> 47520 | ... CO33: =$F24 * CO27 * CO30 -> 0
E34: Passengers | G34: pax | H34: =SUM(J34:CO34) -> 186163560 | J34: =SUM(J32:J33) -> 0 | K34: =SUM(K32:K33) -> 0 | L34: =SUM(L32:L33) -> 2164290 | M34: =SUM(M32:M33) -> 2062830 | N34: =SUM(N32:N33) -> 2178330 | O34: =SUM(O32:O33) -> 2068770 | P34: =SUM(P32:P33) -> 2184270 | Q34: =SUM(Q32:Q33) -> 2068770 | ... CO34: =SUM(CO32:CO33) -> 0
B36: Operating revenue
E37: =InpC!E$35 -> Average fare per passenger | F37: =InpC!F$35 -> 7.15 | G37: =InpC!G$35 -> USD/pax
E38: =InpC!E$102 -> Unit in thousand | F38: =InpC!F$102 -> 1000 | G38: =InpC!G$102 -> units
E39: =E$34 -> Passengers | F39: =F$34 -> 0 | G39: =G$34 -> pax | H39: =H$34 -> 186163560 | I39: =I$34 -> 0 | J39: =J$34 -> 0 | K39: =K$34 -> 0 | L39: =L$34 -> 2164290 | ... CO39: =CO$34 -> 0
E40: =Esc!E$26 -> CPI escalation factor | F40: =Esc!F$26 -> 0 | G40: =Esc!G$26 -> factor | H40: =Esc!H$26 -> 0 | I40: =Esc!I$26 -> 0 | J40: =Esc!J$26 -> 0 | K40: =Esc!K$26 -> 1 | L40: =Esc!L$26 -> 1.0146738 | ... CO40: =Esc!CO$26 -> 1.9416902
E41: =Time!E$69 -> Forecast period flag | F41: =Time!F$69 -> 0 | G41: =Time!G$69 -> flag | H41: =Time!H$69 -> 80 | I41: =Time!I$69 -> 0 | J41: =Time!J$69 -> 0 | K41: =Time!K$69 -> 0 | L41: =Time!L$69 -> 1 | ... CO41: =Time!CO$69 -> 0
E42: Operating revenue | F42: IS | G42: =SMU -> $ 000s | H42: =SUM(J42:CO42) -> 1941568.6 | J42: =IF( J41 = 1,$F37 / $F38 * J39 * J40, 0) -> 0 | K42: =IF( K41 = 1,$F37 / $F38 * K39 * K40, 0) -> 0 | L42: =IF( L41 = 1,$F37 / $F38 * L39 * L40, 0) -> 15701.746 | M42: =IF( M41 = 1,$F37 / $F38 * M39 * M40, 0) -> 15185.266 | N42: =IF( N41 = 1,$F37 / $F38 * N39 * N40, 0) -> 16270.808 | O42: =IF( O41 = 1,$F37 / $F38 * O39 * O40, 0) -> 15679.208 | P42: =IF( P41 = 1,$F37 / $F38 * P39 * P40, 0) -> 16757.744 | Q42: =IF( Q41 = 1,$F37 / $F38 * Q39 * Q40, 0) -> 16066.407 | ... CO42: =IF( CO41 = 1,$F37 / $F38 * CO39 * CO40, 0) -> 0
A45: OPERATING REVENUE RECEIVED
E47: =InpC!E$37 -> Account receivables days | F47: =InpC!F$37 -> 25 | G47: =InpC!G$37 -> days
E48: =Time!E$30 -> Days in model period | F48: =Time!F$30 -> 0 | G48: =Time!G$30 -> days | H48: =Time!H$30 -> 0 | I48: =Time!I$30 -> 0 | J48: =Time!J$30 -> 92 | K48: =Time!K$30 -> 92 | L48: =Time!L$30 -> 90 | ... CO48: =Time!CO$30 -> 91
E49: =E$42 -> Operating revenue | F49: =F$42 -> IS | G49: =G$42 -> $ 000s | H49: =H$42 -> 1941568.6 | I49: =I$42 -> 0 | J49: =J$42 -> 0 | K49: =K$42 -> 0 | L49: =L$42 -> 15701.746 | ... CO49: =CO$42 -> 0
E50: Cash from paid invoices | G50: =SMU -> $ 000s | J50: =(J48 - $F47) / J48 * J49 -> 0 | K50: =(K48 - $F47) / K48 * K49 -> 0 | L50: =(L48 - $F47) / L48 * L49 -> 11340.15 | M50: =(M48 - $F47) / M48 * M49 -> 11013.49 | N50: =(N48 - $F47) / N48 * N49 -> 11849.393 | O50: =(O48 - $F47) / O48 * O49 -> 11418.554 | P50: =(P48 - $F47) / P48 * P49 -> 12102.815 | Q50: =(Q48 - $F47) / Q48 * Q49 -> 11652.559 | ... CO50: =(CO48 - $F47) / CO48 * CO49 -> 0
E52: =E$62 -> Account receivables balance BEG | F52: =F$62 -> 0 | G52: =G$62 -> $ 000s | H52: =H$62 -> 0 | I52: =I$62 -> 0 | J52: =J$62 -> 0 | K52: =K$62 -> 0 | L52: =L$62 -> 0 | ... CO52: =CO$62 -> 0
E53: =E$50 -> Cash from paid invoices | F53: =F$50 -> 0 | G53: =G$50 -> $ 000s | H53: =H$50 -> 0 | I53: =I$50 -> 0 | J53: =J$50 -> 0 | K53: =K$50 -> 0 | L53: =L$50 -> 11340.15 | ... CO53: =CO$50 -> 0
E54: Operating revenue received | F54: CF | G54: =SMU -> $ 000s | H54: =SUM(J54:CO54) -> 1941568.6 | J54: =SUM(J52:J53) -> 0 | K54: =SUM(K52:K53) -> 0 | L54: =SUM(L52:L53) -> 11340.15 | M54: =SUM(M52:M53) -> 15375.086 | N54: =SUM(N52:N53) -> 16021.169 | O54: =SUM(O52:O53) -> 15839.969 | P54: =SUM(P52:P53) -> 16363.469 | Q54: =SUM(Q52:Q53) -> 16307.488 | ... CO54: =SUM(CO52:CO53) -> 0
A57: ACCOUNT RECEIVABLES BALANCE
E59: Account receivables - initial balance | F59: 0
E60: =Time!E$45 -> Acquisition / initial balance date flag | F60: =Time!F$45 -> 0 | G60: =Time!G$45 -> flag | H60: =Time!H$45 -> 1 | I60: =Time!I$45 -> 0 | J60: =Time!J$45 -> 0 | K60: =Time!K$45 -> 1 | L60: =Time!L$45 -> 0 | ... CO60: =Time!CO$45 -> 0
E62: Account receivables balance BEG | G62: $ 000s | J62: =I65 -> 0 | K62: =J65 -> 0 | L62: =K65 -> 0 | M62: =L65 -> 4361.5962 | N62: =M65 -> 4171.7765 | O62: =N65 -> 4421.4151 | P62: =O65 -> 4260.6543 | Q62: =P65 -> 4654.9289 | ... CO62: =CN65 -> 0
D63: plus | E63: =E$42 -> Operating revenue | F63: =F$42 -> IS | G63: =G$42 -> $ 000s | H63: =H$42 -> 1941568.6 | I63: =I$42 -> 0 | J63: =J$42 -> 0 | K63: =K$42 -> 0 | L63: =L$42 -> 15701.746 | ... CO63: =CO$42 -> 0
D64: less | E64: =E$54 -> Operating revenue received | F64: =F$54 -> CF | G64: =G$54 -> $ 000s | H64: =H$54 -> 1941568.6 | I64: =I$54 -> 0 | J64: =J$54 -> 0 | K64: =K$54 -> 0 | L64: =L$54 -> 11340.15 | ... CO64: =CO$54 -> 0
E65: Account receivables balance | F65: BS | G65: $ 000s | J65: =IF(J60 = 1, $F59, J62 + J63 - J64) -> 0 | K65: =IF(K60 = 1, $F59, K62 + K63 - K64) -> 0 | L65: =IF(L60 = 1, $F59, L62 + L63 - L64) -> 4361.5962 | M65: =IF(M60 = 1, $F59, M62 + M63 - M64) -> 4171.7765 | N65: =IF(N60 = 1, $F59, N62 + N63 - N64) -> 4421.4151 | O65: =IF(O60 = 1, $F59, O62 + O63 - O64) -> 4260.6543 | P65: =IF(P60 = 1, $F59, P62 + P63 - P64) -> 4654.9289 | Q65: =IF(Q60 = 1, $F59, Q62 + Q63 - Q64) -> 4413.8481 | ... CO65: =IF(CO60 = 1, $F59, CO62 + CO63 - CO64) -> 0

Sheet OpCost
A1: =RIGHT(CELL("filename", A1), LEN(CELL("filename", A1)) - SEARCH("]", CELL("filename", A1)))
E2: =Time!E$25 -> Model period ending | J2: =Time!J$25 -> 44469 | K2: =Time!K$25 -> 44561 | L2: =Time!L$25 -> 44651 | M2: =Time!M$25 -> 44742 | N2: =Time!N$25 -> 44834 | O2: =Time!O$25 -> 44926 | P2: =Time!P$25 -> 45016 | Q2: =Time!Q$25 -> 45107 | ... CO2: =Time!CO$25 -> 52047
E3: =Time!E$111 -> Timeline label | J3: =Time!J$111 -> Pre-fcst | K3: =Time!K$111 -> Fin close | L3: =Time!L$111 -> Forecast | M3: =Time!M$111 -> Forecast | N3: =Time!N$111 -> Forecast | O3: =Time!O$111 -> Forecast | P3: =Time!P$111 -> Forecast | Q3: =Time!Q$111 -> Forecast | ... CO3: =Time!CO$111 -> Post-fcst
E4: =Time!E$37 -> Financial year ending | J4: =Time!J$37 -> 2021 | K4: =Time!K$37 -> 2021 | L4: =Time!L$37 -> 2022 | M4: =Time!M$37 -> 2022 | N4: =Time!N$37 -> 2022 | O4: =Time!O$37 -> 2022 | P4: =Time!P$37 -> 2023 | Q4: =Time!Q$37 -> 2023 | ... CO4: =Time!CO$37 -> 2042
E5: =Time!E$10 -> Model column counter | F5: Constant | G5: Unit | H5: Total | J5: =Time!J$10 -> 1 | K5: =Time!K$10 -> 2 | L5: =Time!L$10 -> 3 | M5: =Time!M$10 -> 4 | N5: =Time!N$10 -> 5 | O5: =Time!O$10 -> 6 | P5: =Time!P$10 -> 7 | Q5: =Time!Q$10 -> 8 | ... CO5: =Time!CO$10 -> 84
A7: OPERATING COST
B9: Handling cost
C10: Variable cost
E11: =InpC!E$44 -> Handling cost - variable | F11: =InpC!F$44 -> 550 | G11: =InpC!G$44 -> USD/arrival
E12: =InpC!E$102 -> Unit in thousand | F12: =InpC!F$102 -> 1000 | G12: =InpC!G$102 -> units
E13: =OpRev!E$21 -> Arrivals | F13: =OpRev!F$21 -> 0 | G13: =OpRev!G$21 -> arrivals | H13: =OpRev!H$21 -> 924648 | I13: =OpRev!I$21 -> 0 | J13: =OpRev!J$21 -> 0 | K13: =OpRev!K$21 -> 0 | L13: =OpRev!L$21 -> 11508 | ... CO13: =OpRev!CO$21 -> 0
E14: =Esc!E$32 -> Handling escalation factor | F14: =Esc!F$32 -> 0 | G14: =Esc!G$32 -> factor | H14: =Esc!H$32 -> 0 | I14: =Esc!I$32 -> 0 | J14: =Esc!J$32 -> 0 | K14: =Esc!K$32 -> 1.2083333 | L14: =Esc!L$32 -> 1.2260642 | ... CO14: =Esc!CO$32 -> 2.346209
E15: =Time!E$69 -> Forecast period flag | F15: =Time!F$69 -> 0 | G15: =Time!G$69 -> flag | H15: =Time!H$69 -> 80 | I15: =Time!I$69 -> 0 | J15: =Time!J$69 -> 0 | K15: =Time!K$69 -> 0 | L15: =Time!L$69 -> 1 | ... CO15: =Time!CO$69 -> 0
E16: Handling variable cost | G16: =SMU -> $ 000s | H16: =SUM(J16:CO16) -> 890187.43 | J16: =IF( J15 = 1,$F11 / $F12 * J13 * J14, 0) -> 0 | K16: =IF( K15 = 1,$F11 / $F12 * K13 * K14, 0) -> 0 | L16: =IF( L15 = 1,$F11 / $F12 * L13 * L14, 0) -> 7760.2509 | M16: =IF( M15 = 1,$F11 / $F12 * M13 * M14, 0) -> 7605.9053 | N16: =IF( N15 = 1,$F11 / $F12 * N13 * N14, 0) -> 8134.0757 | O16: =IF( O15 = 1,$F11 / $F12 * O13 * O14, 0) -> 7892.7512 | P16: =IF( P15 = 1,$F11 / $F12 * P13 * P14, 0) -> 8417.475 | Q16: =IF( Q15 = 1,$F11 / $F12 * Q13 * Q14, 0) -> 8087.6633 | ... CO16: =IF( CO15 = 1,$F11 / $F12 * CO13 * CO14, 0) -> 0
C18: Fixed cost
E19: =InpC!E$42 -> Handling cost- fixed per annum | F19: =InpC!F$42 -> 4500 | G19: =InpC!G$42 -> $ 000s
E20: =InpC!E$99 -> No of periods in a year | F20: =InpC!F$99 -> 4 | G20: =InpC!G$99 -> periods
E21: =Esc!E$32 -> Handling escalation factor | F21: =Esc!F$32 -> 0 | G21: =Esc!G$32 -> factor | H21: =Esc!H$32 -> 0 | I21: =Esc!I$32 -> 0 | J21: =Esc!J$32 -> 0 | K21: =Esc!K$32 -> 1.2083333 | L21: =Esc!L$32 -> 1.2260642 | ... CO21: =Esc!CO$32 -> 2.346209
E22: =Time!E$69 -> Forecast period flag | F22: =Time!F$69 -> 0 | G22: =Time!G$69 -> flag | H22: =Time!H$69 -> 80 | I22: =Time!I$69 -> 0 | J22: =Time!J$69 -> 0 | K22: =Time!K$69 -> 0 | L22: =Time!L$69 -> 1 | ... CO22: =Time!CO$69 -> 0
E23: Handling fixed cost | G23: =SMU -> $ 000s | H23: =SUM(J23:CO23) -> 157311.6 | J23: =IF(J22 = 1, $F19 / $F20 * J21, 0) -> 0 | K23: =IF(K22 = 1, $F19 / $F20 * K21, 0) -> 0 | L23: =IF(L22 = 1, $F19 / $F20 * L21, 0) -> 1379.3223 | M23: =IF(M22 = 1, $F19 / $F20 * M21, 0) -> 1399.5622 | N23: =IF(N22 = 1, $F19 / $F20 * N21, 0) -> 1420.0992 | O23: =IF(O22 = 1, $F19 / $F20 * O21, 0) -> 1440.9375 | P23: =IF(P22 = 1, $F19 / $F20 * P21, 0) -> 1458.621 | Q23: =IF(Q22 = 1, $F19 / $F20 * Q21, 0) -> 1476.5216 | ... CO23: =IF(CO22 = 1, $F19 / $F20 * CO21, 0) -> 0
B25: O&M Cost
E26: =InpC!E$48 -> O&M cost- fixed per annum | F26: =InpC!F$48 -> 3300 | G26: =InpC!G$48 -> $ 000s
E27: =InpC!E$99 -> No of periods in a year | F27: =InpC!F$99 -> 4 | G27: =InpC!G$99 -> periods
E28: =InpC!E$46 -> O&M cost - sensitivity | F28: =InpC!F$46 -> 0 | G28: =InpC!G$46 -> (1 + X%)
E29: =Esc!E$38 -> O&M escalation factor | F29: =Esc!F$38 -> 0 | G29: =Esc!G$38 -> factor | H29: =Esc!H$38 -> 0 | I29: =Esc!I$38 -> 0 | J29: =Esc!J$38 -> 0 | K29: =Esc!K$38 -> 1.0984848 | L29: =Esc!L$38 -> 1.1146038 | ... CO29: =Esc!CO$38 -> 2.1329173
E30: =Time!E$69 -> Forecast period flag | F30: =Time!F$69 -> 0 | G30: =Time!G$69 -> flag | H30: =Time!H$69 -> 80 | I30: =Time!I$69 -> 0 | J30: =Time!J$69 -> 0 | K30: =Time!K$69 -> 0 | L30: =Time!L$69 -> 1 | ... CO30: =Time!CO$69 -> 0
E31: O&M fixed cost | G31: =SMU -> $ 000s | H31: =SUM(J31:CO31) -> 104874.4 | J31: =IF(J30=1,$F26/$F27*J29*(1+$F28),0) -> 0 | K31: =IF(K30=1,$F26/$F27*K29*(1+$F28),0) -> 0 | L31: =IF(L30=1,$F26/$F27*L29*(1+$F28),0) -> 919.54817 | M31: =IF(M30=1,$F26/$F27*M29*(1+$F28),0) -> 933.04148 | N31: =IF(N30=1,$F26/$F27*N29*(1+$F28),0) -> 946.73279 | O31: =IF(O30=1,$F26/$F27*O29*(1+$F28),0) -> 960.625 | P31: =IF(P30=1,$F26/$F27*P29*(1+$F28),0) -> 972.41402 | Q31: =IF(Q30=1,$F26/$F27*Q29*(1+$F28),0) -> 984.34771 | ... CO31: =IF(CO30=1,$F26/$F27*CO29*(1+$F28),0) -> 0
A34: Summary of operating cost
E35: =E$16 -> Handling variable cost | F35: =F$16 -> 0 | G35: =G$16 -> $ 000s | H35: =H$16 -> 890187.43 | I35: =I$16 -> 0 | J35: =J$16 -> 0 | K35: =K$16 -> 0 | L35: =L$16 -> 7760.2509 | ... CO35: =CO$16 -> 0
E36: =E$23 -> Handling fixed cost | F36: =F$23 -> 0 | G36: =G$23 -> $ 000s | H36: =H$23 -> 157311.6 | I36: =I$23 -> 0 | J36: =J$23 -> 0 | K36: =K$23 -> 0 | L36: =L$23 -> 1379.3223 | ... CO36: =CO$23 -> 0
E37: =E$31 -> O&M fixed cost | F37: =F$31 -> 0 | G37: =G$31 -> $ 000s | H37: =H$31 -> 104874.4 | I37: =I$31 -> 0 | J37: =J$31 -> 0 | K37: =K$31 -> 0 | L37: =L$31 -> 919.54817 | ... CO37: =CO$31 -> 0
E38: Operating cost POS | G38: =SMU -> $ 000s | H38: =SUM(J38:CO38) -> 1152373.4 | J38: =SUM(J35:J37) -> 0 | K38: =SUM(K35:K37) -> 0 | L38: =SUM(L35:L37) -> 10059.121 | M38: =SUM(M35:M37) -> 9938.5091 | N38: =SUM(N35:N37) -> 10500.908 | O38: =SUM(O35:O37) -> 10294.314 | P38: =SUM(P35:P37) -> 10848.51 | Q38: =SUM(Q35:Q37) -> 10548.533 | ... CO38: =SUM(CO35:CO37) -> 0
E39: =LEFT(E38, LEN(E38) - 4) -> Operating cost | F39: IS | G39: =G38 -> $ 000s | H39: =SUM(J39:CO39) -> -1152373.4 | J39: =-1 * J38 -> 0 | K39: =-1 * K38 -> 0 | L39: =-1 * L38 -> -10059.121 | M39: =-1 * M38 -> -9938.5091 | N39: =-1 * N38 -> -10500.908 | O39: =-1 * O38 -> -10294.314 | P39: =-1 * P38 -> -10848.51 | Q39: =-1 * Q38 -> -10548.533 | ... CO39: =-1 * CO38 -> 0
A41: OPERATING COST PAID
E43: =InpC!E$50 -> Account payables days | F43: =InpC!F$50 -> 35 | G43: =InpC!G$50 -> days
E44: =Time!E$30 -> Days in model period | F44: =Time!F$30 -> 0 | G44: =Time!G$30 -> days | H44: =Time!H$30 -> 0 | I44: =Time!I$30 -> 0 | J44: =Time!J$30 -> 92 | K44: =Time!K$30 -> 92 | L44: =Time!L$30 -> 90 | ... CO44: =Time!CO$30 -> 91
E45: =E$38 -> Operating cost POS | F45: =F$38 -> 0 | G45: =G$38 -> $ 000s | H45: =H$38 -> 1152373.4 | I45: =I$38 -> 0 | J45: =J$38 -> 0 | K45: =K$38 -> 0 | L45: =L$38 -> 10059.121 | ... CO45: =CO$38 -> 0
E46: Cash paid out for invoices | G46: =SMU -> $ 000s | J46: =(J44 - $F43) / J44 * J45 -> 0 | K46: =(K44 - $F43) / K44 * K45 -> 0 | L46: =(L44 - $F43) / L44 * L45 -> 6147.2408 | M46: =(M44 - $F43) / M44 * M45 -> 6116.0056 | N46: =(N44 - $F43) / N44 * N45 -> 6505.9971 | O46: =(O44 - $F43) / O44 * O45 -> 6377.9987 | P46: =(P44 - $F43) / P44 * P45 -> 6629.645 | Q46: =(Q44 - $F43) / Q44 * Q45 -> 6491.4046 | ... CO46: =(CO44 - $F43) / CO44 * CO45 -> 0
E48: =E$59 -> Account payables balance BEG | F48: =F$59 -> 0 | G48: =G$59 -> $ 000s | H48: =H$59 -> 0 | I48: =I$59 -> 0 | J48: =J$59 -> 0 | K48: =K$59 -> 0 | L48: =L$59 -> 0 | ... CO48: =CO$59 -> 0
E49: =E$46 -> Cash paid out for invoices | F49: =F$46 -> 0 | G49: =G$46 -> $ 000s | H49: =H$46 -> 0 | I49: =I$46 -> 0 | J49: =J$46 -> 0 | K49: =K$46 -> 0 | L49: =L$46 -> 6147.2408 | ... CO49: =CO$46 -> 0
E50: Operating cost paid POS | G50: =SMU -> $ 000s | H50: =SUM(J50:CO50) -> 1152373.4 | J50: =SUM(J48:J49) -> 0 | K50: =SUM(K48:K49) -> 0 | L50: =SUM(L48:L49) -> 6147.2408 | M50: =SUM(M48:M49) -> 10027.886 | N50: =SUM(N48:N49) -> 10328.501 | O50: =SUM(O48:O49) -> 10372.909 | P50: =SUM(P48:P49) -> 10545.96 | Q50: =SUM(Q48:Q49) -> 10710.27 | ... CO50: =SUM(CO48:CO49) -> 0
E51: =LEFT(E50, LEN(E50) - 4) -> Operating cost paid | F51: CF | G51: =G50 -> $ 000s | H51: =SUM(J51:CO51) -> -1152373.4 | J51: =-1 * J50 -> 0 | K51: =-1 * K50 -> 0 | L51: =-1 * L50 -> -6147.2408 | M51: =-1 * M50 -> -10027.886 | N51: =-1 * N50 -> -10328.501 | O51: =-1 * O50 -> -10372.909 | P51: =-1 * P50 -> -10545.96 | Q51: =-1 * Q50 -> -10710.27 | ... CO51: =-1 * CO50 -> 0
A54: ACCOUNT PAYABLES BALANCE
E56: Account payables - initial balance | F56: 0
E57: =Time!E$45 -> Acquisition / initial balance date flag | F57: =Time!F$45 -> 0 | G57: =Time!G$45 -> flag | H57: =Time!H$45 -> 1 | I57: =Time!I$45 -> 0 | J57: =Time!J$45 -> 0 | K57: =Time!K$45 -> 1 | L57: =Time!L$45 -> 0 | ... CO57: =Time!CO$45 -> 0
E59: Account payables balance BEG | G59: $ 000s | J59: =I62 -> 0 | K59: =J62 -> 0 | L59: =K62 -> 0 | M59: =L62 -> 3911.8805 | N59: =M62 -> 3822.5035 | O59: =N62 -> 3994.9105 | P59: =O62 -> 3916.315 | Q59: =P62 -> 4218.865 | ... CO59: =CN62 -> 0
D60: plus | E60: =E$38 -> Operating cost POS | F60: =F$38 -> 0 | G60: =G$38 -> $ 000s | H60: =H$38 -> 1152373.4 | I60: =I$38 -> 0 | J60: =J$38 -> 0 | K60: =K$38 -> 0 | L60: =L$38 -> 10059.121 | ... CO60: =CO$38 -> 0
D61: less | E61: =E$50 -> Operating cost paid POS | F61: =F$50 -> 0 | G61: =G$50 -> $ 000s | H61: =H$50 -> 1152373.4 | I61: =I$50 -> 0 | J61: =J$50 -> 0 | K61: =K$50 -> 0 | L61: =L$50 -> 6147.2408 | ... CO61: =CO$50 -> 0
E62: Account payables balance | F62: BS | G62: $ 000s | J62: =IF(J57 = 1, $F56, J59 + J60 - J61) -> 0 | K62: =IF(K57 = 1, $F56, K59 + K60 - K61) -> 0 | L62: =IF(L57 = 1, $F56, L59 + L60 - L61) -> 3911.8805 | M62: =IF(M57 = 1, $F56, M59 + M60 - M61) -> 3822.5035 | N62: =IF(N57 = 1, $F56, N59 + N60 - N61) -> 3994.9105 | O62: =IF(O57 = 1, $F56, O59 + O60 - O61) -> 3916.315 | P62: =IF(P57 = 1, $F56, P59 + P60 - P61) -> 4218.865 | Q62: =IF(Q57 = 1, $F56, Q59 + Q60 - Q61) -> 4057.1279 | ... CO62: =IF(CO57 = 1, $F56, CO59 + CO60 - CO61) -> 0

Sheet Tax
A1: =RIGHT(CELL("filename", A1), LEN(CELL("filename", A1)) - SEARCH("]", CELL("filename", A1)))
E2: =Time!E$25 -> Model period ending | J2: =Time!J$25 -> 44469 | K2: =Time!K$25 -> 44561 | L2: =Time!L$25 -> 44651 | M2: =Time!M$25 -> 44742 | N2: =Time!N$25 -> 44834 | O2: =Time!O$25 -> 44926 | P2: =Time!P$25 -> 45016 | Q2: =Time!Q$25 -> 45107 | ... CO2: =Time!CO$25 -> 52047
E3: =Time!E$111 -> Timeline label | J3: =Time!J$111 -> Pre-fcst | K3: =Time!K$111 -> Fin close | L3: =Time!L$111 -> Forecast | M3: =Time!M$111 -> Forecast | N3: =Time!N$111 -> Forecast | O3: =Time!O$111 -> Forecast | P3: =Time!P$111 -> Forecast | Q3: =Time!Q$111 -> Forecast | ... CO3: =Time!CO$111 -> Post-fcst
E4: =Time!E$37 -> Financial year ending | J4: =Time!J$37 -> 2021 | K4: =Time!K$37 -> 2021 | L4: =Time!L$37 -> 2022 | M4: =Time!M$37 -> 2022 | N4: =Time!N$37 -> 2022 | O4: =Time!O$37 -> 2022 | P4: =Time!P$37 -> 2023 | Q4: =Time!Q$37 -> 2023 | ... CO4: =Time!CO$37 -> 2042
E5: =Time!E$10 -> Model column counter | F5: Constant | G5: Unit | H5: Total | J5: =Time!J$10 -> 1 | K5: =Time!K$10 -> 2 | L5: =Time!L$10 -> 3 | M5: =Time!M$10 -> 4 | N5: =Time!N$10 -> 5 | O5: =Time!O$10 -> 6 | P5: =Time!P$10 -> 7 | Q5: =Time!Q$10 -> 8 | ... CO5: =Time!CO$10 -> 84
A7: TAX DEPRECIATION
E8: =InpC!E$84 -> Tax depreciation rate | F8: =InpC!F$84 -> 0.05 | G8: =InpC!G$84 -> % TWDV
E9: =E$18 -> Tax written down value balance BEG | F9: =F$18 -> 0 | G9: =G$18 -> $ 000s | H9: =H$18 -> 0 | I9: =I$18 -> 0 | J9: =J$18 -> 0 | K9: =K$18 -> 0 | L9: =L$18 -> 101067.8 | ... CO9: =CO$18 -> 0
E10: =Time!E$75 -> Last forecast period flag | F10: =Time!F$75 -> 0 | G10: =Time!G$75 -> flag | H10: =Time!H$75 -> 1 | I10: =Time!I$75 -> 0 | J10: =Time!J$75 -> 0 | K10: =Time!K$75 -> 0 | L10: =Time!L$75 -> 0 | ... CO10: =Time!CO$75 -> 0
E11: Tax depreciation | G11: =SMU -> $ 000s | H11: =SUM(J11:CO11) -> 109067.8 | J11: =IF(J10 = 1, J9, $F8 * J9) -> 0 | K11: =IF(K10 = 1, K9, $F8 * K9) -> 0 | L11: =IF(L10 = 1, L9, $F8 * L9) -> 5053.39 | M11: =IF(M10 = 1, M9, $F8 * M9) -> 4800.7205 | N11: =IF(N10 = 1, N9, $F8 * N9) -> 4560.6844 | O11: =IF(O10 = 1, O9, $F8 * O9) -> 4332.6502 | P11: =IF(P10 = 1, P9, $F8 * P9) -> 4116.0177 | Q11: =IF(Q10 = 1, Q9, $F8 * Q9) -> 3910.2168 | ... CO11: =IF(CO10 = 1, CO9, $F8 * CO9) -> 0
A13: TAX WRITTEN DOWN VALUE BALANCE
E15: =InpC!E$64 -> Non current asset - initial balance | F15: =InpC!F$64 -> 101067.8 | G15: =InpC!G$64 -> $ 000s
E16: =Time!E$45 -> Acquisition / initial balance date flag | F16: =Time!F$45 -> 0 | G16: =Time!G$45 -> flag | H16: =Time!H$45 -> 1 | I16: =Time!I$45 -> 0 | J16: =Time!J$45 -> 0 | K16: =Time!K$45 -> 1 | L16: =Time!L$45 -> 0 | ... CO16: =Time!CO$45 -> 0
E18: Tax written down value balance BEG | G18: $ 000s | J18: =I21 -> 0 | K18: =J21 -> 0 | L18: =K21 -> 101067.8 | M18: =L21 -> 96014.409 | N18: =M21 -> 91213.689 | O18: =N21 -> 86653.004 | P18: =O21 -> 82320.354 | Q18: =P21 -> 78204.336 | ... CO18: =CN21 -> 0
D19: plus | E19: =NCA!E$18 -> Capital expenditure POS | F19: =NCA!F$18 -> 0 | G19: =NCA!G$18 -> $ 000s | H19: =NCA!H$18 -> 8000 | I19: =NCA!I$18 -> 0 | J19: =NCA!J$18 -> 0 | K19: =NCA!K$18 -> 0 | L19: =NCA!L$18 -> 0 | ... CO19: =NCA!CO$18 -> 0
D20: less | E20: =E$11 -> Tax depreciation | F20: =F$11 -> 0 | G20: =G$11 -> $ 000s | H20: =H$11 -> 109067.8 | I20: =I$11 -> 0 | J20: =J$11 -> 0 | K20: =K$11 -> 0 | L20: =L$11 -> 5053.39 | ... CO20: =CO$11 -> 0
E21: Tax written down value balance | G21: $ 000s | J21: =IF(J16 = 1, $F15, J18 + J19 - J20) -> 0 | K21: =IF(K16 = 1, $F15, K18 + K19 - K20) -> 101067.8 | L21: =IF(L16 = 1, $F15, L18 + L19 - L20) -> 96014.409 | M21: =IF(M16 = 1, $F15, M18 + M19 - M20) -> 91213.689 | N21: =IF(N16 = 1, $F15, N18 + N19 - N20) -> 86653.004 | O21: =IF(O16 = 1, $F15, O18 + O19 - O20) -> 82320.354 | P21: =IF(P16 = 1, $F15, P18 + P19 - P20) -> 78204.336 | Q21: =IF(Q16 = 1, $F15, Q18 + Q19 - Q20) -> 74294.12 | ... CO21: =IF(CO16 = 1, $F15, CO18 + CO19 - CO20) -> 0
A23: TAX PAID
E24: =FinStat!E$11 -> EBITDA | F24: =FinStat!F$11 -> 0 | G24: =FinStat!G$11 -> $ 000s | H24: =FinStat!H$11 -> 789195.2 | I24: =FinStat!I$11 -> 0 | J24: =FinStat!J$11 -> 0 | K24: =FinStat!K$11 -> 0 | L24: =FinStat!L$11 -> 5642.6251 | ... CO24: =FinStat!CO$11 -> 0
D25: less | E25: =E$11 -> Tax depreciation | F25: =F$11 -> 0 | G25: =G$11 -> $ 000s | H25: =H$11 -> 109067.8 | I25: =I$11 -> 0 | J25: =J$11 -> 0 | K25: =K$11 -> 0 | L25: =L$11 -> 5053.39 | ... CO25: =CO$11 -> 0
D26: less | E26: Interest due (senior debt and shareholder loan) | G26: =SMU -> $ 000s | H26: =SUM(J26:CO26) -> 47907.655 | J26: =Debt!J$33+SHL!J$20 -> 0 | K26: =Debt!K$33+SHL!K$20 -> 0 | L26: =Debt!L$33+SHL!L$20 -> 1606.2098 | M26: =Debt!M$33+SHL!M$20 -> 1617.6543 | N26: =Debt!N$33+SHL!N$20 -> 1616.3464 | O26: =Debt!O$33+SHL!O$20 -> 1596.298 | P26: =Debt!P$33+SHL!P$20 -> 1542.9469 | Q26: =Debt!Q$33+SHL!Q$20 -> 1539.5843 | ... CO26: =Debt!CO$33+SHL!CO$20 -> -1.7639637e-12
E27: Taxable income | G27: =SMU -> $ 000s | H27: =SUM(J27:CO27) -> 632219.75 | J27: =J24 - J25 - J26 -> 0 | K27: =K24 - K25 - K26 -> 0 | L27: =L24 - L25 - L26 -> -1016.9746 | M27: =M24 - M25 - M26 -> -1171.6175 | N27: =N24 - N25 - N26 -> -407.1307 | O27: =O24 - O25 - O26 -> -544.05406 | P27: =P24 - P25 - P26 -> 250.26942 | Q27: =Q24 - Q25 - Q26 -> 68.073383 | ... CO27: =CO24 - CO25 - CO26 -> 1.7639637e-12
E29: =InpC!E$86 -> Corporation tax rate | F29: =InpC!F$86 -> 0.3 | G29: =InpC!G$86 -> %
E30: =E$27 -> Taxable income | F30: =F$27 -> 0 | G30: =G$27 -> $ 000s | H30: =H$27 -> 632219.75 | I30: =I$27 -> 0 | J30: =J$27 -> 0 | K30: =K$27 -> 0 | L30: =L$27 -> -1016.9746 | ... CO30: =CO$27 -> 1.7639637e-12
E31: Tax paid POS | G31: =SMU -> $ 000s | H31: =SUM(J31:CO31) -> 189665.92 | J31: =$F29 * J30 -> 0 | K31: =$F29 * K30 -> 0 | L31: =$F29 * L30 -> -305.09239 | M31: =$F29 * M30 -> -351.48526 | N31: =$F29 * N30 -> -122.13921 | O31: =$F29 * O30 -> -163.21622 | P31: =$F29 * P30 -> 75.080825 | Q31: =$F29 * Q30 -> 20.422015 | ... CO31: =$F29 * CO30 -> 5.2918912e-13
E32: =LEFT(E31, LEN(E31) - 4) -> Tax paid | F32: CF | G32: =G31 -> $ 000s | H32: =SUM(J32:CO32) -> -189665.92 | J32: =-1 * J31 -> 0 | K32: =-1 * K31 -> 0 | L32: =-1 * L31 -> 305.09239 | M32: =-1 * M31 -> 351.48526 | N32: =-1 * N31 -> 122.13921 | O32: =-1 * O31 -> 163.21622 | P32: =-1 * P31 -> -75.080825 | Q32: =-1 * Q31 -> -20.422015 | ... CO32: =-1 * CO31 -> -5.2918912e-13
A34: TAX EXPENSE
E35: =InpC!E$86 -> Corporation tax rate | F35: =InpC!F$86 -> 0.3 | G35: =InpC!G$86 -> %
E36: =FinStat!E$16 -> Profit before tax | F36: =FinStat!F$16 -> 0 | G36: =FinStat!G$16 -> $ 000s | H36: =FinStat!H$16 -> 632219.75 | I36: =FinStat!I$16 -> 0 | J36: =FinStat!J$16 -> 0 | K36: =FinStat!K$16 -> 0 | L36: =FinStat!L$16 -> 2351.952 | ... CO36: =FinStat!CO$16 -> 1.7639637e-12
E37: Tax expense POS | G37: =SMU -> $ 000s | H37: =SUM(J37:CO37) -> 189665.92 | J37: =$F35 * J36 -> 0 | K37: =$F35 * K36 -> 0 | L37: =$F35 * L36 -> 705.5856 | M37: =$F35 * M36 -> 583.39189 | N37: =$F35 * N36 -> 740.72713 | O37: =$F35 * O36 -> 631.23985 | P37: =$F35 * P36 -> 804.54714 | Q37: =$F35 * Q36 -> 688.14807 | ... CO37: =$F35 * CO36 -> 5.2918912e-13
E38: =LEFT(E37, LEN(E37) - 4) -> Tax expense | F38: IS | G38: =G37 -> $ 000s | H38: =SUM(J38:CO38) -> -189665.92 | J38: =-1 * J37 -> 0 | K38: =-1 * K37 -> 0 | L38: =-1 * L37 -> -705.5856 | M38: =-1 * M37 -> -583.39189 | N38: =-1 * N37 -> -740.72713 | O38: =-1 * O37 -> -631.23985 | P38: =-1 * P37 -> -804.54714 | Q38: =-1 * Q37 -> -688.14807 | ... CO38: =-1 * CO37 -> -5.2918912e-13
A41: DEFERRED TAX BALANCE
E43: Deferred tax - initial balance | F43: 0
E44: =Time!E$45 -> Acquisition / initial balance date flag | F44: =Time!F$45 -> 0 | G44: =Time!G$45 -> flag | H44: =Time!H$45 -> 1 | I44: =Time!I$45 -> 0 | J44: =Time!J$45 -> 0 | K44: =Time!K$45 -> 1 | L44: =Time!L$45 -> 0 | ... CO44: =Time!CO$45 -> 0
E46: Deferred tax balance BEG | G46: $ 000s | J46: =I49 -> 0 | K46: =J49 -> 0 | L46: =K49 -> 0 | M46: =L49 -> 1010.678 | N46: =M49 -> 1945.5551 | O46: =N49 -> 2808.4215 | P46: =O49 -> 3602.8775 | Q46: =P49 -> 4332.3439 | ... CO46: =CN49 -> -4.5474735e-12
D47: plus | E47: =E$37 -> Tax expense POS | F47: =F$37 -> 0 | G47: =G$37 -> $ 000s | H47: =H$37 -> 189665.92 | I47: =I$37 -> 0 | J47: =J$37 -> 0 | K47: =K$37 -> 0 | L47: =L$37 -> 705.5856 | ... CO47: =CO$37 -> 5.2918912e-13
D48: less | E48: =E$31 -> Tax paid POS | F48: =F$31 -> 0 | G48: =G$31 -> $ 000s | H48: =H$31 -> 189665.92 | I48: =I$31 -> 0 | J48: =J$31 -> 0 | K48: =K$31 -> 0 | L48: =L$31 -> -305.09239 | ... CO48: =CO$31 -> 5.2918912e-13
E49: Deferred tax balance | F49: BS | G49: $ 000s | J49: =IF(J44 = 1, $F43, J46 + J47 - J48) -> 0 | K49: =IF(K44 = 1, $F43, K46 + K47 - K48) -> 0 | L49: =IF(L44 = 1, $F43, L46 + L47 - L48) -> 1010.678 | M49: =IF(M44 = 1, $F43, M46 + M47 - M48) -> 1945.5551 | N49: =IF(N44 = 1, $F43, N46 + N47 - N48) -> 2808.4215 | O49: =IF(O44 = 1, $F43, O46 + O47 - O48) -> 3602.8775 | P49: =IF(P44 = 1, $F43, P46 + P47 - P48) -> 4332.3439 | Q49: =IF(Q44 = 1, $F43, Q46 + Q47 - Q48) -> 5000.0699 | ... CO49: =IF(CO44 = 1, $F43, CO46 + CO47 - CO48) -> -4.5474735e-12
A51: TAX BEFORE INTEREST DEDUCTION (used only for sizing debt)
E52: Taxable income before interest deduction | G52: =SMU -> $ 000s | H52: =SUM(J52:CO52) -> 680127.4 | J52: =J24-J25 -> 0 | K52: =K24-K25 -> 0 | L52: =L24-L25 -> 589.23514 | M52: =M24-M25 -> 446.03681 | N52: =N24-N25 -> 1209.2157 | O52: =O24-O25 -> 1052.2439 | P52: =P24-P25 -> 1793.2163 | Q52: =Q24-Q25 -> 1607.6577 | ... CO52: =CO24-CO25 -> 0
E53: Tax paid before interest deduction POS (for debt sizing) | G53: =SMU -> $ 000s | H53: =SUM(J53:CO53) -> 204038.22 | J53: =$F29*J52 -> 0 | K53: =$F29*K52 -> 0 | L53: =$F29*L52 -> 176.77054 | M53: =$F29*M52 -> 133.81104 | N53: =$F29*N52 -> 362.7647 | O53: =$F29*O52 -> 315.67318 | P53: =$F29*P52 -> 537.96488 | Q53: =$F29*Q52 -> 482.29731 | ... CO53: =$F29*CO52 -> 0

Sheet NCA
A1: =RIGHT(CELL("filename", A1), LEN(CELL("filename", A1)) - SEARCH("]", CELL("filename", A1)))
E2: =Time!E$25 -> Model period ending | J2: =Time!J$25 -> 44469 | K2: =Time!K$25 -> 44561 | L2: =Time!L$25 -> 44651 | M2: =Time!M$25 -> 44742 | N2: =Time!N$25 -> 44834 | O2: =Time!O$25 -> 44926 | P2: =Time!P$25 -> 45016 | Q2: =Time!Q$25 -> 45107 | ... CO2: =Time!CO$25 -> 52047
E3: =Time!E$111 -> Timeline label | J3: =Time!J$111 -> Pre-fcst | K3: =Time!K$111 -> Fin close | L3: =Time!L$111 -> Forecast | M3: =Time!M$111 -> Forecast | N3: =Time!N$111 -> Forecast | O3: =Time!O$111 -> Forecast | P3: =Time!P$111 -> Forecast | Q3: =Time!Q$111 -> Forecast | ... CO3: =Time!CO$111 -> Post-fcst
E4: =Time!E$37 -> Financial year ending | J4: =Time!J$37 -> 2021 | K4: =Time!K$37 -> 2021 | L4: =Time!L$37 -> 2022 | M4: =Time!M$37 -> 2022 | N4: =Time!N$37 -> 2022 | O4: =Time!O$37 -> 2022 | P4: =Time!P$37 -> 2023 | Q4: =Time!Q$37 -> 2023 | ... CO4: =Time!CO$37 -> 2042
E5: =Time!E$10 -> Model column counter | F5: Constant | G5: Unit | H5: Total | J5: =Time!J$10 -> 1 | K5: =Time!K$10 -> 2 | L5: =Time!L$10 -> 3 | M5: =Time!M$10 -> 4 | N5: =Time!N$10 -> 5 | O5: =Time!O$10 -> 6 | P5: =Time!P$10 -> 7 | Q5: =Time!Q$10 -> 8 | ... CO5: =Time!CO$10 -> 84
A7: CAPITAL EXPENDITURE
E9: =InpC!E$55 -> Investment / addition date | F9: =InpC!F$55 -> $000s | G9: =InpC!G$55 -> 0
E10: =InpC!E$56 -> 45291 | F10: =InpC!F$56 -> 2000 | G10: =InpC!G$56 -> $ 000s
E11: =InpC!E$57 -> 45657 | F11: =InpC!F$57 -> 1000 | G11: =InpC!G$57 -> $ 000s
E12: =InpC!E$58 -> 46022 | F12: =InpC!F$58 -> 1500 | G12: =InpC!G$58 -> $ 000s
E13: =InpC!E$59 -> 46387 | F13: =InpC!F$59 -> 1000 | G13: =InpC!G$59 -> $ 000s
E14: =InpC!E$60 -> 46752 | F14: =InpC!F$60 -> 500 | G14: =InpC!G$60 -> $ 000s
E15: =InpC!E$61 -> 47118 | F15: =InpC!F$61 -> 1000 | G15: =InpC!G$61 -> $ 000s
E16: =InpC!E$62 -> 47483 | F16: =InpC!F$62 -> 1000 | G16: =InpC!G$62 -> $ 000s
E17: =Time!E$25 -> Model period ending | F17: =Time!F$25 -> 0 | G17: =Time!G$25 -> date | H17: =Time!H$25 -> 0 | I17: =Time!I$25 -> 0 | J17: =Time!J$25 -> 44469 | K17: =Time!K$25 -> 44561 | L17: =Time!L$25 -> 44651 | ... CO17: =Time!CO$25 -> 52047
E18: Capital expenditure POS | G18: =SMU -> $ 000s | H18: =SUM(J18:CO18) -> 8000 | J18: =_xlfn.IFNA(VLOOKUP(J17, $E10:$F16, 2,FALSE),0) -> 0 | K18: =_xlfn.IFNA(VLOOKUP(K17, $E10:$F16, 2,FALSE),0) -> 0 | L18: =_xlfn.IFNA(VLOOKUP(L17, $E10:$F16, 2,FALSE),0) -> 0 | M18: =_xlfn.IFNA(VLOOKUP(M17, $E10:$F16, 2,FALSE),0) -> 0 | N18: =_xlfn.IFNA(VLOOKUP(N17, $E10:$F16, 2,FALSE),0) -> 0 | O18: =_xlfn.IFNA(VLOOKUP(O17, $E10:$F16, 2,FALSE),0) -> 0 | P18: =_xlfn.IFNA(VLOOKUP(P17, $E10:$F16, 2,FALSE),0) -> 0 | Q18: =_xlfn.IFNA(VLOOKUP(Q17, $E10:$F16, 2,FALSE),0) -> 0 | ... CO18: =_xlfn.IFNA(VLOOKUP(CO17, $E10:$F16, 2,FALSE),0) -> 0
E19: =LEFT(E18, LEN(E18) - 4) -> Capital expenditure | F19: CF | G19: =G18 -> $ 000s | H19: =SUM(J19:CO19) -> -8000 | J19: =-1 * J18 -> 0 | K19: =-1 * K18 -> 0 | L19: =-1 * L18 -> 0 | M19: =-1 * M18 -> 0 | N19: =-1 * N18 -> 0 | O19: =-1 * O18 -> 0 | P19: =-1 * P18 -> 0 | Q19: =-1 * Q18 -> 0 | ... CO19: =-1 * CO18 -> 0
A22: ACCOUNTING DEPRECIATION
C24: Accounting depreciation - Initial balance
E25: =InpC!E$64 -> Non current asset - initial balance | F25: =InpC!F$64 -> 101067.8 | G25: =InpC!G$64 -> $ 000s
E26: =InpC!E$65 -> Useful life of NCA at acquisition | F26: =InpC!F$65 -> 15 | G26: =InpC!G$65 -> years
E27: =InpC!E$99 -> No of periods in a year | F27: =InpC!F$99 -> 4 | G27: =InpC!G$99 -> periods
E28: =Time!E$95 -> Depreciation period flag | F28: =Time!F$95 -> 0 | G28: =Time!G$95 -> flag | H28: =Time!H$95 -> 60 | I28: =Time!I$95 -> 0 | J28: =Time!J$95 -> 0 | K28: =Time!K$95 -> 0 | L28: =Time!L$95 -> 1 | ... CO28: =Time!CO$95 -> 0
E29: Accounting depreciation - Initial balance | G29: =SMU -> $ 000s | H29: =SUM(J29:CO29) -> 101067.8 | J29: =IF(J28 = 1, $F25 / ( $F26 * $F27),0) -> 0 | K29: =IF(K28 = 1, $F25 / ( $F26 * $F27),0) -> 0 | L29: =IF(L28 = 1, $F25 / ( $F26 * $F27),0) -> 1684.4633 | M29: =IF(M28 = 1, $F25 / ( $F26 * $F27),0) -> 1684.4633 | N29: =IF(N28 = 1, $F25 / ( $F26 * $F27),0) -> 1684.4633 | O29: =IF(O28 = 1, $F25 / ( $F26 * $F27),0) -> 1684.4633 | P29: =IF(P28 = 1, $F25 / ( $F26 * $F27),0) -> 1684.4633 | Q29: =IF(Q28 = 1, $F25 / ( $F26 * $F27),0) -> 1684.4633 | ... CO29: =IF(CO28 = 1, $F25 / ( $F26 * $F27),0) -> 0
C31: Accounting depreciation - capex
E32: =InpC!E$67 -> Useful life -capex | F32: =InpC!F$67 -> 5 | G32: =InpC!G$67 -> yrs
E33: =InpC!E$99 -> No of periods in a year | F33: =InpC!F$99 -> 4 | G33: =InpC!G$99 -> periods
E34: Periodic useful life | F34: =F32 * F33 -> 20 | G34: periods
E36: =E$34 -> Periodic useful life | F36: =F$34 -> 20 | G36: =G$34 -> periods
E37: =Time!E$10 -> Model column counter | F37: =Time!F$10 -> 0 | G37: =Time!G$10 -> counter | H37: =Time!H$10 -> 0 | I37: =Time!I$10 -> 0 | J37: =Time!J$10 -> 1 | K37: =Time!K$10 -> 2 | L37: =Time!L$10 -> 3 | ... CO37: =Time!CO$10 -> 84
E38: =E$18 -> Capital expenditure POS | F38: =F$18 -> 0 | G38: =G$18 -> $ 000s | H38: =H$18 -> 8000 | I38: =I$18 -> 0 | J38: =J$18 -> 0 | K38: =K$18 -> 0 | L38: =L$18 -> 0 | ... CO38: =CO$18 -> 0
E39: Retirement of capex | G39: =SMU -> $ 000s | H39: =SUM(J39:CO39) -> 8000 | J39: =SUMIFS($J38:J38, $J37:J37, J37 - $F36) -> 0 | K39: =SUMIFS($J38:K38, $J37:K37, K37 - $F36) -> 0 | L39: =SUMIFS($J38:L38, $J37:L37, L37 - $F36) -> 0 | M39: =SUMIFS($J38:M38, $J37:M37, M37 - $F36) -> 0 | N39: =SUMIFS($J38:N38, $J37:N37, N37 - $F36) -> 0 | O39: =SUMIFS($J38:O38, $J37:O37, O37 - $F36) -> 0 | P39: =SUMIFS($J38:P38, $J37:P37, P37 - $F36) -> 0 | Q39: =SUMIFS($J38:Q38, $J37:Q37, Q37 - $F36) -> 0 | ... CO39: =SUMIFS($J38:CO38, $J37:CO37, CO37 - $F36) -> 0
E41: Capex depreciable balance BEG | G41: =SMU -> $ 000s | J41: =I44 -> 0 | K41: =J44 -> 0 | L41: =K44 -> 0 | M41: =L44 -> 0 | N41: =M44 -> 0 | O41: =N44 -> 0 | P41: =O44 -> 0 | Q41: =P44 -> 0 | ... CO41: =CN44 -> 0
D42: plus | E42: =E$18 -> Capital expenditure POS | F42: =F$18 -> 0 | G42: =G$18 -> $ 000s | H42: =H$18 -> 8000 | I42: =I$18 -> 0 | J42: =J$18 -> 0 | K42: =K$18 -> 0 | L42: =L$18 -> 0 | ... CO42: =CO$18 -> 0
D43: less | E43: =E$39 -> Retirement of capex | F43: =F$39 -> 0 | G43: =G$39 -> $ 000s | H43: =H$39 -> 8000 | I43: =I$39 -> 0 | J43: =J$39 -> 0 | K43: =K$39 -> 0 | L43: =L$39 -> 0 | ... CO43: =CO$39 -> 0
E44: Capex depreciable balance END | G44: =SMU -> $ 000s | J44: =J41 + J42 - J43 -> 0 | K44: =K41 + K42 - K43 -> 0 | L44: =L41 + L42 - L43 -> 0 | M44: =M41 + M42 - M43 -> 0 | N44: =N41 + N42 - N43 -> 0 | O44: =O41 + O42 - O43 -> 0 | P44: =P41 + P42 - P43 -> 0 | Q44: =Q41 + Q42 - Q43 -> 0 | ... CO44: =CO41 + CO42 - CO43 -> 0
E46: =E$34 -> Periodic useful life | F46: =F$34 -> 20 | G46: =G$34 -> periods
E47: =E$41 -> Capex depreciable balance BEG | F47: =F$41 -> 0 | G47: =G$41 -> $ 000s | H47: =H$41 -> 0 | I47: =I$41 -> 0 | J47: =J$41 -> 0 | K47: =K$41 -> 0 | L47: =L$41 -> 0 | ... CO47: =CO$41 -> 0
E48: Accounting depreciation - capex | G48: =SMU -> $ 000s | H48: =SUM(J48:CO48) -> 8000 | J48: =J47 / $F46 -> 0 | K48: =K47 / $F46 -> 0 | L48: =L47 / $F46 -> 0 | M48: =M47 / $F46 -> 0 | N48: =N47 / $F46 -> 0 | O48: =O47 / $F46 -> 0 | P48: =P47 / $F46 -> 0 | Q48: =Q47 / $F46 -> 0 | ... CO48: =CO47 / $F46 -> 0
A50: Summary of accounting depreciation
E51: =E$29 -> Accounting depreciation - Initial balance | F51: =F$29 -> 0 | G51: =G$29 -> $ 000s | H51: =H$29 -> 101067.8 | I51: =I$29 -> 0 | J51: =J$29 -> 0 | K51: =K$29 -> 0 | L51: =L$29 -> 1684.4633 | ... CO51: =CO$29 -> 0
E52: =E$48 -> Accounting depreciation - capex | F52: =F$48 -> 0 | G52: =G$48 -> $ 000s | H52: =H$48 -> 8000 | I52: =I$48 -> 0 | J52: =J$48 -> 0 | K52: =K$48 -> 0 | L52: =L$48 -> 0 | ... CO52: =CO$48 -> 0
E53: Accounting depreciation POS | G53: =SMU -> $ 000s | H53: =SUM(J53:CO53) -> 109067.8 | J53: =SUM(J51:J52) -> 0 | K53: =SUM(K51:K52) -> 0 | L53: =SUM(L51:L52) -> 1684.4633 | M53: =SUM(M51:M52) -> 1684.4633 | N53: =SUM(N51:N52) -> 1684.4633 | O53: =SUM(O51:O52) -> 1684.4633 | P53: =SUM(P51:P52) -> 1684.4633 | Q53: =SUM(Q51:Q52) -> 1684.4633 | ... CO53: =SUM(CO51:CO52) -> 0
E54: =LEFT(E53, LEN(E53) - 4) -> Accounting depreciation | F54: IS | G54: =G53 -> $ 000s | H54: =SUM(J54:CO54) -> -109067.8 | J54: =-1 * J53 -> 0 | K54: =-1 * K53 -> 0 | L54: =-1 * L53 -> -1684.4633 | M54: =-1 * M53 -> -1684.4633 | N54: =-1 * N53 -> -1684.4633 | O54: =-1 * O53 -> -1684.4633 | P54: =-1 * P53 -> -1684.4633 | Q54: =-1 * Q53 -> -1684.4633 | ... CO54: =-1 * CO53 -> 0
A56: NON CURRENT ASSET BALANCE
E58: =InpC!E$64 -> Non current asset - initial balance | F58: =InpC!F$64 -> 101067.8 | G58: =InpC!G$64 -> $ 000s
E59: =Time!E$45 -> Acquisition / initial balance date flag | F59: =Time!F$45 -> 0 | G59: =Time!G$45 -> flag | H59: =Time!H$45 -> 1 | I59: =Time!I$45 -> 0 | J59: =Time!J$45 -> 0 | K59: =Time!K$45 -> 1 | L59: =Time!L$45 -> 0 | ... CO59: =Time!CO$45 -> 0
E61: Non current asset balance BEG | G61: $ 000s | J61: =I64 -> 0 | K61: =J64 -> 0 | L61: =K64 -> 101067.8 | M61: =L64 -> 99383.336 | N61: =M64 -> 97698.873 | O61: =N64 -> 96014.409 | P61: =O64 -> 94329.946 | Q61: =P64 -> 92645.483 | ... CO61: =CN64 -> 8.2309271e-11
D62: plus | E62: =E$18 -> Capital expenditure POS | F62: =F$18 -> 0 | G62: =G$18 -> $ 000s | H62: =H$18 -> 8000 | I62: =I$18 -> 0 | J62: =J$18 -> 0 | K62: =K$18 -> 0 | L62: =L$18 -> 0 | ... CO62: =CO$18 -> 0
D63: less | E63: =E$53 -> Accounting depreciation POS | F63: =F$53 -> 0 | G63: =G$53 -> $ 000s | H63: =H$53 -> 109067.8 | I63: =I$53 -> 0 | J63: =J$53 -> 0 | K63: =K$53 -> 0 | L63: =L$53 -> 1684.4633 | ... CO63: =CO$53 -> 0
E64: Non current asset balance | G64: $ 000s | J64: =IF(J59 = 1, $F58, J61 + J62 - J63) -> 0 | K64: =IF(K59 = 1, $F58, K61 + K62 - K63) -> 101067.8 | L64: =IF(L59 = 1, $F58, L61 + L62 - L63) -> 99383.336 | M64: =IF(M59 = 1, $F58, M61 + M62 - M63) -> 97698.873 | N64: =IF(N59 = 1, $F58, N61 + N62 - N63) -> 96014.409 | O64: =IF(O59 = 1, $F58, O61 + O62 - O63) -> 94329.946 | P64: =IF(P59 = 1, $F58, P61 + P62 - P63) -> 92645.483 | Q64: =IF(Q59 = 1, $F58, Q61 + Q62 - Q63) -> 90961.019 | ... CO64: =IF(CO59 = 1, $F58, CO61 + CO62 - CO63) -> 8.2309271e-11

Sheet Debt
A1: =RIGHT(CELL("filename", A1), LEN(CELL("filename", A1)) - SEARCH("]", CELL("filename", A1)))
E2: =Time!E$25 -> Model period ending | J2: =Time!J$25 -> 44469 | K2: =Time!K$25 -> 44561 | L2: =Time!L$25 -> 44651 | M2: =Time!M$25 -> 44742 | N2: =Time!N$25 -> 44834 | O2: =Time!O$25 -> 44926 | P2: =Time!P$25 -> 45016 | Q2: =Time!Q$25 -> 45107 | ... CO2: =Time!CO$25 -> 52047
E3: =Time!E$111 -> Timeline label | J3: =Time!J$111 -> Pre-fcst | K3: =Time!K$111 -> Fin close | L3: =Time!L$111 -> Forecast | M3: =Time!M$111 -> Forecast | N3: =Time!N$111 -> Forecast | O3: =Time!O$111 -> Forecast | P3: =Time!P$111 -> Forecast | Q3: =Time!Q$111 -> Forecast | ... CO3: =Time!CO$111 -> Post-fcst
E4: =Time!E$37 -> Financial year ending | J4: =Time!J$37 -> 2021 | K4: =Time!K$37 -> 2021 | L4: =Time!L$37 -> 2022 | M4: =Time!M$37 -> 2022 | N4: =Time!N$37 -> 2022 | O4: =Time!O$37 -> 2022 | P4: =Time!P$37 -> 2023 | Q4: =Time!Q$37 -> 2023 | ... CO4: =Time!CO$37 -> 2042
E5: =Time!E$10 -> Model column counter | F5: Constant | G5: Unit | H5: Total | J5: =Time!J$10 -> 1 | K5: =Time!K$10 -> 2 | L5: =Time!L$10 -> 3 | M5: =Time!M$10 -> 4 | N5: =Time!N$10 -> 5 | O5: =Time!O$10 -> 6 | P5: =Time!P$10 -> 7 | Q5: =Time!Q$10 -> 8 | ... CO5: =Time!CO$10 -> 84
A7: SENIOR DEBT PRINCIPAL REPAYMENT
E9: =InpC!E$64 -> Non current asset - initial balance | F9: =InpC!F$64 -> 101067.8 | G9: =InpC!G$64 -> $ 000s
E10: =InpC!E$72 -> % of NCA financed with debt | F10: =InpC!F$72 -> 0.71391903 | G10: =InpC!G$72 -> %
E11: Senior debt - Initial balance | F11: =Constr!$F$53 -> 72154.225 | G11: =SMU -> $ 000s
E13: =InpC!E$74 -> Senior debt principal repayment profile selection | F13: =InpC!F$74 -> 4 | G13: =InpC!G$74 -> switch
E14: =InpS!E$18 -> Senior debt profile 1 - 7.5 years | F14: =InpS!F$18 -> 0 | G14: =InpS!G$18 -> % | H14: =InpS!H$18 -> 1 | I14: =InpS!I$18 -> 0 | J14: =InpS!J$18 -> 0 | K14: =InpS!K$18 -> 0 | L14: =InpS!L$18 -> 0 | ... CO14: =InpS!CO$18 -> 0
E15: =InpS!E$19 -> Senior debt profile 2 - 10 years | F15: =InpS!F$19 -> 0 | G15: =InpS!G$19 -> % | H15: =InpS!H$19 -> 1 | I15: =InpS!I$19 -> 0 | J15: =InpS!J$19 -> 0 | K15: =InpS!K$19 -> 0 | L15: =InpS!L$19 -> 0 | ... CO15: =InpS!CO$19 -> 0
E16: =InpS!E$20 -> Senior debt profile 3 - 15 years | F16: =InpS!F$20 -> 0 | G16: =InpS!G$20 -> % | H16: =InpS!H$20 -> 1 | I16: =InpS!I$20 -> 0 | J16: =InpS!J$20 -> 0 | K16: =InpS!K$20 -> 0 | L16: =InpS!L$20 -> 0 | ... CO16: =InpS!CO$20 -> 0
E17: Senior debt profile 4 - sculpted | G17: % | H17: =SUM(J17:CO17) -> 1 | J17: =Sculpt!J$40 -> 0 | K17: =Sculpt!K$40 -> 0 | L17: =Sculpt!L$40 -> 0.014647637 | M17: =Sculpt!M$40 -> 0.015922741 | N17: =Sculpt!N$40 -> 0.016727014 | O17: =Sculpt!O$40 -> 0.015905264 | P17: =Sculpt!P$40 -> 0.017297166 | Q17: =Sculpt!Q$40 -> 0.016398201 | ... CO17: =Sculpt!CO$40 -> 2.6518181e-17
E18: {=INDEX(E14:E17,F13)&" - active"} -> Senior debt profile 4 - sculpted - active | G18: % | J18: =INDEX(J14:J17,$F13) -> 0 | K18: =INDEX(K14:K17,$F13) -> 0 | L18: =INDEX(L14:L17,$F13) -> 0.014647637 | M18: =INDEX(M14:M17,$F13) -> 0.015922741 | N18: =INDEX(N14:N17,$F13) -> 0.016727014 | O18: =INDEX(O14:O17,$F13) -> 0.015905264 | P18: =INDEX(P14:P17,$F13) -> 0.017297166 | Q18: =INDEX(Q14:Q17,$F13) -> 0.016398201 | ... CO18: =INDEX(CO14:CO17,$F13) -> 2.6518181e-17
E20: =E$11 -> Senior debt - Initial balance | F20: =F$11 -> 72154.225 | G20: =G$11 -> $ 000s
E21: =E$18 -> Senior debt profile 4 - sculpted - active | F21: =F$18 -> 0 | G21: =G$18 -> % | H21: =H$18 -> 0 | I21: =I$18 -> 0 | J21: =J$18 -> 0 | K21: =K$18 -> 0 | L21: =L$18 -> 0.014647637 | ... CO21: =CO$18 -> 2.6518181e-17
E22: Senior debt principal repayment POS | G22: =SMU -> $ 000s | H22: =SUM(J22:CO22) -> 72154.225 | J22: =$F20 * J21 -> 0 | K22: =$F20 * K21 -> 0 | L22: =$F20 * L21 -> 1056.8889 | M22: =$F20 * M21 -> 1148.893 | N22: =$F20 * N21 -> 1206.9248 | O22: =$F20 * O21 -> 1147.632 | P22: =$F20 * P21 -> 1248.0636 | Q22: =$F20 * Q21 -> 1183.1995 | ... CO22: =$F20 * CO21 -> 1.9133988e-12
E23: =LEFT(E22, LEN(E22) - 4) -> Senior debt principal repayment | F23: CF | G23: =G22 -> $ 000s | H23: =SUM(J23:CO23) -> -72154.225 | J23: =-1 * J22 -> 0 | K23: =-1 * K22 -> 0 | L23: =-1 * L22 -> -1056.8889 | M23: =-1 * M22 -> -1148.893 | N23: =-1 * N22 -> -1206.9248 | O23: =-1 * O22 -> -1147.632 | P23: =-1 * P22 -> -1248.0636 | Q23: =-1 * Q22 -> -1183.1995 | ... CO23: =-1 * CO22 -> -1.9133988e-12
A25: SENIOR DEBT INTEREST PAYMENT
E26: =InpC!E$77 -> All in annual senior debt interest rate | F26: =InpC!F$77 -> 0.065 | G26: =InpC!G$77 -> %
E27: =InpC!E$79 -> Day count convention | F27: =InpC!F$79 -> 360 | G27: =InpC!G$79 -> days
E28: =Time!E$30 -> Days in model period | F28: =Time!F$30 -> 0 | G28: =Time!G$30 -> days | H28: =Time!H$30 -> 0 | I28: =Time!I$30 -> 0 | J28: =Time!J$30 -> 92 | K28: =Time!K$30 -> 92 | L28: =Time!L$30 -> 90 | ... CO28: =Time!CO$30 -> 91
E29: Periodic interest rate | G29: % | J29: =$F26 / $F27 * J28 -> 0.016611111 | K29: =$F26 / $F27 * K28 -> 0.016611111 | L29: =$F26 / $F27 * L28 -> 0.01625 | M29: =$F26 / $F27 * M28 -> 0.016430556 | N29: =$F26 / $F27 * N28 -> 0.016611111 | O29: =$F26 / $F27 * O28 -> 0.016611111 | P29: =$F26 / $F27 * P28 -> 0.01625 | Q29: =$F26 / $F27 * Q28 -> 0.016430556 | ... CO29: =$F26 / $F27 * CO28 -> 0.016430556
E31: =E$42 -> Senior debt balance BEG | F31: =F$42 -> 0 | G31: =G$42 -> $ 000s | H31: =H$42 -> 0 | I31: =I$42 -> 0 | J31: =J$42 -> 0 | K31: =K$42 -> 0 | L31: =L$42 -> 72154.225 | ... CO31: =CO$42 -> -1.0735874e-10
E32: =E$29 -> Periodic interest rate | F32: =F$29 -> 0 | G32: =G$29 -> % | H32: =H$29 -> 0 | I32: =I$29 -> 0 | J32: =J$29 -> 0.016611111 | K32: =K$29 -> 0.016611111 | L32: =L$29 -> 0.01625 | ... CO32: =CO$29 -> 0.016430556
E33: Senior debt interest payment POS | G33: =SMU -> $ 000s | H33: =SUM(J33:CO33) -> 29083.355 | J33: =J31 * J32 -> 0 | K33: =K31 * K32 -> 0 | L33: =L31 * L32 -> 1172.5062 | M33: =M31 * M32 -> 1168.1687 | N33: =N31 * N32 -> 1161.9214 | O33: =O31 * O32 -> 1141.873 | P33: =P31 * P32 -> 1098.4006 | Q33: =Q31 * Q32 -> 1090.0987 | ... CO33: =CO31 * CO32 -> -1.7639637e-12
E34: =LEFT(E33, LEN(E33) - 4) -> Senior debt interest payment | F34: IS&CF | G34: =G33 -> $ 000s | H34: =SUM(J34:CO34) -> -29083.355 | J34: =-1 * J33 -> 0 | K34: =-1 * K33 -> 0 | L34: =-1 * L33 -> -1172.5062 | M34: =-1 * M33 -> -1168.1687 | N34: =-1 * N33 -> -1161.9214 | O34: =-1 * O33 -> -1141.873 | P34: =-1 * P33 -> -1098.4006 | Q34: =-1 * Q33 -> -1090.0987 | ... CO34: =-1 * CO33 -> 1.7639637e-12
A37: SENIOR DEBT BALANCE
E39: =E$11 -> Senior debt - Initial balance | F39: =F$11 -> 72154.225 | G39: =G$11 -> $ 000s
E40: =Time!E$45 -> Acquisition / initial balance date flag | F40: =Time!F$45 -> 0 | G40: =Time!G$45 -> flag | H40: =Time!H$45 -> 1 | I40: =Time!I$45 -> 0 | J40: =Time!J$45 -> 0 | K40: =Time!K$45 -> 1 | L40: =Time!L$45 -> 0 | ... CO40: =Time!CO$45 -> 0
E42: Senior debt balance BEG | G42: $ 000s | J42: =I45 -> 0 | K42: =J45 -> 0 | L42: =K45 -> 72154.225 | M42: =L45 -> 71097.336 | N42: =M45 -> 69948.443 | O42: =N45 -> 68741.518 | P42: =O45 -> 67593.886 | Q42: =P45 -> 66345.822 | ... CO42: =CN45 -> -1.0735874e-10
D43: plus | E43: =InpS!E$22 -> Senior debt - additional drawdown | F43: =InpS!F$22 -> 0 | G43: =InpS!G$22 -> $ 000s | H43: =SUM(J43:CO43) -> 0 | J43: =InpS!J$22 -> 0 | K43: =InpS!K$22 -> 0 | L43: =InpS!L$22 -> 0 | M43: =InpS!M$22 -> 0 | N43: =InpS!N$22 -> 0 | O43: =InpS!O$22 -> 0 | P43: =InpS!P$22 -> 0 | Q43: =InpS!Q$22 -> 0 | ... CO43: =InpS!CO$22 -> 0
D44: less | E44: =E$22 -> Senior debt principal repayment POS | F44: =F$22 -> 0 | G44: =G$22 -> $ 000s | H44: =H$22 -> 72154.225 | I44: =I$22 -> 0 | J44: =J$22 -> 0 | K44: =K$22 -> 0 | L44: =L$22 -> 1056.8889 | ... CO44: =CO$22 -> 1.9133988e-12
E45: Senior debt balance | F45: BS | G45: $ 000s | J45: =IF(J40 = 1, $F39, J42 + J43 - J44) -> 0 | K45: =IF(K40 = 1, $F39, K42 + K43 - K44) -> 72154.225 | L45: =IF(L40 = 1, $F39, L42 + L43 - L44) -> 71097.336 | M45: =IF(M40 = 1, $F39, M42 + M43 - M44) -> 69948.443 | N45: =IF(N40 = 1, $F39, N42 + N43 - N44) -> 68741.518 | O45: =IF(O40 = 1, $F39, O42 + O43 - O44) -> 67593.886 | P45: =IF(P40 = 1, $F39, P42 + P43 - P44) -> 66345.822 | Q45: =IF(Q40 = 1, $F39, Q42 + Q43 - Q44) -> 65162.623 | ... CO45: =IF(CO40 = 1, $F39, CO42 + CO43 - CO44) -> -1.0927214e-10

Sheet Sculpt
A1: =RIGHT(CELL("filename", A1), LEN(CELL("filename", A1)) - SEARCH("]", CELL("filename", A1)))
E2: =Time!E$25 -> Model period ending | J2: =Time!J$25 -> 44469 | K2: =Time!K$25 -> 44561 | L2: =Time!L$25 -> 44651 | M2: =Time!M$25 -> 44742 | N2: =Time!N$25 -> 44834 | O2: =Time!O$25 -> 44926 | P2: =Time!P$25 -> 45016 | Q2: =Time!Q$25 -> 45107 | ... CO2: =Time!CO$25 -> 52047
E3: =Time!E$111 -> Timeline label | J3: =Time!J$111 -> Pre-fcst | K3: =Time!K$111 -> Fin close | L3: =Time!L$111 -> Forecast | M3: =Time!M$111 -> Forecast | N3: =Time!N$111 -> Forecast | O3: =Time!O$111 -> Forecast | P3: =Time!P$111 -> Forecast | Q3: =Time!Q$111 -> Forecast | ... CO3: =Time!CO$111 -> Post-fcst
E4: =Time!E$37 -> Financial year ending | J4: =Time!J$37 -> 2021 | K4: =Time!K$37 -> 2021 | L4: =Time!L$37 -> 2022 | M4: =Time!M$37 -> 2022 | N4: =Time!N$37 -> 2022 | O4: =Time!O$37 -> 2022 | P4: =Time!P$37 -> 2023 | Q4: =Time!Q$37 -> 2023 | ... CO4: =Time!CO$37 -> 2042
E5: =Time!E$10 -> Model column counter | F5: Constant | G5: Unit | H5: Total | J5: =Time!J$10 -> 1 | K5: =Time!K$10 -> 2 | L5: =Time!L$10 -> 3 | M5: =Time!M$10 -> 4 | N5: =Time!N$10 -> 5 | O5: =Time!O$10 -> 6 | P5: =Time!P$10 -> 7 | Q5: =Time!Q$10 -> 8 | ... CO5: =Time!CO$10 -> 84
A7: LOAN TIMELINE
E9: =InpC!E$139 -> Senior debt tenor | F9: =InpC!F$139 -> 40 | G9: =InpC!G$139 -> quarters
E10: Forecast period flag | G10: flag | J10: =Time!J$69 -> 0 | K10: =Time!K$69 -> 0 | L10: =Time!L$69 -> 1 | M10: =Time!M$69 -> 1 | N10: =Time!N$69 -> 1 | O10: =Time!O$69 -> 1 | P10: =Time!P$69 -> 1 | Q10: =Time!Q$69 -> 1 | ... CO10: =Time!CO$69 -> 0
E11: Operating period counter | G11: counter | J11: =I11+J10 -> 0 | K11: =J11+K10 -> 0 | L11: =K11+L10 -> 1 | M11: =L11+M10 -> 2 | N11: =M11+N10 -> 3 | O11: =N11+O10 -> 4 | P11: =O11+P10 -> 5 | Q11: =P11+Q10 -> 6 | ... CO11: =CN11+CO10 -> 80
E12: Repayment period flag | G12: flag | H12: =SUM(J12:CO12) -> 40 | J12: =IF(AND(J11>=1,J11<=$F$9),1,0) -> 0 | K12: =IF(AND(K11>=1,K11<=$F$9),1,0) -> 0 | L12: =IF(AND(L11>=1,L11<=$F$9),1,0) -> 1 | M12: =IF(AND(M11>=1,M11<=$F$9),1,0) -> 1 | N12: =IF(AND(N11>=1,N11<=$F$9),1,0) -> 1 | O12: =IF(AND(O11>=1,O11<=$F$9),1,0) -> 1 | P12: =IF(AND(P11>=1,P11<=$F$9),1,0) -> 1 | Q12: =IF(AND(Q11>=1,Q11<=$F$9),1,0) -> 1 | ... CO12: =IF(AND(CO11>=1,CO11<=$F$9),1,0) -> 0
A14: DEBT SIZING
E15: =InpC!E$140 -> Target DSCR for sculpting | F15: =InpC!F$140 -> 2.25 | G15: =InpC!G$140 -> x
E16: =InpC!E$77 -> All in annual senior debt interest rate | F16: =InpC!F$77 -> 0.065 | G16: =InpC!G$77 -> %
E17: =InpC!E$79 -> Day count convention | F17: =InpC!F$79 -> 360 | G17: =InpC!G$79 -> days
E18: Days in period | G18: days | J18: =Time!J$30 -> 92 | K18: =Time!K$30 -> 92 | L18: =Time!L$30 -> 90 | M18: =Time!M$30 -> 91 | N18: =Time!N$30 -> 92 | O18: =Time!O$30 -> 92 | P18: =Time!P$30 -> 90 | Q18: =Time!Q$30 -> 91 | ... CO18: =Time!CO$30 -> 91
E19: Periodic interest rate | G19: % | J19: =$F$16/$F$17*J18 -> 0.016611111 | K19: =$F$16/$F$17*K18 -> 0.016611111 | L19: =$F$16/$F$17*L18 -> 0.01625 | M19: =$F$16/$F$17*M18 -> 0.016430556 | N19: =$F$16/$F$17*N18 -> 0.016611111 | O19: =$F$16/$F$17*O18 -> 0.016611111 | P19: =$F$16/$F$17*P18 -> 0.01625 | Q19: =$F$16/$F$17*Q18 -> 0.016430556 | ... CO19: =$F$16/$F$17*CO18 -> 0.016430556
E20: CFADS for sizing (tax before interest deduction) | G20: $ 000s | H20: =SUM(J20:CO20) -> 577156.98 | J20: =FinStat!J$36-Tax!J$53 -> 0 | K20: =FinStat!K$36-Tax!K$53 -> 0 | L20: =FinStat!L$36-Tax!L$53 -> 5016.1389 | M20: =FinStat!M$36-Tax!M$53 -> 5213.389 | N20: =FinStat!N$36-Tax!N$53 -> 5329.9038 | O20: =FinStat!O$36-Tax!O$53 -> 5151.3863 | P20: =FinStat!P$36-Tax!P$53 -> 5279.5445 | Q20: =FinStat!Q$36-Tax!Q$53 -> 5114.9209 | ... CO20: =FinStat!CO$36-Tax!CO$53 -> 0
E21: CFADS available to lenders | G21: $ 000s | H21: =SUM(J21:CO21) -> 227784.55 | J21: =J20*J12 -> 0 | K21: =K20*K12 -> 0 | L21: =L20*L12 -> 5016.1389 | M21: =M20*M12 -> 5213.389 | N21: =N20*N12 -> 5329.9038 | O21: =O20*O12 -> 5151.3863 | P21: =P20*P12 -> 5279.5445 | Q21: =Q20*Q12 -> 5114.9209 | ... CO21: =CO20*CO12 -> 0
E22: Debt service at target DSCR | G22: $ 000s | H22: =SUM(J22:CO22) -> 101237.58 | J22: =J21/$F$15 -> 0 | K22: =K21/$F$15 -> 0 | L22: =L21/$F$15 -> 2229.395 | M22: =M21/$F$15 -> 2317.0618 | N22: =N21/$F$15 -> 2368.8461 | O22: =O21/$F$15 -> 2289.505 | P22: =P21/$F$15 -> 2346.4642 | Q22: =Q21/$F$15 -> 2273.2982 | ... CO22: =CO21/$F$15 -> 0
E23: Debt capacity balance END | G23: $ 000s | J23: =(K23+K22)/(1+K19) -> 70975.247 | K23: =(L23+L22)/(1+L19) -> 72154.225 | L23: =(M23+M22)/(1+M19) -> 71097.336 | M23: =(N23+N22)/(1+N19) -> 69948.443 | N23: =(O23+O22)/(1+O19) -> 68741.518 | O23: =(P23+P22)/(1+P19) -> 67593.886 | P23: =(Q23+Q22)/(1+Q19) -> 66345.822 | Q23: =(R23+R22)/(1+R19) -> 65162.623 | ... CO23: =(CP23+CP22)/(1+CP19) -> 0
E25: Acquisition / COD flag | G25: flag | J25: =Time!J$45 -> 0 | K25: =Time!K$45 -> 1 | L25: =Time!L$45 -> 0 | M25: =Time!M$45 -> 0 | N25: =Time!N$45 -> 0 | O25: =Time!O$45 -> 0 | P25: =Time!P$45 -> 0 | Q25: =Time!Q$45 -> 0 | ... CO25: =Time!CO$45 -> 0
E26: Debt capacity at COD | F26: =SUMPRODUCT(J23:CO23,J25:CO25) -> 72154.225 | G26: $ 000s
E27: =InpC!E$141 -> Maximum gearing (debt / total uses) | F27: =InpC!F$141 -> 0.75 | G27: =InpC!G$141 -> %
E28: Debt limit from gearing | F28: =F27*Constr!F52 -> 75800.849 | G28: $ 000s
E29: Senior debt size | F29: =MIN(F26,F28) -> 72154.225 | G29: $ 000s
E30: Binding constraint | F30: =IF(F26<=F28,"DSCR","Gearing") -> DSCR | G30: text
E31: Sculpted DSCR at debt size | F31: =F15*F26/F29 -> 2.25 | G31: x
E32: Debt drawn less debt sized (Goal Seek target = 0) | F32: =Constr!F53-F29 -> -7.4214768e-10 | G32: check
A33: SCULPTED REPAYMENT
E34: Sculpted debt service | G34: $ 000s | H34: =SUM(J34:CO34) -> 101237.58 | J34: =J21/$F$31 -> 0 | K34: =K21/$F$31 -> 0 | L34: =L21/$F$31 -> 2229.395 | M34: =M21/$F$31 -> 2317.0618 | N34: =N21/$F$31 -> 2368.8461 | O34: =O21/$F$31 -> 2289.505 | P34: =P21/$F$31 -> 2346.4642 | Q34: =Q21/$F$31 -> 2273.2982 | ... CO34: =CO21/$F$31 -> 0
E35: Senior debt balance BEG | G35: $ 000s | J35: =I38 -> 0 | K35: =J38 -> 0 | L35: =K38 -> 72154.225 | M35: =L38 -> 71097.336 | N35: =M38 -> 69948.443 | O35: =N38 -> 68741.518 | P35: =O38 -> 67593.886 | Q35: =P38 -> 66345.822 | ... CO35: =CN38 -> -1.1645369e-10
E36: Interest | G36: $ 000s | H36: =SUM(J36:CO36) -> 29083.355 | J36: =J35*J19 -> 0 | K36: =K35*K19 -> 0 | L36: =L35*L19 -> 1172.5062 | M36: =M35*M19 -> 1168.1687 | N36: =N35*N19 -> 1161.9214 | O36: =O35*O19 -> 1141.873 | P36: =P35*P19 -> 1098.4006 | Q36: =Q35*Q19 -> 1090.0987 | ... CO36: =CO35*CO19 -> -1.9133988e-12
E37: Principal | G37: $ 000s | H37: =SUM(J37:CO37) -> 72154.225 | J37: =J34-J36 -> 0 | K37: =K34-K36 -> 0 | L37: =L34-L36 -> 1056.8889 | M37: =M34-M36 -> 1148.893 | N37: =N34-N36 -> 1206.9248 | O37: =O34-O36 -> 1147.632 | P37: =P34-P36 -> 1248.0636 | Q37: =Q34-Q36 -> 1183.1995 | ... CO37: =CO34-CO36 -> 1.9133988e-12
E38: Senior debt balance END | G38: $ 000s | J38: =IF(J25=1,$F$29,J35-J37) -> 0 | K38: =IF(K25=1,$F$29,K35-K37) -> 72154.225 | L38: =IF(L25=1,$F$29,L35-L37) -> 71097.336 | M38: =IF(M25=1,$F$29,M35-M37) -> 69948.443 | N38: =IF(N25=1,$F$29,N35-N37) -> 68741.518 | O38: =IF(O25=1,$F$29,O35-O37) -> 67593.886 | P38: =IF(P25=1,$F$29,P35-P37) -> 66345.822 | Q38: =IF(Q25=1,$F$29,Q35-Q37) -> 65162.623 | ... CO38: =IF(CO25=1,$F$29,CO35-CO37) -> -1.1836709e-10
E40: Sculpted repayment profile (% of opening debt) | G40: % | H40: =SUM(J40:CO40) -> 1 | J40: =J37/$F$29 -> 0 | K40: =K37/$F$29 -> 0 | L40: =L37/$F$29 -> 0.014647637 | M40: =M37/$F$29 -> 0.015922741 | N40: =N37/$F$29 -> 0.016727014 | O40: =O37/$F$29 -> 0.015905264 | P40: =P37/$F$29 -> 0.017297166 | Q40: =Q37/$F$29 -> 0.016398201 | ... CO40: =CO37/$F$29 -> 2.6518181e-17

Sheet DSRA
A1: =RIGHT(CELL("filename", A1), LEN(CELL("filename", A1)) - SEARCH("]", CELL("filename", A1)))
E2: =Time!E$25 -> Model period ending | J2: =Time!J$25 -> 44469 | K2: =Time!K$25 -> 44561 | L2: =Time!L$25 -> 44651 | M2: =Time!M$25 -> 44742 | N2: =Time!N$25 -> 44834 | O2: =Time!O$25 -> 44926 | P2: =Time!P$25 -> 45016 | Q2: =Time!Q$25 -> 45107 | ... CO2: =Time!CO$25 -> 52047
E3: =Time!E$111 -> Timeline label | J3: =Time!J$111 -> Pre-fcst | K3: =Time!K$111 -> Fin close | L3: =Time!L$111 -> Forecast | M3: =Time!M$111 -> Forecast | N3: =Time!N$111 -> Forecast | O3: =Time!O$111 -> Forecast | P3: =Time!P$111 -> Forecast | Q3: =Time!Q$111 -> Forecast | ... CO3: =Time!CO$111 -> Post-fcst
E4: =Time!E$37 -> Financial year ending | J4: =Time!J$37 -> 2021 | K4: =Time!K$37 -> 2021 | L4: =Time!L$37 -> 2022 | M4: =Time!M$37 -> 2022 | N4: =Time!N$37 -> 2022 | O4: =Time!O$37 -> 2022 | P4: =Time!P$37 -> 2023 | Q4: =Time!Q$37 -> 2023 | ... CO4: =Time!CO$37 -> 2042
E5: =Time!E$10 -> Model column counter | F5: Constant | G5: Unit | H5: Total | J5: =Time!J$10 -> 1 | K5: =Time!K$10 -> 2 | L5: =Time!L$10 -> 3 | M5: =Time!M$10 -> 4 | N5: =Time!N$10 -> 5 | O5: =Time!O$10 -> 6 | P5: =Time!P$10 -> 7 | Q5: =Time!Q$10 -> 8 | ... CO5: =Time!CO$10 -> 84
A7: DEBT SERVICE RESERVE ACCOUNT
E9: =InpC!E$143 -> DSRA cover (periods of debt service) | F9: =InpC!F$143 -> 2 | G9: =InpC!G$143 -> periods
E10: Operating period counter | G10: counter | J10: =Sculpt!J$11 -> 0 | K10: =Sculpt!K$11 -> 0 | L10: =Sculpt!L$11 -> 1 | M10: =Sculpt!M$11 -> 2 | N10: =Sculpt!N$11 -> 3 | O10: =Sculpt!O$11 -> 4 | P10: =Sculpt!P$11 -> 5 | Q10: =Sculpt!Q$11 -> 6 | ... CO10: =Sculpt!CO$11 -> 80
E11: Senior debt service | G11: $ 000s | H11: =SUM(J11:CO11) -> 101237.58 | J11: =FinStat!J$94 -> 0 | K11: =FinStat!K$94 -> 0 | L11: =FinStat!L$94 -> 2229.395 | M11: =FinStat!M$94 -> 2317.0618 | N11: =FinStat!N$94 -> 2368.8461 | O11: =FinStat!O$94 -> 2289.505 | P11: =FinStat!P$94 -> 2346.4642 | Q11: =FinStat!Q$94 -> 2273.2982 | ... CO11: =FinStat!CO$94 -> 1.4943503e-13
E12: DSRA target (next periods of debt service) | G12: $ 000s | J12: =SUMIFS($J11:$CO11,$J10:$CO10,">"&J10,$J10:$CO10,"<="&J10+$F$9)*(1-Time!J$58+Time!J$45) -> 0 | K12: =SUMIFS($J11:$CO11,$J10:$CO10,">"&K10,$J10:$CO10,"<="&K10+$F$9)*(1-Time!K$58+Time!K$45) -> 4546.4568 | L12: =SUMIFS($J11:$CO11,$J10:$CO10,">"&L10,$J10:$CO10,"<="&L10+$F$9)*(1-Time!L$58+Time!L$45) -> 4685.9079 | M12: =SUMIFS($J11:$CO11,$J10:$CO10,">"&M10,$J10:$CO10,"<="&M10+$F$9)*(1-Time!M$58+Time!M$45) -> 4658.3511 | N12: =SUMIFS($J11:$CO11,$J10:$CO10,">"&N10,$J10:$CO10,"<="&N10+$F$9)*(1-Time!N$58+Time!N$45) -> 4635.9693 | O12: =SUMIFS($J11:$CO11,$J10:$CO10,">"&O10,$J10:$CO10,"<="&O10+$F$9)*(1-Time!O$58+Time!O$45) -> 4619.7624 | P12: =SUMIFS($J11:$CO11,$J10:$CO10,">"&P10,$J10:$CO10,"<="&P10+$F$9)*(1-Time!P$58+Time!P$45) -> 4616.6881 | Q12: =SUMIFS($J11:$CO11,$J10:$CO10,">"&Q10,$J10:$CO10,"<="&Q10+$F$9)*(1-Time!Q$58+Time!Q$45) -> 3717.6792 | ... CO12: =SUMIFS($J11:$CO11,$J10:$CO10,">"&CO10,$J10:$CO10,"<="&CO10+$F$9)*(1-Time!CO$58+Time!CO$45) -> 0
E13: Cash flow after senior debt service | G13: $ 000s | J13: =FinStat!J$43 -> 0 | K13: =FinStat!K$43 -> 0 | L13: =FinStat!L$43 -> 3268.6067 | M13: =FinStat!M$43 -> 3381.6235 | N13: =FinStat!N$43 -> 3445.9616 | O13: =FinStat!O$43 -> 3340.7707 | P13: =FinStat!P$43 -> 3395.9644 | Q13: =FinStat!Q$43 -> 3303.498 | ... CO13: =FinStat!CO$43 -> -6.7862415e-13
E14: DSRA balance BEG | G14: $ 000s | J14: =I18 -> 0 | K14: =J18 -> 0 | L14: =K18 -> 0 | M14: =L18 -> 3268.6067 | N14: =M18 -> 4658.3511 | O14: =N18 -> 4635.9693 | P14: =O18 -> 4619.7624 | Q14: =P18 -> 4616.6881 | ... CO14: =CN18 -> 0
E15: Funding | G15: $ 000s | H15: =SUM(J15:CO15) -> 9788.4532 | J15: =MIN(MAX(J12-J14,0),MAX(J13,0)) -> 0 | K15: =MIN(MAX(K12-K14,0),MAX(K13,0)) -> 0 | L15: =MIN(MAX(L12-L14,0),MAX(L13,0)) -> 3268.6067 | M15: =MIN(MAX(M12-M14,0),MAX(M13,0)) -> 1389.7444 | N15: =MIN(MAX(N12-N14,0),MAX(N13,0)) -> 0 | O15: =MIN(MAX(O12-O14,0),MAX(O13,0)) -> 0 | P15: =MIN(MAX(P12-P14,0),MAX(P13,0)) -> 0 | Q15: =MIN(MAX(Q12-Q14,0),MAX(Q13,0)) -> 0 | ... CO15: =MIN(MAX(CO12-CO14,0),MAX(CO13,0)) -> 0
E16: Release | G16: $ 000s | H16: =SUM(J16:CO16) -> 9788.4532 | J16: =MAX(J14-J12,0) -> 0 | K16: =MAX(K14-K12,0) -> 0 | L16: =MAX(L14-L12,0) -> 0 | M16: =MAX(M14-M12,0) -> 0 | N16: =MAX(N14-N12,0) -> 22.381873 | O16: =MAX(O14-O12,0) -> 16.206842 | P16: =MAX(P14-P12,0) -> 3.0743241 | Q16: =MAX(Q14-Q12,0) -> 899.0089 | ... CO16: =MAX(CO14-CO12,0) -> 0
E17: DSRA (funding) / release | G17: $ 000s | H17: =SUM(J17:CO17) -> -8.2738754e-14 | J17: =J16-J15 -> 0 | K17: =K16-K15 -> 0 | L17: =L16-L15 -> -3268.6067 | M17: =M16-M15 -> -1389.7444 | N17: =N16-N15 -> 22.381873 | O17: =O16-O15 -> 16.206842 | P17: =P16-P15 -> 3.0743241 | Q17: =Q16-Q15 -> 899.0089 | ... CO17: =CO16-CO15 -> 0
E18: DSRA balance END | G18: $ 000s | J18: =IF(Time!J$45=1,0,J14+J15-J16) -> 0 | K18: =IF(Time!K$45=1,0,K14+K15-K16) -> 0 | L18: =IF(Time!L$45=1,0,L14+L15-L16) -> 3268.6067 | M18: =IF(Time!M$45=1,0,M14+M15-M16) -> 4658.3511 | N18: =IF(Time!N$45=1,0,N14+N15-N16) -> 4635.9693 | O18: =IF(Time!O$45=1,0,O14+O15-O16) -> 4619.7624 | P18: =IF(Time!P$45=1,0,P14+P15-P16) -> 4616.6881 | Q18: =IF(Time!Q$45=1,0,Q14+Q15-Q16) -> 3717.6792 | ... CO18: =IF(Time!CO$45=1,0,CO14+CO15-CO16) -> 0

Sheet SHL
A1: =RIGHT(CELL("filename", A1), LEN(CELL("filename", A1)) - SEARCH("]", CELL("filename", A1)))
E2: =Time!E$25 -> Model period ending | J2: =Time!J$25 -> 44469 | K2: =Time!K$25 -> 44561 | L2: =Time!L$25 -> 44651 | M2: =Time!M$25 -> 44742 | N2: =Time!N$25 -> 44834 | O2: =Time!O$25 -> 44926 | P2: =Time!P$25 -> 45016 | Q2: =Time!Q$25 -> 45107 | ... CO2: =Time!CO$25 -> 52047
E3: =Time!E$111 -> Timeline label | J3: =Time!J$111 -> Pre-fcst | K3: =Time!K$111 -> Fin close | L3: =Time!L$111 -> Forecast | M3: =Time!M$111 -> Forecast | N3: =Time!N$111 -> Forecast | O3: =Time!O$111 -> Forecast | P3: =Time!P$111 -> Forecast | Q3: =Time!Q$111 -> Forecast | ... CO3: =Time!CO$111 -> Post-fcst
E4: =Time!E$37 -> Financial year ending | J4: =Time!J$37 -> 2021 | K4: =Time!K$37 -> 2021 | L4: =Time!L$37 -> 2022 | M4: =Time!M$37 -> 2022 | N4: =Time!N$37 -> 2022 | O4: =Time!O$37 -> 2022 | P4: =Time!P$37 -> 2023 | Q4: =Time!Q$37 -> 2023 | ... CO4: =Time!CO$37 -> 2042
E5: =Time!E$10 -> Model column counter | F5: Constant | G5: Unit | H5: Total | J5: =Time!J$10 -> 1 | K5: =Time!K$10 -> 2 | L5: =Time!L$10 -> 3 | M5: =Time!M$10 -> 4 | N5: =Time!N$10 -> 5 | O5: =Time!O$10 -> 6 | P5: =Time!P$10 -> 7 | Q5: =Time!Q$10 -> 8 | ... CO5: =Time!CO$10 -> 84
A7: SHAREHOLDER LOAN
E9: =InpC!E$147 -> Shareholder loan share of sponsor funding | F9: =InpC!F$147 -> 0.6 | G9: =InpC!G$147 -> %
E10: =InpC!E$148 -> Shareholder loan interest rate | F10: =InpC!F$148 -> 0.1 | G10: =InpC!G$148 -> % p.a
E11: =InpC!E$79 -> Day count convention | F11: =InpC!F$79 -> 360 | G11: =InpC!G$79 -> days
E12: Sponsor funding at COD | F12: =Constr!F54 -> 28913.574 | G12: $ 000s
E13: Shareholder loan - initial balance | F13: =F12*F9 -> 17348.145 | G13: $ 000s
E14: Share capital - initial balance | F14: =F12-F13 -> 11565.43 | G14: $ 000s
E16: Cash available for shareholder loan | G16: $ 000s | J16: =MAX(FinStat!J$43+DSRA!J$17,0) -> 0 | K16: =MAX(FinStat!K$43+DSRA!K$17,0) -> 0 | L16: =MAX(FinStat!L$43+DSRA!L$17,0) -> 0 | M16: =MAX(FinStat!M$43+DSRA!M$17,0) -> 1991.8791 | N16: =MAX(FinStat!N$43+DSRA!N$17,0) -> 3468.3434 | O16: =MAX(FinStat!O$43+DSRA!O$17,0) -> 3356.9775 | P16: =MAX(FinStat!P$43+DSRA!P$17,0) -> 3399.0387 | Q16: =MAX(FinStat!Q$43+DSRA!Q$17,0) -> 4202.5069 | ... CO16: =MAX(FinStat!CO$43+DSRA!CO$17,0) -> 0
E17: Post-senior-loan flag | G17: flag | J17: =IF(Sculpt!J$11>Sculpt!$F$9,1,0) -> 0 | K17: =IF(Sculpt!K$11>Sculpt!$F$9,1,0) -> 0 | L17: =IF(Sculpt!L$11>Sculpt!$F$9,1,0) -> 0 | M17: =IF(Sculpt!M$11>Sculpt!$F$9,1,0) -> 0 | N17: =IF(Sculpt!N$11>Sculpt!$F$9,1,0) -> 0 | O17: =IF(Sculpt!O$11>Sculpt!$F$9,1,0) -> 0 | P17: =IF(Sculpt!P$11>Sculpt!$F$9,1,0) -> 0 | Q17: =IF(Sculpt!Q$11>Sculpt!$F$9,1,0) -> 0 | ... CO17: =IF(Sculpt!CO$11>Sculpt!$F$9,1,0) -> 1
E18: Days in period | G18: days | J18: =Time!J$30 -> 92 | K18: =Time!K$30 -> 92 | L18: =Time!L$30 -> 90 | M18: =Time!M$30 -> 91 | N18: =Time!N$30 -> 92 | O18: =Time!O$30 -> 92 | P18: =Time!P$30 -> 90 | Q18: =Time!Q$30 -> 91 | ... CO18: =Time!CO$30 -> 91
E19: Shareholder loan balance BEG | G19: $ 000s | J19: =I24 -> 0 | K19: =J24 -> 0 | L19: =K24 -> 17348.145 | M19: =L24 -> 17781.848 | N19: =M24 -> 17781.848 | O19: =N24 -> 17781.848 | P19: =O24 -> 17781.848 | Q19: =P24 -> 17781.848 | ... CO19: =CN24 -> 0
E20: Interest due | G20: $ 000s | H20: =SUM(J20:CO20) -> 18824.3 | J20: =J19*$F$10/$F$11*J18 -> 0 | K20: =K19*$F$10/$F$11*K18 -> 0 | L20: =L19*$F$10/$F$11*L18 -> 433.70362 | M20: =M19*$F$10/$F$11*M18 -> 449.48561 | N20: =N19*$F$10/$F$11*N18 -> 454.42501 | O20: =O19*$F$10/$F$11*O18 -> 454.42501 | P20: =P19*$F$10/$F$11*P18 -> 444.54621 | Q20: =Q19*$F$10/$F$11*Q18 -> 449.48561 | ... CO20: =CO19*$F$10/$F$11*CO18 -> 0
E21: Interest paid | G21: $ 000s | H21: =SUM(J21:CO21) -> 18390.596 | J21: =MIN(J20,J16) -> 0 | K21: =MIN(K20,K16) -> 0 | L21: =MIN(L20,L16) -> 0 | M21: =MIN(M20,M16) -> 449.48561 | N21: =MIN(N20,N16) -> 454.42501 | O21: =MIN(O20,O16) -> 454.42501 | P21: =MIN(P20,P16) -> 444.54621 | Q21: =MIN(Q20,Q16) -> 449.48561 | ... CO21: =MIN(CO20,CO16) -> 0
E22: Interest capitalised (unpaid) | G22: $ 000s | H22: =SUM(J22:CO22) -> 433.70362 | J22: =J20-J21 -> 0 | K22: =K20-K21 -> 0 | L22: =L20-L21 -> 433.70362 | M22: =M20-M21 -> 0 | N22: =N20-N21 -> 0 | O22: =O20-O21 -> 0 | P22: =P20-P21 -> 0 | Q22: =Q20-Q21 -> 0 | ... CO22: =CO20-CO21 -> 0
E23: Principal repaid | G23: $ 000s | H23: =SUM(J23:CO23) -> 17781.848 | J23: =J17*MIN(J19+J22,J16-J21) -> 0 | K23: =K17*MIN(K19+K22,K16-K21) -> 0 | L23: =L17*MIN(L19+L22,L16-L21) -> 0 | M23: =M17*MIN(M19+M22,M16-M21) -> 0 | N23: =N17*MIN(N19+N22,N16-N21) -> 0 | O23: =O17*MIN(O19+O22,O16-O21) -> 0 | P23: =P17*MIN(P19+P22,P16-P21) -> 0 | Q23: =Q17*MIN(Q19+Q22,Q16-Q21) -> 0 | ... CO23: =CO17*MIN(CO19+CO22,CO16-CO21) -> 0
E24: Shareholder loan balance END | G24: $ 000s | J24: =IF(Time!J$45=1,$F$13,J19+J22-J23) -> 0 | K24: =IF(Time!K$45=1,$F$13,K19+K22-K23) -> 17348.145 | L24: =IF(Time!L$45=1,$F$13,L19+L22-L23) -> 17781.848 | M24: =IF(Time!M$45=1,$F$13,M19+M22-M23) -> 17781.848 | N24: =IF(Time!N$45=1,$F$13,N19+N22-N23) -> 17781.848 | O24: =IF(Time!O$45=1,$F$13,O19+O22-O23) -> 17781.848 | P24: =IF(Time!P$45=1,$F$13,P19+P22-P23) -> 17781.848 | Q24: =IF(Time!Q$45=1,$F$13,Q19+Q22-Q23) -> 17781.848 | ... CO24: =IF(Time!CO$45=1,$F$13,CO19+CO22-CO23) -> 0
E25: Shareholder loan interest | G25: $ 000s | H25: =SUM(J25:CO25) -> -18824.3 | J25: =-1*J20 -> 0 | K25: =-1*K20 -> 0 | L25: =-1*L20 -> -433.70362 | M25: =-1*M20 -> -449.48561 | N25: =-1*N20 -> -454.42501 | O25: =-1*O20 -> -454.42501 | P25: =-1*P20 -> -444.54621 | Q25: =-1*Q20 -> -449.48561 | ... CO25: =-1*CO20 -> 0
E26: Shareholder loan interest paid | G26: $ 000s | H26: =SUM(J26:CO26) -> -18390.596 | J26: =-1*J21 -> 0 | K26: =-1*K21 -> 0 | L26: =-1*L21 -> 0 | M26: =-1*M21 -> -449.48561 | N26: =-1*N21 -> -454.42501 | O26: =-1*O21 -> -454.42501 | P26: =-1*P21 -> -444.54621 | Q26: =-1*Q21 -> -449.48561 | ... CO26: =-1*CO21 -> 0
E27: Shareholder loan principal repaid | G27: $ 000s | H27: =SUM(J27:CO27) -> -17781.848 | J27: =-1*J23 -> 0 | K27: =-1*K23 -> 0 | L27: =-1*L23 -> 0 | M27: =-1*M23 -> 0 | N27: =-1*N23 -> 0 | O27: =-1*O23 -> 0 | P27: =-1*P23 -> 0 | Q27: =-1*Q23 -> 0 | ... CO27: =-1*CO23 -> 0

Sheet Equity
A1: =RIGHT(CELL("filename", A1), LEN(CELL("filename", A1)) - SEARCH("]", CELL("filename", A1)))
E2: =Time!E$25 -> Model period ending | J2: =Time!J$25 -> 44469 | K2: =Time!K$25 -> 44561 | L2: =Time!L$25 -> 44651 | M2: =Time!M$25 -> 44742 | N2: =Time!N$25 -> 44834 | O2: =Time!O$25 -> 44926 | P2: =Time!P$25 -> 45016 | Q2: =Time!Q$25 -> 45107 | ... CO2: =Time!CO$25 -> 52047
E3: =Time!E$111 -> Timeline label | J3: =Time!J$111 -> Pre-fcst | K3: =Time!K$111 -> Fin close | L3: =Time!L$111 -> Forecast | M3: =Time!M$111 -> Forecast | N3: =Time!N$111 -> Forecast | O3: =Time!O$111 -> Forecast | P3: =Time!P$111 -> Forecast | Q3: =Time!Q$111 -> Forecast | ... CO3: =Time!CO$111 -> Post-fcst
E4: =Time!E$37 -> Financial year ending | J4: =Time!J$37 -> 2021 | K4: =Time!K$37 -> 2021 | L4: =Time!L$37 -> 2022 | M4: =Time!M$37 -> 2022 | N4: =Time!N$37 -> 2022 | O4: =Time!O$37 -> 2022 | P4: =Time!P$37 -> 2023 | Q4: =Time!Q$37 -> 2023 | ... CO4: =Time!CO$37 -> 2042
E5: =Time!E$10 -> Model column counter | F5: Constant | G5: Unit | H5: Total | J5: =Time!J$10 -> 1 | K5: =Time!K$10 -> 2 | L5: =Time!L$10 -> 3 | M5: =Time!M$10 -> 4 | N5: =Time!N$10 -> 5 | O5: =Time!O$10 -> 6 | P5: =Time!P$10 -> 7 | Q5: =Time!Q$10 -> 8 | ... CO5: =Time!CO$10 -> 84
A7: SHARE CAPITAL REDEMPTION
E8: =E$21 -> Share capital balance BEG | F8: =F$21 -> 0 | G8: =G$21 -> $ 000s | H8: =H$21 -> 0 | I8: =I$21 -> 0 | J8: =J$21 -> 0 | K8: =K$21 -> 0 | L8: =L$21 -> 11565.43 | ... CO8: =CO$21 -> 0
E9: =Time!E$75 -> Last forecast period flag | F9: =Time!F$75 -> 0 | G9: =Time!G$75 -> flag | H9: =Time!H$75 -> 1 | I9: =Time!I$75 -> 0 | J9: =Time!J$75 -> 0 | K9: =Time!K$75 -> 0 | L9: =Time!L$75 -> 0 | ... CO9: =Time!CO$75 -> 0
E10: Share capital redemption POS | G10: =SMU -> $ 000s | H10: =SUM(J10:CO10) -> 11565.43 | J10: =J8 * J9 -> 0 | K10: =K8 * K9 -> 0 | L10: =L8 * L9 -> 0 | M10: =M8 * M9 -> 0 | N10: =N8 * N9 -> 0 | O10: =O8 * O9 -> 0 | P10: =P8 * P9 -> 0 | Q10: =Q8 * Q9 -> 0 | ... CO10: =CO8 * CO9 -> 0
E11: =LEFT(E10, LEN(E10) - 4) -> Share capital redemption | F11: CF | G11: =G10 -> $ 000s | H11: =SUM(J11:CO11) -> -11565.43 | J11: =-1 * J10 -> 0 | K11: =-1 * K10 -> 0 | L11: =-1 * L10 -> 0 | M11: =-1 * M10 -> 0 | N11: =-1 * N10 -> 0 | O11: =-1 * O10 -> 0 | P11: =-1 * P10 -> 0 | Q11: =-1 * Q10 -> 0 | ... CO11: =-1 * CO10 -> 0
A13: SHARE CAPITAL BALANCE
E14: =InpC!E$64 -> Non current asset - initial balance | F14: =InpC!F$64 -> 101067.8 | G14: =InpC!G$64 -> $ 000s
E15: =InpC!E$72 -> % of NCA financed with debt | F15: =InpC!F$72 -> 0.71391903 | G15: =InpC!G$72 -> %
E16: Share capital - Initial balance | F16: =SHL!$F$14 -> 11565.43 | G16: =SMU -> $ 000s
E18: =E$16 -> Share capital - Initial balance | F18: =F$16 -> 11565.43 | G18: =G$16 -> $ 000s
E19: =Time!E$45 -> Acquisition / initial balance date flag | F19: =Time!F$45 -> 0 | G19: =Time!G$45 -> flag | H19: =Time!H$45 -> 1 | I19: =Time!I$45 -> 0 | J19: =Time!J$45 -> 0 | K19: =Time!K$45 -> 1 | L19: =Time!L$45 -> 0 | ... CO19: =Time!CO$45 -> 0
E21: Share capital balance BEG | G21: $ 000s | J21: =I24 -> 0 | K21: =J24 -> 0 | L21: =K24 -> 11565.43 | M21: =L24 -> 11565.43 | N21: =M24 -> 11565.43 | O21: =N24 -> 11565.43 | P21: =O24 -> 11565.43 | Q21: =P24 -> 11565.43 | ... CO21: =CN24 -> 0
D22: plus | E22: =InpS!E$23 -> Share capital - additional injection | F22: =InpS!F$23 -> 0 | G22: =InpS!G$23 -> $ 000s | H22: =SUM(J22:CO22) -> 0 | J22: =InpS!J$23 -> 0 | K22: =InpS!K$23 -> 0 | L22: =InpS!L$23 -> 0 | M22: =InpS!M$23 -> 0 | N22: =InpS!N$23 -> 0 | O22: =InpS!O$23 -> 0 | P22: =InpS!P$23 -> 0 | Q22: =InpS!Q$23 -> 0 | ... CO22: =InpS!CO$23 -> 0
D23: less | E23: =E$10 -> Share capital redemption POS | F23: =F$10 -> 0 | G23: =G$10 -> $ 000s | H23: =H$10 -> 11565.43 | I23: =I$10 -> 0 | J23: =J$10 -> 0 | K23: =K$10 -> 0 | L23: =L$10 -> 0 | ... CO23: =CO$10 -> 0
E24: Share capital balance | F24: BS | G24: $ 000s | J24: =IF(J19 = 1, $F18, J21 + J22 - J23) -> 0 | K24: =IF(K19 = 1, $F18, K21 + K22 - K23) -> 11565.43 | L24: =IF(L19 = 1, $F18, L21 + L22 - L23) -> 11565.43 | M24: =IF(M19 = 1, $F18, M21 + M22 - M23) -> 11565.43 | N24: =IF(N19 = 1, $F18, N21 + N22 - N23) -> 11565.43 | O24: =IF(O19 = 1, $F18, O21 + O22 - O23) -> 11565.43 | P24: =IF(P19 = 1, $F18, P21 + P22 - P23) -> 11565.43 | Q24: =IF(Q19 = 1, $F18, Q21 + Q22 - Q23) -> 11565.43 | ... CO24: =IF(CO19 = 1, $F18, CO21 + CO22 - CO23) -> 0
A27: DIVIDEND DECLARED AND PAID
E29: =E$47 -> Retained cash balance BEG | F29: =F$47 -> 0 | G29: =G$47 -> $ 000s | H29: =H$47 -> 0 | I29: =I$47 -> 0 | J29: =J$47 -> 0 | K29: =K$47 -> 0 | L29: =L$47 -> 0 | ... CO29: =CO$47 -> 0
E30: =FinStat!E$49 -> Cash flow available for dividends | F30: =FinStat!F$49 -> 0 | G30: =FinStat!G$49 -> $ 000s | H30: =FinStat!H$49 -> 442553.82 | I30: =FinStat!I$49 -> 0 | J30: =FinStat!J$49 -> 0 | K30: =FinStat!K$49 -> 0 | L30: =FinStat!L$49 -> 0 | ... CO30: =FinStat!CO$49 -> -6.7862415e-13
E31: Aggregate cash available for dividend | G31: =SMU -> $ 000s | H31: =SUM(J31:CO31) -> 848378.48 | J31: =MAX(SUM(J29:J30), 0) -> 0 | K31: =MAX(SUM(K29:K30), 0) -> 0 | L31: =MAX(SUM(L29:L30), 0) -> 0 | M31: =MAX(SUM(M29:M30), 0) -> 1542.3935 | N31: =MAX(SUM(N29:N30), 0) -> 3013.9184 | O31: =MAX(SUM(O29:O30), 0) -> 2902.5525 | P31: =MAX(SUM(P29:P30), 0) -> 4204.4865 | Q31: =MAX(SUM(Q29:Q30), 0) -> 6080.2311 | ... CO31: =MAX(SUM(CO29:CO30), 0) -> 0
E33: =E$58 -> Retained earnings balance BEG | F33: =F$58 -> 0 | G33: =G$58 -> $ 000s | H33: =H$58 -> 0 | I33: =I$58 -> 0 | J33: =J$58 -> 0 | K33: =K$58 -> 0 | L33: =L$58 -> 0 | ... CO33: =CO$58 -> 1.1459633e-10
E34: =FinStat!E$19 -> Profit after tax | F34: =FinStat!F$19 -> 0 | G34: =FinStat!G$19 -> $ 000s | H34: =FinStat!H$19 -> 442553.82 | I34: =FinStat!I$19 -> 0 | J34: =FinStat!J$19 -> 0 | K34: =FinStat!K$19 -> 0 | L34: =FinStat!L$19 -> 1646.3664 | ... CO34: =FinStat!CO$19 -> 1.2347746e-12
E35: Aggregate earnings available for dividend | G35: =SMU -> $ 000s | H35: =SUM(J35:CO35) -> 558962.96 | J35: =MAX(SUM(J33:J34), 0) -> 0 | K35: =MAX(SUM(K33:K34), 0) -> 0 | L35: =MAX(SUM(L33:L34), 0) -> 1646.3664 | M35: =MAX(SUM(M33:M34), 0) -> 3007.6141 | N35: =MAX(SUM(N33:N34), 0) -> 3193.5839 | O35: =MAX(SUM(O33:O34), 0) -> 1652.5585 | P35: =MAX(SUM(P33:P34), 0) -> 1877.2767 | Q35: =MAX(SUM(Q33:Q34), 0) -> 1605.6788 | ... CO35: =MAX(SUM(CO33:CO34), 0) -> 1.1583111e-10
E37: =E$31 -> Aggregate cash available for dividend | F37: =F$31 -> 0 | G37: =G$31 -> $ 000s | H37: =H$31 -> 848378.48 | I37: =I$31 -> 0 | J37: =J$31 -> 0 | K37: =K$31 -> 0 | L37: =L$31 -> 0 | ... CO37: =CO$31 -> 0
E38: =E$35 -> Aggregate earnings available for dividend | F38: =F$35 -> 0 | G38: =G$35 -> $ 000s | H38: =H$35 -> 558962.96 | I38: =I$35 -> 0 | J38: =J$35 -> 0 | K38: =K$35 -> 0 | L38: =L$35 -> 1646.3664 | ... CO38: =CO$35 -> 1.1583111e-10
E39: Dividend declared and paid POS | G39: =SMU -> $ 000s | H39: =SUM(J39:CO39) -> 442553.82 | J39: =MIN(J37:J38) -> 0 | K39: =MIN(K37:K38) -> 0 | L39: =MIN(L37:L38) -> 0 | M39: =MIN(M37:M38) -> 1542.3935 | N39: =MIN(N37:N38) -> 3013.9184 | O39: =MIN(O37:O38) -> 1652.5585 | P39: =MIN(P37:P38) -> 1877.2767 | Q39: =MIN(Q37:Q38) -> 1605.6788 | ... CO39: =MIN(CO37:CO38) -> 0
E40: =LEFT(E39, LEN(E39) - 4) -> Dividend declared and paid | F40: IS&CF | G40: =G39 -> $ 000s | H40: =SUM(J40:CO40) -> -442553.82 | J40: =-1 * J39 -> 0 | K40: =-1 * K39 -> 0 | L40: =-1 * L39 -> 0 | M40: =-1 * M39 -> -1542.3935 | N40: =-1 * N39 -> -3013.9184 | O40: =-1 * O39 -> -1652.5585 | P40: =-1 * P39 -> -1877.2767 | Q40: =-1 * Q39 -> -1605.6788 | ... CO40: =-1 * CO39 -> 0
A42: RETAINED CASH BALANCE
E44: Retained cash - initial balance | F44: 0
E45: =Time!E$45 -> Acquisition / initial balance date flag | F45: =Time!F$45 -> 0 | G45: =Time!G$45 -> flag | H45: =Time!H$45 -> 1 | I45: =Time!I$45 -> 0 | J45: =Time!J$45 -> 0 | K45: =Time!K$45 -> 1 | L45: =Time!L$45 -> 0 | ... CO45: =Time!CO$45 -> 0
E47: Retained cash balance BEG | G47: $ 000s | J47: =I50 -> 0 | K47: =J50 -> 0 | L47: =K50 -> 0 | M47: =L50 -> 0 | N47: =M50 -> 0 | O47: =N50 -> 0 | P47: =O50 -> 1249.994 | Q47: =P50 -> 2327.2098 | ... CO47: =CN50 -> 0
D48: plus | E48: =FinStat!E$49 -> Cash flow available for dividends | F48: =FinStat!F$49 -> 0 | G48: =FinStat!G$49 -> $ 000s | H48: =FinStat!H$49 -> 442553.82 | I48: =FinStat!I$49 -> 0 | J48: =FinStat!J$49 -> 0 | K48: =FinStat!K$49 -> 0 | L48: =FinStat!L$49 -> 0 | ... CO48: =FinStat!CO$49 -> -6.7862415e-13
D49: less | E49: =E$39 -> Dividend declared and paid POS | F49: =F$39 -> 0 | G49: =G$39 -> $ 000s | H49: =H$39 -> 442553.82 | I49: =I$39 -> 0 | J49: =J$39 -> 0 | K49: =K$39 -> 0 | L49: =L$39 -> 0 | ... CO49: =CO$39 -> 0
E50: Retained cash balance | F50: BS | G50: $ 000s | J50: =IF(J45 = 1, $F44, J47 + J48 - J49) -> 0 | K50: =IF(K45 = 1, $F44, K47 + K48 - K49) -> 0 | L50: =IF(L45 = 1, $F44, L47 + L48 - L49) -> 0 | M50: =IF(M45 = 1, $F44, M47 + M48 - M49) -> 0 | N50: =IF(N45 = 1, $F44, N47 + N48 - N49) -> 0 | O50: =IF(O45 = 1, $F44, O47 + O48 - O49) -> 1249.994 | P50: =IF(P45 = 1, $F44, P47 + P48 - P49) -> 2327.2098 | Q50: =IF(Q45 = 1, $F44, Q47 + Q48 - Q49) -> 4474.5523 | ... CO50: =IF(CO45 = 1, $F44, CO47 + CO48 - CO49) -> -6.7862415e-13
A53: RETAINED EARNINGS BALANCE
E55: Retained earnings - initial balance | F55: 0
E56: =Time!E$45 -> Acquisition / initial balance date flag | F56: =Time!F$45 -> 0 | G56: =Time!G$45 -> flag | H56: =Time!H$45 -> 1 | I56: =Time!I$45 -> 0 | J56: =Time!J$45 -> 0 | K56: =Time!K$45 -> 1 | L56: =Time!L$45 -> 0 | ... CO56: =Time!CO$45 -> 0
E58: Retained earnings balance BEG | G58: $ 000s | J58: =I61 -> 0 | K58: =J61 -> 0 | L58: =K61 -> 0 | M58: =L61 -> 1646.3664 | N58: =M61 -> 1465.2206 | O58: =N61 -> 179.66553 | P58: =O61 -> 0 | Q58: =P61 -> 0 | ... CO58: =CN61 -> 1.1459633e-10
D59: plus | E59: =FinStat!E$19 -> Profit after tax | F59: =FinStat!F$19 -> 0 | G59: =FinStat!G$19 -> $ 000s | H59: =FinStat!H$19 -> 442553.82 | I59: =FinStat!I$19 -> 0 | J59: =FinStat!J$19 -> 0 | K59: =FinStat!K$19 -> 0 | L59: =FinStat!L$19 -> 1646.3664 | ... CO59: =FinStat!CO$19 -> 1.2347746e-12
D60: less | E60: =E$39 -> Dividend declared and paid POS | F60: =F$39 -> 0 | G60: =G$39 -> $ 000s | H60: =H$39 -> 442553.82 | I60: =I$39 -> 0 | J60: =J$39 -> 0 | K60: =K$39 -> 0 | L60: =L$39 -> 0 | ... CO60: =CO$39 -> 0
E61: Retained earnings balance | F61: BS | G61: $ 000s | J61: =IF(J56 = 1, $F55, J58 + J59 - J60) -> 0 | K61: =IF(K56 = 1, $F55, K58 + K59 - K60) -> 0 | L61: =IF(L56 = 1, $F55, L58 + L59 - L60) -> 1646.3664 | M61: =IF(M56 = 1, $F55, M58 + M59 - M60) -> 1465.2206 | N61: =IF(N56 = 1, $F55, N58 + N59 - N60) -> 179.66553 | O61: =IF(O56 = 1, $F55, O58 + O59 - O60) -> 0 | P61: =IF(P56 = 1, $F55, P58 + P59 - P60) -> 0 | Q61: =IF(Q56 = 1, $F55, Q58 + Q59 - Q60) -> 0 | ... CO61: =IF(CO56 = 1, $F55, CO58 + CO59 - CO60) -> 1.1583111e-10

Sheet FinStat
A1: =RIGHT(CELL("filename", A1), LEN(CELL("filename", A1)) - SEARCH("]", CELL("filename", A1)))
E2: =Time!E$25 -> Model period ending | J2: =Time!J$25 -> 44469 | K2: =Time!K$25 -> 44561 | L2: =Time!L$25 -> 44651 | M2: =Time!M$25 -> 44742 | N2: =Time!N$25 -> 44834 | O2: =Time!O$25 -> 44926 | P2: =Time!P$25 -> 45016 | Q2: =Time!Q$25 -> 45107 | ... CO2: =Time!CO$25 -> 52047
E3: =Time!E$111 -> Timeline label | J3: =Time!J$111 -> Pre-fcst | K3: =Time!K$111 -> Fin close | L3: =Time!L$111 -> Forecast | M3: =Time!M$111 -> Forecast | N3: =Time!N$111 -> Forecast | O3: =Time!O$111 -> Forecast | P3: =Time!P$111 -> Forecast | Q3: =Time!Q$111 -> Forecast | ... CO3: =Time!CO$111 -> Post-fcst
E4: =Time!E$37 -> Financial year ending | J4: =Time!J$37 -> 2021 | K4: =Time!K$37 -> 2021 | L4: =Time!L$37 -> 2022 | M4: =Time!M$37 -> 2022 | N4: =Time!N$37 -> 2022 | O4: =Time!O$37 -> 2022 | P4: =Time!P$37 -> 2023 | Q4: =Time!Q$37 -> 2023 | ... CO4: =Time!CO$37 -> 2042
E5: =Time!E$10 -> Model column counter | F5: Constant | G5: Unit | H5: Total | J5: =Time!J$10 -> 1 | K5: =Time!K$10 -> 2 | L5: =Time!L$10 -> 3 | M5: =Time!M$10 -> 4 | N5: =Time!N$10 -> 5 | O5: =Time!O$10 -> 6 | P5: =Time!P$10 -> 7 | Q5: =Time!Q$10 -> 8 | ... CO5: =Time!CO$10 -> 84
A7: INCOME STATEMENT
E9: =OpRev!E$42 -> Operating revenue | F9: =OpRev!F$42 -> IS | G9: =OpRev!G$42 -> $ 000s | H9: =OpRev!H$42 -> 1941568.6 | I9: =OpRev!I$42 -> 0 | J9: =OpRev!J$42 -> 0 | K9: =OpRev!K$42 -> 0 | L9: =OpRev!L$42 -> 15701.746 | ... CO9: =OpRev!CO$42 -> 0
E10: =OpCost!E$39 -> Operating cost | F10: =OpCost!F$39 -> IS | G10: =OpCost!G$39 -> $ 000s | H10: =OpCost!H$39 -> -1152373.4 | I10: =OpCost!I$39 -> 0 | J10: =OpCost!J$39 -> 0 | K10: =OpCost!K$39 -> 0 | L10: =OpCost!L$39 -> -10059.121 | ... CO10: =OpCost!CO$39 -> 0
E11: EBITDA | G11: $ 000s | H11: =SUM(J11:CO11) -> 789195.2 | J11: =SUM(J9:J10) -> 0 | K11: =SUM(K9:K10) -> 0 | L11: =SUM(L9:L10) -> 5642.6251 | M11: =SUM(M9:M10) -> 5246.7573 | N11: =SUM(N9:N10) -> 5769.9001 | O11: =SUM(O9:O10) -> 5384.8942 | P11: =SUM(P9:P10) -> 5909.234 | Q11: =SUM(Q9:Q10) -> 5517.8745 | ... CO11: =SUM(CO9:CO10) -> 0
E13: =NCA!E$54 -> Accounting depreciation | F13: =NCA!F$54 -> IS | G13: =NCA!G$54 -> $ 000s | H13: =NCA!H$54 -> -109067.8 | I13: =NCA!I$54 -> 0 | J13: =NCA!J$54 -> 0 | K13: =NCA!K$54 -> 0 | L13: =NCA!L$54 -> -1684.4633 | ... CO13: =NCA!CO$54 -> 0
E14: =Debt!E$34 -> Senior debt interest payment | F14: =Debt!F$34 -> IS&CF | G14: =Debt!G$34 -> $ 000s | H14: =Debt!H$34 -> -29083.355 | I14: =Debt!I$34 -> 0 | J14: =Debt!J$34 -> 0 | K14: =Debt!K$34 -> 0 | L14: =Debt!L$34 -> -1172.5062 | ... CO14: =Debt!CO$34 -> 1.7639637e-12
E15: =SHL!E$25 -> Shareholder loan interest | G15: $ 000s | H15: =SUM(J15:CO15) -> -18824.3 | J15: =SHL!J$25 -> 0 | K15: =SHL!K$25 -> 0 | L15: =SHL!L$25 -> -433.70362 | M15: =SHL!M$25 -> -449.48561 | N15: =SHL!N$25 -> -454.42501 | O15: =SHL!O$25 -> -454.42501 | P15: =SHL!P$25 -> -444.54621 | Q15: =SHL!Q$25 -> -449.48561 | ... CO15: =SHL!CO$25 -> 0
E16: Profit before tax | G16: $ 000s | H16: =SUM(J16:CO16) -> 632219.75 | J16: =J11+SUM(J13:J15) -> 0 | K16: =K11+SUM(K13:K15) -> 0 | L16: =L11+SUM(L13:L15) -> 2351.952 | M16: =M11+SUM(M13:M15) -> 1944.6396 | N16: =N11+SUM(N13:N15) -> 2469.0904 | O16: =O11+SUM(O13:O15) -> 2104.1328 | P16: =P11+SUM(P13:P15) -> 2681.8238 | Q16: =Q11+SUM(Q13:Q15) -> 2293.8269 | ... CO16: =CO11+SUM(CO13:CO15) -> 1.7639637e-12
E18: =Tax!E$38 -> Tax expense | F18: =Tax!F$38 -> IS | G18: =Tax!G$38 -> $ 000s | H18: =Tax!H$38 -> -189665.92 | I18: =Tax!I$38 -> 0 | J18: =Tax!J$38 -> 0 | K18: =Tax!K$38 -> 0 | L18: =Tax!L$38 -> -705.5856 | ... CO18: =Tax!CO$38 -> -5.2918912e-13
E19: Profit after tax | G19: $ 000s | H19: =SUM(J19:CO19) -> 442553.82 | J19: =J16 + J18 -> 0 | K19: =K16 + K18 -> 0 | L19: =L16 + L18 -> 1646.3664 | M19: =M16 + M18 -> 1361.2477 | N19: =N16 + N18 -> 1728.3633 | O19: =O16 + O18 -> 1472.893 | P19: =P16 + P18 -> 1877.2767 | Q19: =Q16 + Q18 -> 1605.6788 | ... CO19: =CO16 + CO18 -> 1.2347746e-12
E21: =Equity!E$40 -> Dividend declared and paid | F21: =Equity!F$40 -> IS&CF | G21: =Equity!G$40 -> $ 000s | H21: =Equity!H$40 -> -442553.82 | I21: =Equity!I$40 -> 0 | J21: =Equity!J$40 -> 0 | K21: =Equity!K$40 -> 0 | L21: =Equity!L$40 -> 0 | ... CO21: =Equity!CO$40 -> 0
E22: Retained earnings | G22: $ 000s | H22: =SUM(J22:CO22) -> 1.176501e-10 | J22: =J19 + SUM(J21:J21) -> 0 | K22: =K19 + SUM(K21:K21) -> 0 | L22: =L19 + SUM(L21:L21) -> 1646.3664 | M22: =M19 + SUM(M21:M21) -> -181.14576 | N22: =N19 + SUM(N21:N21) -> -1285.5551 | O22: =O19 + SUM(O21:O21) -> -179.66553 | P22: =P19 + SUM(P21:P21) -> 0 | Q22: =Q19 + SUM(Q21:Q21) -> 0 | ... CO22: =CO19 + SUM(CO21:CO21) -> 1.2347746e-12
E24: Retained earnings balance BEG | J24: =I26 -> 0 | K24: =J26 -> 0 | L24: =K26 -> 0 | M24: =L26 -> 1646.3664 | N24: =M26 -> 1465.2206 | O24: =N26 -> 179.66553 | P24: =O26 -> 0 | Q24: =P26 -> 0 | ... CO24: =CN26 -> 1.1823431e-10
D25: plus | E25: =E$22 -> Retained earnings | F25: =F$22 -> 0 | G25: $ 000s | H25: =H$22 -> 1.176501e-10 | I25: =I$22 -> 0 | J25: =J$22 -> 0 | K25: =K$22 -> 0 | L25: =L$22 -> 1646.3664 | M25: =M$22 -> -181.14576 | N25: =N$22 -> -1285.5551 | O25: =O$22 -> -179.66553 | ... CO25: =CO$22 -> 1.2347746e-12
E26: Retained earnings balance | G26: $ 000s | J26: =SUM(J24:J25) -> 0 | K26: =SUM(K24:K25) -> 0 | L26: =SUM(L24:L25) -> 1646.3664 | M26: =SUM(M24:M25) -> 1465.2206 | N26: =SUM(N24:N25) -> 179.66553 | O26: =SUM(O24:O25) -> 0 | P26: =SUM(P24:P25) -> 0 | Q26: =SUM(Q24:Q25) -> 0 | ... CO26: =SUM(CO24:CO25) -> 1.1946909e-10
A29: CASH FLOW PAYMENT CASCADE
E31: =OpRev!E$54 -> Operating revenue received | F31: =OpRev!F$54 -> CF | G31: =OpRev!G$54 -> $ 000s | H31: =OpRev!H$54 -> 1941568.6 | I31: =OpRev!I$54 -> 0 | J31: =OpRev!J$54 -> 0 | K31: =OpRev!K$54 -> 0 | L31: =OpRev!L$54 -> 11340.15 | ... CO31: =OpRev!CO$54 -> 0
E32: =OpCost!E$51 -> Operating cost paid | F32: =OpCost!F$51 -> CF | G32: =OpCost!G$51 -> $ 000s | H32: =OpCost!H$51 -> -1152373.4 | I32: =OpCost!I$51 -> 0 | J32: =OpCost!J$51 -> 0 | K32: =OpCost!K$51 -> 0 | L32: =OpCost!L$51 -> -6147.2408 | ... CO32: =OpCost!CO$51 -> 0
E33: Operating cash flow | G33: $ 000s | H33: =SUM(J33:CO33) -> 789195.2 | J33: =SUM(J31:J32) -> 0 | K33: =SUM(K31:K32) -> 0 | L33: =SUM(L31:L32) -> 5192.9094 | M33: =SUM(M31:M32) -> 5347.2 | N33: =SUM(N31:N32) -> 5692.6685 | O33: =SUM(O31:O32) -> 5467.0595 | P33: =SUM(P31:P32) -> 5817.5094 | Q33: =SUM(Q31:Q32) -> 5597.2182 | ... CO33: =SUM(CO31:CO32) -> 0
E35: =NCA!E$19 -> Capital expenditure | F35: =NCA!F$19 -> CF | G35: =NCA!G$19 -> $ 000s | H35: =NCA!H$19 -> -8000 | I35: =NCA!I$19 -> 0 | J35: =NCA!J$19 -> 0 | K35: =NCA!K$19 -> 0 | L35: =NCA!L$19 -> 0 | ... CO35: =NCA!CO$19 -> 0
E36: Pre tax pre financing cash flow | G36: $ 000s | H36: =SUM(J36:CO36) -> 781195.2 | J36: =J33 + SUM(J35:J35) -> 0 | K36: =K33 + SUM(K35:K35) -> 0 | L36: =L33 + SUM(L35:L35) -> 5192.9094 | M36: =M33 + SUM(M35:M35) -> 5347.2 | N36: =N33 + SUM(N35:N35) -> 5692.6685 | O36: =O33 + SUM(O35:O35) -> 5467.0595 | P36: =P33 + SUM(P35:P35) -> 5817.5094 | Q36: =Q33 + SUM(Q35:Q35) -> 5597.2182 | ... CO36: =CO33 + SUM(CO35:CO35) -> 0
E38: =Tax!E$32 -> Tax paid | F38: =Tax!F$32 -> CF | G38: =Tax!G$32 -> $ 000s | H38: =Tax!H$32 -> -189665.92 | I38: =Tax!I$32 -> 0 | J38: =Tax!J$32 -> 0 | K38: =Tax!K$32 -> 0 | L38: =Tax!L$32 -> 305.09239 | ... CO38: =Tax!CO$32 -> -5.2918912e-13
E39: Cash flow available for debt service (CFADS) | G39: $ 000s | H39: =SUM(J39:CO39) -> 591529.28 | J39: =J36 + SUM(J38:J38) -> 0 | K39: =K36 + SUM(K38:K38) -> 0 | L39: =L36 + SUM(L38:L38) -> 5498.0018 | M39: =M36 + SUM(M38:M38) -> 5698.6853 | N39: =N36 + SUM(N38:N38) -> 5814.8077 | O39: =O36 + SUM(O38:O38) -> 5630.2757 | P39: =P36 + SUM(P38:P38) -> 5742.4286 | Q39: =Q36 + SUM(Q38:Q38) -> 5576.7962 | ... CO39: =CO36 + SUM(CO38:CO38) -> -5.2918912e-13
E40: =Debt!E$43 -> Senior debt - additional drawdown | F40: =Debt!F$43 -> 0 | G40: =Debt!G$43 -> $ 000s | H40: =SUM(J40:CO40) -> 0 | J40: =Debt!J$43 -> 0 | K40: =Debt!K$43 -> 0 | L40: =Debt!L$43 -> 0 | M40: =Debt!M$43 -> 0 | N40: =Debt!N$43 -> 0 | O40: =Debt!O$43 -> 0 | P40: =Debt!P$43 -> 0 | Q40: =Debt!Q$43 -> 0 | ... CO40: =Debt!CO$43 -> 0
E41: =Debt!E$34 -> Senior debt interest payment | F41: =Debt!F$34 -> IS&CF | G41: =Debt!G$34 -> $ 000s | H41: =Debt!H$34 -> -29083.355 | I41: =Debt!I$34 -> 0 | J41: =Debt!J$34 -> 0 | K41: =Debt!K$34 -> 0 | L41: =Debt!L$34 -> -1172.5062 | ... CO41: =Debt!CO$34 -> 1.7639637e-12
E42: =Debt!E$23 -> Senior debt principal repayment | F42: =Debt!F$23 -> CF | G42: =Debt!G$23 -> $ 000s | H42: =Debt!H$23 -> -72154.225 | I42: =Debt!I$23 -> 0 | J42: =Debt!J$23 -> 0 | K42: =Debt!K$23 -> 0 | L42: =Debt!L$23 -> -1056.8889 | ... CO42: =Debt!CO$23 -> -1.9133988e-12
E43: Cash flow available to shareholders | G43: $ 000s | H43: =SUM(J43:CO43) -> 490291.7 | J43: =J39+SUM(J40:J42) -> 0 | K43: =K39+SUM(K40:K42) -> 0 | L43: =L39+SUM(L40:L42) -> 3268.6067 | M43: =M39+SUM(M40:M42) -> 3381.6235 | N43: =N39+SUM(N40:N42) -> 3445.9616 | O43: =O39+SUM(O40:O42) -> 3340.7707 | P43: =P39+SUM(P40:P42) -> 3395.9644 | Q43: =Q39+SUM(Q40:Q42) -> 3303.498 | ... CO43: =CO39+SUM(CO40:CO42) -> -6.7862415e-13
E44: =DSRA!E$17 -> DSRA (funding) / release | G44: $ 000s | H44: =SUM(J44:CO44) -> -8.2738754e-14 | J44: =DSRA!J$17 -> 0 | K44: =DSRA!K$17 -> 0 | L44: =DSRA!L$17 -> -3268.6067 | M44: =DSRA!M$17 -> -1389.7444 | N44: =DSRA!N$17 -> 22.381873 | O44: =DSRA!O$17 -> 16.206842 | P44: =DSRA!P$17 -> 3.0743241 | Q44: =DSRA!Q$17 -> 899.0089 | ... CO44: =DSRA!CO$17 -> 0
E45: =SHL!E$26 -> Shareholder loan interest paid | G45: $ 000s | H45: =SUM(J45:CO45) -> -18390.596 | J45: =SHL!J$26 -> 0 | K45: =SHL!K$26 -> 0 | L45: =SHL!L$26 -> 0 | M45: =SHL!M$26 -> -449.48561 | N45: =SHL!N$26 -> -454.42501 | O45: =SHL!O$26 -> -454.42501 | P45: =SHL!P$26 -> -444.54621 | Q45: =SHL!Q$26 -> -449.48561 | ... CO45: =SHL!CO$26 -> 0
E46: =SHL!E$27 -> Shareholder loan principal repaid | G46: $ 000s | H46: =SUM(J46:CO46) -> -17781.848 | J46: =SHL!J$27 -> 0 | K46: =SHL!K$27 -> 0 | L46: =SHL!L$27 -> 0 | M46: =SHL!M$27 -> 0 | N46: =SHL!N$27 -> 0 | O46: =SHL!O$27 -> 0 | P46: =SHL!P$27 -> 0 | Q46: =SHL!Q$27 -> 0 | ... CO46: =SHL!CO$27 -> 0
E47: =Equity!E$22 -> Share capital - additional injection | F47: =Equity!F$22 -> 0 | G47: =Equity!G$22 -> $ 000s | H47: =SUM(J47:CO47) -> 0 | J47: =Equity!J$22 -> 0 | K47: =Equity!K$22 -> 0 | L47: =Equity!L$22 -> 0 | M47: =Equity!M$22 -> 0 | N47: =Equity!N$22 -> 0 | O47: =Equity!O$22 -> 0 | P47: =Equity!P$22 -> 0 | Q47: =Equity!Q$22 -> 0 | ... CO47: =Equity!CO$22 -> 0
E48: =Equity!E$11 -> Share capital redemption | F48: =Equity!F$11 -> CF | G48: =Equity!G$11 -> $ 000s | H48: =Equity!H$11 -> -11565.43 | I48: =Equity!I$11 -> 0 | J48: =Equity!J$11 -> 0 | K48: =Equity!K$11 -> 0 | L48: =Equity!L$11 -> 0 | ... CO48: =Equity!CO$11 -> 0
E49: Cash flow available for dividends | G49: $ 000s | H49: =SUM(J49:CO49) -> 442553.82 | J49: =J43+SUM(J44:J48) -> 0 | K49: =K43+SUM(K44:K48) -> 0 | L49: =L43+SUM(L44:L48) -> 0 | M49: =M43+SUM(M44:M48) -> 1542.3935 | N49: =N43+SUM(N44:N48) -> 3013.9184 | O49: =O43+SUM(O44:O48) -> 2902.5525 | P49: =P43+SUM(P44:P48) -> 2954.4925 | Q49: =Q43+SUM(Q44:Q48) -> 3753.0213 | ... CO49: =CO43+SUM(CO44:CO48) -> -6.7862415e-13
E51: =Equity!E$40 -> Dividend declared and paid | F51: =Equity!F$40 -> IS&CF | G51: =Equity!G$40 -> $ 000s | H51: =Equity!H$40 -> -442553.82 | I51: =Equity!I$40 -> 0 | J51: =Equity!J$40 -> 0 | K51: =Equity!K$40 -> 0 | L51: =Equity!L$40 -> 0 | ... CO51: =Equity!CO$40 -> 0
E52: Net cash flow | G52: $ 000s | H52: =SUM(J52:CO52) -> -6.1355924e-12 | J52: =J49 + SUM(J51:J51) -> 0 | K52: =K49 + SUM(K51:K51) -> 0 | L52: =L49 + SUM(L51:L51) -> 0 | M52: =M49 + SUM(M51:M51) -> 0 | N52: =N49 + SUM(N51:N51) -> 0 | O52: =O49 + SUM(O51:O51) -> 1249.994 | P52: =P49 + SUM(P51:P51) -> 1077.2158 | Q52: =Q49 + SUM(Q51:Q51) -> 2147.3425 | ... CO52: =CO49 + SUM(CO51:CO51) -> -6.7862415e-13
E54: Retained cash balance BEG | J54: =I56 -> 0 | K54: =J56 -> 0 | L54: =K56 -> 0 | M54: =L56 -> 0 | N54: =M56 -> 0 | O54: =N56 -> 0 | P54: =O56 -> 1249.994 | Q54: =P56 -> 2327.2098 | ... CO54: =CN56 -> -5.4569682e-12
D55: plus | E55: =E$52 -> Net cash flow | F55: =F$52 -> 0 | G55: $ 000s | H55: =H$52 -> -6.1355924e-12 | I55: =I$52 -> 0 | J55: =J$52 -> 0 | K55: =K$52 -> 0 | L55: =L$52 -> 0 | M55: =M$52 -> 0 | N55: =N$52 -> 0 | O55: =O$52 -> 1249.994 | ... CO55: =CO$52 -> -6.7862415e-13
E56: Retained cash balance | G56: $ 000s | J56: =SUM(J54:J55) -> 0 | K56: =SUM(K54:K55) -> 0 | L56: =SUM(L54:L55) -> 0 | M56: =SUM(M54:M55) -> 0 | N56: =SUM(N54:N55) -> 0 | O56: =SUM(O54:O55) -> 1249.994 | P56: =SUM(P54:P55) -> 2327.2098 | Q56: =SUM(Q54:Q55) -> 4474.5523 | ... CO56: =SUM(CO54:CO55) -> -6.1355924e-12
A59: BALANCE SHEET
B61: Assets
E62: =NCA!E$64 -> Non current asset balance | F62: =NCA!F$64 | G62: =NCA!G$64 -> $ 000s | H62: =NCA!H$64 -> 0 | I62: =NCA!I$64 -> 0 | J62: =NCA!J$64 -> 0 | K62: =NCA!K$64 -> 101067.8 | L62: =NCA!L$64 -> 99383.336 | ... CO62: =NCA!CO$64 -> 8.2309271e-11
E63: =OpRev!E$65 -> Account receivables balance | F63: =OpRev!F$65 -> BS | G63: =OpRev!G$65 -> $ 000s | H63: =OpRev!H$65 -> 0 | I63: =OpRev!I$65 -> 0 | J63: =OpRev!J$65 -> 0 | K63: =OpRev!K$65 -> 0 | L63: =OpRev!L$65 -> 4361.5962 | ... CO63: =OpRev!CO$65 -> 0
E64: =Equity!E$50 -> Retained cash balance | F64: =Equity!F$50 -> BS | G64: =Equity!G$50 -> $ 000s | H64: =Equity!H$50 -> 0 | I64: =Equity!I$50 -> 0 | J64: =Equity!J$50 -> 0 | K64: =Equity!K$50 -> 0 | L64: =Equity!L$50 -> 0 | ... CO64: =Equity!CO$50 -> -6.7862415e-13
E65: =DSRA!E$18 -> DSRA balance END | G65: $ 000s | J65: =DSRA!J$18 -> 0 | K65: =DSRA!K$18 -> 0 | L65: =DSRA!L$18 -> 3268.6067 | M65: =DSRA!M$18 -> 4658.3511 | N65: =DSRA!N$18 -> 4635.9693 | O65: =DSRA!O$18 -> 4619.7624 | P65: =DSRA!P$18 -> 4616.6881 | Q65: =DSRA!Q$18 -> 3717.6792 | ... CO65: =DSRA!CO$18 -> 0
E66: Total assets | G66: $ 000s | J66: =SUM(J62:J65) -> 0 | K66: =SUM(K62:K65) -> 101067.8 | L66: =SUM(L62:L65) -> 107013.54 | M66: =SUM(M62:M65) -> 106529 | N66: =SUM(N62:N65) -> 105071.79 | O66: =SUM(O62:O65) -> 104460.36 | P66: =SUM(P62:P65) -> 104244.31 | Q66: =SUM(Q62:Q65) -> 103567.1 | ... CO66: =SUM(CO62:CO65) -> 8.1630646e-11
B68: Liabilities
E69: =OpCost!E$62 -> Account payables balance | F69: =OpCost!F$62 -> BS | G69: =OpCost!G$62 -> $ 000s | H69: =OpCost!H$62 -> 0 | I69: =OpCost!I$62 -> 0 | J69: =OpCost!J$62 -> 0 | K69: =OpCost!K$62 -> 0 | L69: =OpCost!L$62 -> 3911.8805 | ... CO69: =OpCost!CO$62 -> 0
E70: =Debt!E$45 -> Senior debt balance | F70: =Debt!F$45 -> BS | G70: =Debt!G$45 -> $ 000s | H70: =Debt!H$45 -> 0 | I70: =Debt!I$45 -> 0 | J70: =Debt!J$45 -> 0 | K70: =Debt!K$45 -> 72154.225 | L70: =Debt!L$45 -> 71097.336 | ... CO70: =Debt!CO$45 -> -1.0927214e-10
E71: =SHL!E$24 -> Shareholder loan balance END | G71: $ 000s | J71: =SHL!J$24 -> 0 | K71: =SHL!K$24 -> 17348.145 | L71: =SHL!L$24 -> 17781.848 | M71: =SHL!M$24 -> 17781.848 | N71: =SHL!N$24 -> 17781.848 | O71: =SHL!O$24 -> 17781.848 | P71: =SHL!P$24 -> 17781.848 | Q71: =SHL!Q$24 -> 17781.848 | ... CO71: =SHL!CO$24 -> 0
E72: =Tax!E$49 -> Deferred tax balance | F72: =Tax!F$49 -> BS | G72: =Tax!G$49 -> $ 000s | H72: =Tax!H$49 -> 0 | I72: =Tax!I$49 -> 0 | J72: =Tax!J$49 -> 0 | K72: =Tax!K$49 -> 0 | L72: =Tax!L$49 -> 1010.678 | ... CO72: =Tax!CO$49 -> -4.5474735e-12
E73: =Equity!E$24 -> Share capital balance | F73: =Equity!F$24 -> BS | G73: =Equity!G$24 -> $ 000s | H73: =Equity!H$24 -> 0 | I73: =Equity!I$24 -> 0 | J73: =Equity!J$24 -> 0 | K73: =Equity!K$24 -> 11565.43 | L73: =Equity!L$24 -> 11565.43 | ... CO73: =Equity!CO$24 -> 0
E74: =Equity!E$61 -> Retained earnings balance | F74: =Equity!F$61 -> BS | G74: =Equity!G$61 -> $ 000s | H74: =Equity!H$61 -> 0 | I74: =Equity!I$61 -> 0 | J74: =Equity!J$61 -> 0 | K74: =Equity!K$61 -> 0 | L74: =Equity!L$61 -> 1646.3664 | ... CO74: =Equity!CO$61 -> 1.1583111e-10
E75: Total liabilities and shareholder funds | G75: $ 000s | J75: =SUM(J69:J74) -> 0 | K75: =SUM(K69:K74) -> 101067.8 | L75: =SUM(L69:L74) -> 107013.54 | M75: =SUM(M69:M74) -> 106529 | N75: =SUM(N69:N74) -> 105071.79 | O75: =SUM(O69:O74) -> 104460.36 | P75: =SUM(P69:P74) -> 104244.31 | Q75: =SUM(Q69:Q74) -> 103567.1 | ... CO75: =SUM(CO69:CO74) -> 2.0114953e-12
A78: FINANCIAL STATEMENT CHECKS
E80: FinStat - income statement check | F80: =IF(SUM(J80:CO80) <> 0, 1, 0) -> 0 | G80: check | J80: =IF(ABS(J26 - J74) > CHK_TOL, 1, 0) -> 0 | K80: =IF(ABS(K26 - K74) > CHK_TOL, 1, 0) -> 0 | L80: =IF(ABS(L26 - L74) > CHK_TOL, 1, 0) -> 0 | M80: =IF(ABS(M26 - M74) > CHK_TOL, 1, 0) -> 0 | N80: =IF(ABS(N26 - N74) > CHK_TOL, 1, 0) -> 0 | O80: =IF(ABS(O26 - O74) > CHK_TOL, 1, 0) -> 0 | P80: =IF(ABS(P26 - P74) > CHK_TOL, 1, 0) -> 0 | Q80: =IF(ABS(Q26 - Q74) > CHK_TOL, 1, 0) -> 0 | ... CO80: =IF(ABS(CO26 - CO74) > CHK_TOL, 1, 0) -> 0
E81: FinStat - income statement difference | G81: $ 000s | H81: =SUM(J81:CO81) -> 1.3005774e-10 | J81: =J26 - J74 -> 0 | K81: =K26 - K74 -> 0 | L81: =L26 - L74 -> 0 | M81: =M26 - M74 -> 0 | N81: =N26 - N74 -> 0 | O81: =O26 - O74 -> 0 | P81: =P26 - P74 -> 0 | Q81: =Q26 - Q74 -> 0 | ... CO81: =CO26 - CO74 -> 3.6379788e-12
E83: FinStat - cash flow check | F83: =IF(SUM(J83:CO83) <> 0, 1, 0) -> 0 | G83: check | J83: =IF(ABS(J64 - J56) > CHK_TOL, 1, 0) -> 0 | K83: =IF(ABS(K64 - K56) > CHK_TOL, 1, 0) -> 0 | L83: =IF(ABS(L64 - L56) > CHK_TOL, 1, 0) -> 0 | M83: =IF(ABS(M64 - M56) > CHK_TOL, 1, 0) -> 0 | N83: =IF(ABS(N64 - N56) > CHK_TOL, 1, 0) -> 0 | O83: =IF(ABS(O64 - O56) > CHK_TOL, 1, 0) -> 0 | P83: =IF(ABS(P64 - P56) > CHK_TOL, 1, 0) -> 0 | Q83: =IF(ABS(Q64 - Q56) > CHK_TOL, 1, 0) -> 0 | ... CO83: =IF(ABS(CO64 - CO56) > CHK_TOL, 1, 0) -> 0
E84: FinStat - cash flow difference | G84: $ 000s | H84: =SUM(J84:CO84) -> 1.1186785e-10 | J84: =J64 - J56 -> 0 | K84: =K64 - K56 -> 0 | L84: =L64 - L56 -> 0 | M84: =M64 - M56 -> 0 | N84: =N64 - N56 -> 0 | O84: =O64 - O56 -> 0 | P84: =P64 - P56 -> 0 | Q84: =Q64 - Q56 -> 0 | ... CO84: =CO64 - CO56 -> 5.4569682e-12
E86: FinStat - balance sheet check | F86: =IF(SUM(J86:CO86) <> 0, 1, 0) -> 0 | G86: check | J86: =IF(ABS(J66 - J75) > CHK_TOL, 1, 0) -> 0 | K86: =IF(ABS(K66 - K75) > CHK_TOL, 1, 0) -> 0 | L86: =IF(ABS(L66 - L75) > CHK_TOL, 1, 0) -> 0 | M86: =IF(ABS(M66 - M75) > CHK_TOL, 1, 0) -> 0 | N86: =IF(ABS(N66 - N75) > CHK_TOL, 1, 0) -> 0 | O86: =IF(ABS(O66 - O75) > CHK_TOL, 1, 0) -> 0 | P86: =IF(ABS(P66 - P75) > CHK_TOL, 1, 0) -> 0 | Q86: =IF(ABS(Q66 - Q75) > CHK_TOL, 1, 0) -> 0 | ... CO86: =IF(ABS(CO66 - CO75) > CHK_TOL, 1, 0) -> 0
E87: FinStat - balance sheet difference | G87: $ 000s | H87: =SUM(J87:CO87) -> 8.2300943e-09 | J87: =J66 - J75 -> 0 | K87: =K66 - K75 -> 1.4551915e-11 | L87: =L66 - L75 -> 2.910383e-11 | M87: =M66 - M75 -> 2.910383e-11 | N87: =N66 - N75 -> 5.8207661e-11 | O87: =O66 - O75 -> 4.3655746e-11 | P87: =P66 - P75 -> 4.3655746e-11 | Q87: =Q66 - Q75 -> 2.910383e-11 | ... CO87: =CO66 - CO75 -> 7.9619151e-11
A89: SENIOR DEBT RATIOS
E91: =Debt!E$22 -> Senior debt principal repayment POS | F91: =Debt!F$22 -> 0 | G91: =Debt!G$22 -> $ 000s | H91: =Debt!H$22 -> 72154.225 | J91: =Debt!J$22 -> 0 | K91: =Debt!K$22 -> 0 | L91: =Debt!L$22 -> 1056.8889 | M91: =Debt!M$22 -> 1148.893 | N91: =Debt!N$22 -> 1206.9248 | O91: =Debt!O$22 -> 1147.632 | P91: =Debt!P$22 -> 1248.0636 | Q91: =Debt!Q$22 -> 1183.1995 | ... CO91: =Debt!CO$22 -> 1.9133988e-12
E92: =Debt!E$33 -> Senior debt interest payment POS | F92: =Debt!F$33 -> 0 | G92: =Debt!G$33 -> $ 000s | H92: =Debt!H$33 -> 29083.355 | J92: =Debt!J$33 -> 0 | K92: =Debt!K$33 -> 0 | L92: =Debt!L$33 -> 1172.5062 | M92: =Debt!M$33 -> 1168.1687 | N92: =Debt!N$33 -> 1161.9214 | O92: =Debt!O$33 -> 1141.873 | P92: =Debt!P$33 -> 1098.4006 | Q92: =Debt!Q$33 -> 1090.0987 | ... CO92: =Debt!CO$33 -> -1.7639637e-12
E93: =E$39 -> Cash flow available for debt service (CFADS) | F93: =F$39 -> 0 | G93: =G$39 -> $ 000s | H93: =H$39 -> 591529.28 | J93: =J$39 -> 0 | K93: =K$39 -> 0 | L93: =L$39 -> 5498.0018 | M93: =M$39 -> 5698.6853 | N93: =N$39 -> 5814.8077 | O93: =O$39 -> 5630.2757 | P93: =P$39 -> 5742.4286 | Q93: =Q$39 -> 5576.7962 | ... CO93: =CO$39 -> -5.2918912e-13
E94: Senior debt service | G94: $ 000s | H94: =SUM(J94:CO94) -> 101237.58 | J94: =SUM(J91:J92) -> 0 | K94: =SUM(K91:K92) -> 0 | L94: =SUM(L91:L92) -> 2229.395 | M94: =SUM(M91:M92) -> 2317.0618 | N94: =SUM(N91:N92) -> 2368.8461 | O94: =SUM(O91:O92) -> 2289.505 | P94: =SUM(P91:P92) -> 2346.4642 | Q94: =SUM(Q91:Q92) -> 2273.2982 | ... CO94: =SUM(CO91:CO92) -> 1.4943503e-13
E95: Debt service period flag | G95: flag | H95: =SUM(J95:CO95) -> 40 | J95: =IF(J94>CHK_TOL,1,0) -> 0 | K95: =IF(K94>CHK_TOL,1,0) -> 0 | L95: =IF(L94>CHK_TOL,1,0) -> 1 | M95: =IF(M94>CHK_TOL,1,0) -> 1 | N95: =IF(N94>CHK_TOL,1,0) -> 1 | O95: =IF(O94>CHK_TOL,1,0) -> 1 | P95: =IF(P94>CHK_TOL,1,0) -> 1 | Q95: =IF(Q94>CHK_TOL,1,0) -> 1 | ... CO95: =IF(CO94>CHK_TOL,1,0) -> 0
E96: DSCR (CFADS / debt service) | G96: x | J96: =IF(J95=1,J93/J94,0) -> 0 | K96: =IF(K95=1,K93/K94,0) -> 0 | L96: =IF(L95=1,L93/L94,0) -> 2.4661407 | M96: =IF(M95=1,M93/M94,0) -> 2.4594447 | N96: =IF(N95=1,N93/N94,0) -> 2.4547005 | O96: =IF(O95=1,O93/O94,0) -> 2.4591672 | P96: =IF(P95=1,P93/P94,0) -> 2.4472687 | Q96: =IF(Q95=1,Q93/Q94,0) -> 2.4531741 | ... CO96: =IF(CO95=1,CO93/CO94,0) -> 0
E98: Minimum DSCR | F98: =_xlfn.MINIFS(J96:CO96,J95:CO95,1) -> 2.2966072 | G98: x
E99: Average DSCR | F99: =AVERAGEIFS(J96:CO96,J95:CO95,1) -> 2.3984172 | G99: x
E100: Whole-life cover (CFADS / debt service) | F100: =IF(H94=0,0,H93/H94) -> 5.8429812 | G100: x

Sheet Ratios
A1: =RIGHT(CELL("filename", A1), LEN(CELL("filename", A1)) - SEARCH("]", CELL("filename", A1)))
E2: =Time!E$25 -> Model period ending | J2: =Time!J$25 -> 44469 | K2: =Time!K$25 -> 44561 | L2: =Time!L$25 -> 44651 | M2: =Time!M$25 -> 44742 | N2: =Time!N$25 -> 44834 | O2: =Time!O$25 -> 44926 | P2: =Time!P$25 -> 45016 | Q2: =Time!Q$25 -> 45107 | ... CO2: =Time!CO$25 -> 52047
E3: =Time!E$111 -> Timeline label | J3: =Time!J$111 -> Pre-fcst | K3: =Time!K$111 -> Fin close | L3: =Time!L$111 -> Forecast | M3: =Time!M$111 -> Forecast | N3: =Time!N$111 -> Forecast | O3: =Time!O$111 -> Forecast | P3: =Time!P$111 -> Forecast | Q3: =Time!Q$111 -> Forecast | ... CO3: =Time!CO$111 -> Post-fcst
E4: =Time!E$37 -> Financial year ending | J4: =Time!J$37 -> 2021 | K4: =Time!K$37 -> 2021 | L4: =Time!L$37 -> 2022 | M4: =Time!M$37 -> 2022 | N4: =Time!N$37 -> 2022 | O4: =Time!O$37 -> 2022 | P4: =Time!P$37 -> 2023 | Q4: =Time!Q$37 -> 2023 | ... CO4: =Time!CO$37 -> 2042
E5: =Time!E$10 -> Model column counter | F5: Constant | G5: Unit | H5: Total | J5: =Time!J$10 -> 1 | K5: =Time!K$10 -> 2 | L5: =Time!L$10 -> 3 | M5: =Time!M$10 -> 4 | N5: =Time!N$10 -> 5 | O5: =Time!O$10 -> 6 | P5: =Time!P$10 -> 7 | Q5: =Time!Q$10 -> 8 | ... CO5: =Time!CO$10 -> 84
A7: DEBT SERVICE COVER
E9: Senior debt service | G9: $ 000s | H9: =SUM(J9:CO9) -> 101237.58 | J9: =FinStat!J$94 -> 0 | K9: =FinStat!K$94 -> 0 | L9: =FinStat!L$94 -> 2229.395 | M9: =FinStat!M$94 -> 2317.0618 | N9: =FinStat!N$94 -> 2368.8461 | O9: =FinStat!O$94 -> 2289.505 | P9: =FinStat!P$94 -> 2346.4642 | Q9: =FinStat!Q$94 -> 2273.2982 | ... CO9: =FinStat!CO$94 -> 1.4943503e-13
E10: CFADS | G10: $ 000s | H10: =SUM(J10:CO10) -> 591529.28 | J10: =FinStat!J$39 -> 0 | K10: =FinStat!K$39 -> 0 | L10: =FinStat!L$39 -> 5498.0018 | M10: =FinStat!M$39 -> 5698.6853 | N10: =FinStat!N$39 -> 5814.8077 | O10: =FinStat!O$39 -> 5630.2757 | P10: =FinStat!P$39 -> 5742.4286 | Q10: =FinStat!Q$39 -> 5576.7962 | ... CO10: =FinStat!CO$39 -> -5.2918912e-13
E11: DSCR | G11: x | J11: =FinStat!J$96 -> 0 | K11: =FinStat!K$96 -> 0 | L11: =FinStat!L$96 -> 2.4661407 | M11: =FinStat!M$96 -> 2.4594447 | N11: =FinStat!N$96 -> 2.4547005 | O11: =FinStat!O$96 -> 2.4591672 | P11: =FinStat!P$96 -> 2.4472687 | Q11: =FinStat!Q$96 -> 2.4531741 | ... CO11: =FinStat!CO$96 -> 0
E13: Minimum DSCR | F13: =FinStat!F98 -> 2.2966072 | G13: x
E14: Average DSCR | F14: =FinStat!F99 -> 2.3984172 | G14: x
A16: LOAN LIFE COVER RATIO (LLCR)
E17: Periodic discount rate (debt cost) | G17: % | J17: =Sculpt!J$19 -> 0.016611111 | K17: =Sculpt!K$19 -> 0.016611111 | L17: =Sculpt!L$19 -> 0.01625 | M17: =Sculpt!M$19 -> 0.016430556 | N17: =Sculpt!N$19 -> 0.016611111 | O17: =Sculpt!O$19 -> 0.016611111 | P17: =Sculpt!P$19 -> 0.01625 | Q17: =Sculpt!Q$19 -> 0.016430556 | ... CO17: =Sculpt!CO$19 -> 0.016430556
E18: CFADS in loan life | G18: $ 000s | J18: =FinStat!J$39*Sculpt!J$12 -> 0 | K18: =FinStat!K$39*Sculpt!K$12 -> 0 | L18: =FinStat!L$39*Sculpt!L$12 -> 5498.0018 | M18: =FinStat!M$39*Sculpt!M$12 -> 5698.6853 | N18: =FinStat!N$39*Sculpt!N$12 -> 5814.8077 | O18: =FinStat!O$39*Sculpt!O$12 -> 5630.2757 | P18: =FinStat!P$39*Sculpt!P$12 -> 5742.4286 | Q18: =FinStat!Q$39*Sculpt!Q$12 -> 5576.7962 | ... CO18: =FinStat!CO$39*Sculpt!CO$12 -> 0
E19: PV of CFADS in loan life (END of period) | G19: $ 000s | J19: =(K19+K18)/(1+K17) -> 170330.47 | K19: =(L19+L18)/(1+L17) -> 173159.85 | L19: =(M19+M18)/(1+M17) -> 170475.69 | M19: =(N19+N18)/(1+N17) -> 167578.02 | N19: =(O19+O18)/(1+O17) -> 164546.87 | O19: =(P19+P18)/(1+P17) -> 161649.9 | P19: =(Q19+Q18)/(1+Q17) -> 158534.28 | Q19: =(R19+R18)/(1+R17) -> 155562.29 | ... CO19: =(CP19+CP18)/(1+CP17) -> 0
E20: Senior debt balance END | G20: $ 000s | J20: =Debt!J$45 -> 0 | K20: =Debt!K$45 -> 72154.225 | L20: =Debt!L$45 -> 71097.336 | M20: =Debt!M$45 -> 69948.443 | N20: =Debt!N$45 -> 68741.518 | O20: =Debt!O$45 -> 67593.886 | P20: =Debt!P$45 -> 66345.822 | Q20: =Debt!Q$45 -> 65162.623 | ... CO20: =Debt!CO$45 -> -1.0927214e-10
E21: LLCR | G21: x | J21: =IF(J20>CHK_TOL,J19/J20,0) -> 0 | K21: =IF(K20>CHK_TOL,K19/K20,0) -> 2.3998574 | L21: =IF(L20>CHK_TOL,L19/L20,0) -> 2.3977789 | M21: =IF(M20>CHK_TOL,M19/M20,0) -> 2.3957362 | N21: =IF(N20>CHK_TOL,N19/N20,0) -> 2.3937043 | O21: =IF(O20>CHK_TOL,O19/O20,0) -> 2.391487 | P21: =IF(P20>CHK_TOL,P19/P20,0) -> 2.3895141 | Q21: =IF(Q20>CHK_TOL,Q19/Q20,0) -> 2.3872932 | ... CO21: =IF(CO20>CHK_TOL,CO19/CO20,0) -> 0
E22: LLCR at COD | F22: =SUMPRODUCT(J21:CO21,Time!J45:CO45) -> 2.3998574 | G22: x
A24: PROJECT LIFE COVER RATIO (PLCR)
E25: CFADS in project life | G25: $ 000s | J25: =FinStat!J$39*Time!J$69 -> 0 | K25: =FinStat!K$39*Time!K$69 -> 0 | L25: =FinStat!L$39*Time!L$69 -> 5498.0018 | M25: =FinStat!M$39*Time!M$69 -> 5698.6853 | N25: =FinStat!N$39*Time!N$69 -> 5814.8077 | O25: =FinStat!O$39*Time!O$69 -> 5630.2757 | P25: =FinStat!P$39*Time!P$69 -> 5742.4286 | Q25: =FinStat!Q$39*Time!Q$69 -> 5576.7962 | ... CO25: =FinStat!CO$39*Time!CO$69 -> 0
E26: PV of CFADS in project life (END of period) | G26: $ 000s | J26: =(K26+K25)/(1+K17) -> 297551.87 | K26: =(L26+L25)/(1+L17) -> 302494.54 | L26: =(M26+M25)/(1+M17) -> 301912.08 | M26: =(N26+N25)/(1+N17) -> 301173.97 | N26: =(O26+O25)/(1+O17) -> 300362 | O26: =(P26+P25)/(1+P17) -> 299721.07 | P26: =(Q26+Q25)/(1+Q17) -> 298849.11 | Q26: =(R26+R25)/(1+R17) -> 298182.57 | ... CO26: =(CP26+CP25)/(1+CP17) -> 0
E27: PLCR | G27: x | J27: =IF(J20>CHK_TOL,J26/J20,0) -> 0 | K27: =IF(K20>CHK_TOL,K26/K20,0) -> 4.192333 | L27: =IF(L20>CHK_TOL,L26/L20,0) -> 4.2464612 | M27: =IF(M20>CHK_TOL,M26/M20,0) -> 4.3056566 | N27: =IF(N20>CHK_TOL,N26/N20,0) -> 4.3694409 | O27: =IF(O20>CHK_TOL,O26/O20,0) -> 4.4341447 | P27: =IF(P20>CHK_TOL,P26/P20,0) -> 4.5044149 | Q27: =IF(Q20>CHK_TOL,Q26/Q20,0) -> 4.5759756 | ... CO27: =IF(CO20>CHK_TOL,CO26/CO20,0) -> 0
E28: PLCR at COD | F28: =SUMPRODUCT(J27:CO27,Time!J45:CO45) -> 4.192333 | G28: x

Sheet Val
A1: =RIGHT(CELL("filename", A1), LEN(CELL("filename", A1)) - SEARCH("]", CELL("filename", A1)))
E2: =Time!E$25 -> Model period ending | J2: =Time!J$25 -> 44469 | K2: =Time!K$25 -> 44561 | L2: =Time!L$25 -> 44651 | M2: =Time!M$25 -> 44742 | N2: =Time!N$25 -> 44834 | O2: =Time!O$25 -> 44926 | P2: =Time!P$25 -> 45016 | Q2: =Time!Q$25 -> 45107 | ... CO2: =Time!CO$25 -> 52047
E3: =Time!E$111 -> Timeline label | J3: =Time!J$111 -> Pre-fcst | K3: =Time!K$111 -> Fin close | L3: =Time!L$111 -> Forecast | M3: =Time!M$111 -> Forecast | N3: =Time!N$111 -> Forecast | O3: =Time!O$111 -> Forecast | P3: =Time!P$111 -> Forecast | Q3: =Time!Q$111 -> Forecast | ... CO3: =Time!CO$111 -> Post-fcst
E4: =Time!E$37 -> Financial year ending | J4: =Time!J$37 -> 2021 | K4: =Time!K$37 -> 2021 | L4: =Time!L$37 -> 2022 | M4: =Time!M$37 -> 2022 | N4: =Time!N$37 -> 2022 | O4: =Time!O$37 -> 2022 | P4: =Time!P$37 -> 2023 | Q4: =Time!Q$37 -> 2023 | ... CO4: =Time!CO$37 -> 2042
E5: =Time!E$10 -> Model column counter | F5: Constant | G5: Unit | H5: Total | J5: =Time!J$10 -> 1 | K5: =Time!K$10 -> 2 | L5: =Time!L$10 -> 3 | M5: =Time!M$10 -> 4 | N5: =Time!N$10 -> 5 | O5: =Time!O$10 -> 6 | P5: =Time!P$10 -> 7 | Q5: =Time!Q$10 -> 8 | ... CO5: =Time!CO$10 -> 84
A7: VALUATION
B9: Shareholder discount factor
E10: =InpC!E$90 -> Shareholders valuation date | F10: =InpC!F$90 -> 44561 | G10: =InpC!G$90 -> date
E11: =InpC!E$91 -> Days in shareholder discount year | F11: =InpC!F$91 -> 365 | G11: =InpC!G$91 -> days
E12: =Time!E$25 -> Model period ending | F12: =Time!F$25 -> 0 | G12: =Time!G$25 -> date | H12: =Time!H$25 -> 0 | I12: =Time!I$25 -> 0 | J12: =Time!J$25 -> 44469 | K12: =Time!K$25 -> 44561 | L12: =Time!L$25 -> 44651 | ... CO12: =Time!CO$25 -> 52047
E13: Years from shareholder valuation date | G13: years | J13: =( J12 - $F10) /$F11 -> -0.25205479 | K13: =( K12 - $F10) /$F11 -> 0 | L13: =( L12 - $F10) /$F11 -> 0.24657534 | M13: =( M12 - $F10) /$F11 -> 0.49589041 | N13: =( N12 - $F10) /$F11 -> 0.74794521 | O13: =( O12 - $F10) /$F11 -> 1 | P13: =( P12 - $F10) /$F11 -> 1.2465753 | Q13: =( Q12 - $F10) /$F11 -> 1.4958904 | ... CO13: =( CO12 - $F10) /$F11 -> 20.509589
E15: =InpC!E$93 -> Shareholder required rate of return per annum | F15: =InpC!F$93 -> 0.2525 | G15: =InpC!G$93 -> % p.a
E16: =E$13 -> Years from shareholder valuation date | F16: =F$13 -> 0 | G16: =G$13 -> years | H16: =H$13 -> 0 | I16: =I$13 -> 0 | J16: =J$13 -> -0.25205479 | K16: =K$13 -> 0 | L16: =L$13 -> 0.24657534 | ... CO16: =CO$13 -> 20.509589
E17: Shareholder discount factor | G17: factor | J17: =1 /(1 + $F15) ^ J16 -> 1.0583891 | K17: =1 /(1 + $F15) ^ K16 -> 1 | L17: =1 /(1 + $F15) ^ L16 -> 0.94599844 | M17: =1 /(1 + $F15) ^ M16 -> 0.89436122 | N17: =1 /(1 + $F15) ^ N16 -> 0.84502121 | O17: =1 /(1 + $F15) ^ O16 -> 0.79840319 | P17: =1 /(1 + $F15) ^ P16 -> 0.75528818 | Q17: =1 /(1 + $F15) ^ Q16 -> 0.71406085 | ... CO17: =1 /(1 + $F15) ^ CO16 -> 0.0098768588
B19: Shareholder cashflow
E21: =Equity!E$39 -> Dividend declared and paid POS | F21: =Equity!F$39 -> 0 | G21: =Equity!G$39 -> $ 000s | H21: =Equity!H$39 -> 442553.82 | I21: =Equity!I$39 -> 0 | J21: =Equity!J$39 -> 0 | K21: =Equity!K$39 -> 0 | L21: =Equity!L$39 -> 0 | ... CO21: =Equity!CO$39 -> 0
E22: =Equity!E$10 -> Share capital redemption POS | F22: =Equity!F$10 -> 0 | G22: =Equity!G$10 -> $ 000s | H22: =Equity!H$10 -> 11565.43 | I22: =Equity!I$10 -> 0 | J22: =Equity!J$10 -> 0 | K22: =Equity!K$10 -> 0 | L22: =Equity!L$10 -> 0 | ... CO22: =Equity!CO$10 -> 0
E23: Shareholder loan interest received | F23: =SHL!F$21 -> 0 | G23: =SHL!G$21 -> $ 000s | H23: =SUM(J23:CO23) -> 18390.596 | J23: =SHL!J$21 -> 0 | K23: =SHL!K$21 -> 0 | L23: =SHL!L$21 -> 0 | M23: =SHL!M$21 -> 449.48561 | N23: =SHL!N$21 -> 454.42501 | O23: =SHL!O$21 -> 454.42501 | P23: =SHL!P$21 -> 444.54621 | Q23: =SHL!Q$21 -> 449.48561 | ... CO23: =SHL!CO$21 -> 0
E24: Shareholder loan principal received | F24: =SHL!F$23 -> 0 | G24: =SHL!G$23 -> $ 000s | H24: =SUM(J24:CO24) -> 17781.848 | J24: =SHL!J$23 -> 0 | K24: =SHL!K$23 -> 0 | L24: =SHL!L$23 -> 0 | M24: =SHL!M$23 -> 0 | N24: =SHL!N$23 -> 0 | O24: =SHL!O$23 -> 0 | P24: =SHL!P$23 -> 0 | Q24: =SHL!Q$23 -> 0 | ... CO24: =SHL!CO$23 -> 0
E25: Shareholder cash inflow | G25: =SMU -> $ 000s | H25: =SUM(J25:CO25) -> 490291.7 | J25: =SUM(J21:J24) -> 0 | K25: =SUM(K21:K24) -> 0 | L25: =SUM(L21:L24) -> 0 | M25: =SUM(M21:M24) -> 1991.8791 | N25: =SUM(N21:N24) -> 3468.3434 | O25: =SUM(O21:O24) -> 2106.9835 | P25: =SUM(P21:P24) -> 2321.8229 | Q25: =SUM(Q21:Q24) -> 2055.1644 | ... CO25: =SUM(CO21:CO24) -> 0
E26: =Equity!E$22 -> Share capital - additional injection | F26: =Equity!F$22 -> 0 | G26: =Equity!G$22 -> $ 000s | H26: =SUM(J26:CO26) -> 0 | J26: =Equity!J$22 -> 0 | K26: =Equity!K$22 -> 0 | L26: =Equity!L$22 -> 0 | M26: =Equity!M$22 -> 0 | N26: =Equity!N$22 -> 0 | O26: =Equity!O$22 -> 0 | P26: =Equity!P$22 -> 0 | Q26: =Equity!Q$22 -> 0 | ... CO26: =Equity!CO$22 -> 0
E27: =SHL!E$12 -> Sponsor funding at COD | F27: =SHL!F$12 -> 28913.574 | G27: =SHL!G$12 -> $ 000s
E28: =Time!E$45 -> Acquisition / initial balance date flag | F28: =Time!F$45 -> 0 | G28: =Time!G$45 -> flag | H28: =Time!H$45 -> 1 | I28: =Time!I$45 -> 0 | J28: =Time!J$45 -> 0 | K28: =Time!K$45 -> 1 | L28: =Time!L$45 -> 0 | ... CO28: =Time!CO$45 -> 0
E29: Shareholder cash outflow | G29: =SMU -> $ 000s | J29: =IF(J28=1,$F27,0)+J26 -> 0 | K29: =IF(K28=1,$F27,0)+K26 -> 28913.574 | L29: =IF(L28=1,$F27,0)+L26 -> 0 | M29: =IF(M28=1,$F27,0)+M26 -> 0 | N29: =IF(N28=1,$F27,0)+N26 -> 0 | O29: =IF(O28=1,$F27,0)+O26 -> 0 | P29: =IF(P28=1,$F27,0)+P26 -> 0 | Q29: =IF(Q28=1,$F27,0)+Q26 -> 0 | ... CO29: =IF(CO28=1,$F27,0)+CO26 -> 0
E31: =E$25 -> Shareholder cash inflow | F31: =F$25 -> 0 | G31: =G$25 -> $ 000s | H31: =H$25 -> 490291.7 | I31: =I$25 -> 0 | J31: =J$25 -> 0 | K31: =K$25 -> 0 | L31: =L$25 -> 0 | ... CO31: =CO$25 -> 0
D32: less | E32: =E$29 -> Shareholder cash outflow | F32: =F$29 -> 0 | G32: =G$29 -> $ 000s | H32: =H$29 -> 0 | I32: =I$29 -> 0 | J32: =J$29 -> 0 | K32: =K$29 -> 28913.574 | L32: =L$29 -> 0 | ... CO32: =CO$29 -> 0
E33: Shareholder cashflows | G33: =SMU -> $ 000s | H33: =SUM(J33:CO33) -> 461378.12 | J33: =J31 - J32 -> 0 | K33: =K31 - K32 -> -28913.574 | L33: =L31 - L32 -> 0 | M33: =M31 - M32 -> 1991.8791 | N33: =N31 - N32 -> 3468.3434 | O33: =O31 - O32 -> 2106.9835 | P33: =P31 - P32 -> 2321.8229 | Q33: =Q31 - Q32 -> 2055.1644 | ... CO33: =CO31 - CO32 -> 0
B35: NPV of shareholder cashflow
E36: =E$33 -> Shareholder cashflows | F36: =F$33 -> 0 | G36: =G$33 -> $ 000s | H36: =H$33 -> 461378.12 | I36: =I$33 -> 0 | J36: =J$33 -> 0 | K36: =K$33 -> -28913.574 | L36: =L$33 -> 0 | ... CO36: =CO$33 -> 0
E37: =E$17 -> Shareholder discount factor | F37: =F$17 -> 0 | G37: =G$17 -> factor | H37: =H$17 -> 0 | I37: =I$17 -> 0 | J37: =J$17 -> 1.0583891 | K37: =K$17 -> 1 | L37: =L$17 -> 0.94599844 | ... CO37: =CO$17 -> 0.0098768588
E38: PV of shareholder cashflow | G38: =SMU -> $ 000s | J38: =J36 * J37 -> 0 | K38: =K36 * K37 -> -28913.574 | L38: =L36 * L37 -> 0 | M38: =M36 * M37 -> 1781.4594 | N38: =N36 * N37 -> 2930.8238 | O38: =O36 * O37 -> 1682.2224 | P38: =P36 * P37 -> 1753.6454 | Q38: =Q36 * Q37 -> 1467.5125 | ... CO38: =CO36 * CO37 -> 0
E40: =E$38 -> PV of shareholder cashflow | F40: =F$38 -> 0 | G40: =G$38 -> $ 000s | H40: =H$38 -> 0 | I40: =I$38 -> 0 | J40: =J$38 -> 0 | K40: =K$38 -> -28913.574 | L40: =L$38 -> 0 | ... CO40: =CO$38 -> 0
E41: NPV of shareholder cashflow | F41: =SUM(J40:CO40) -> 28243.56 | G41: =SMU -> $ 000s
A44: Shareholder internal rate of return
E45: =E$33 -> Shareholder cashflows | F45: =F$33 -> 0 | G45: =G$33 -> $ 000s | H45: =H$33 -> 461378.12 | I45: =I$33 -> 0 | J45: =J$33 -> 0 | K45: =K$33 -> -28913.574 | L45: =L$33 -> 0 | ... CO45: =CO$33 -> 0
E46: =Time!E$14 -> First model column flag | F46: =Time!F$14 -> 0 | G46: =Time!G$14 -> flag | H46: =Time!H$14 -> 1 | I46: =Time!I$14 -> 0 | J46: =Time!J$14 -> 1 | K46: =Time!K$14 -> 0 | L46: =Time!L$14 -> 0 | ... CO46: =Time!CO$14 -> 0
E47: Shareholder cashflow for XIRR | G47: =SMU -> $ 000s | J47: =IF(AND(J45 = 0, J46 = 1), -1 *0.001, J45) -> -0.001 | K47: =IF(AND(K45 = 0, K46 = 1), -1 *0.001, K45) -> -28913.574 | L47: =IF(AND(L45 = 0, L46 = 1), -1 *0.001, L45) -> 0 | M47: =IF(AND(M45 = 0, M46 = 1), -1 *0.001, M45) -> 1991.8791 | N47: =IF(AND(N45 = 0, N46 = 1), -1 *0.001, N45) -> 3468.3434 | O47: =IF(AND(O45 = 0, O46 = 1), -1 *0.001, O45) -> 2106.9835 | P47: =IF(AND(P45 = 0, P46 = 1), -1 *0.001, P45) -> 2321.8229 | Q47: =IF(AND(Q45 = 0, Q46 = 1), -1 *0.001, Q45) -> 2055.1644 | ... CO47: =IF(AND(CO45 = 0, CO46 = 1), -1 *0.001, CO45) -> 0
E49: =E$47 -> Shareholder cashflow for XIRR | F49: =F$47 -> 0 | G49: =G$47 -> $ 000s | H49: =H$47 -> 0 | I49: =I$47 -> 0 | J49: =J$47 -> -0.001 | K49: =K$47 -> -28913.574 | L49: =L$47 -> 0 | ... CO49: =CO$47 -> 0
E50: =Time!E$25 -> Model period ending | F50: =Time!F$25 -> 0 | G50: =Time!G$25 -> date | H50: =Time!H$25 -> 0 | I50: =Time!I$25 -> 0 | J50: =Time!J$25 -> 44469 | K50: =Time!K$25 -> 44561 | L50: =Time!L$25 -> 44651 | ... CO50: =Time!CO$25 -> 52047
E51: Shareholder internal rate of return | F51: =XIRR(J49:CO49,J50:CO50) -> 0.43033599 | G51: %p.a

Sheet Track
A1: =RIGHT(CELL("filename", $A$1), LEN(CELL("filename", $A$1)) - SEARCH("]", CELL("filename", $A$1))) | M1: do not del col | O1: do not del col
H2: =TODAY() -> 46305 | J2: =SUM(J6:J75) -> 56
E5: Comparison column label | H5: Base | J5: =MATCH($H$5, M5:O5, 0) -> 1 | K5: Difference | L5: Diff Pct | M5: Base | N5: Downside | O5: Upside
E6: [do not delete row] | J6: range start
A7: KEY OUTPUTS
E8: Sponsor NPV at required return (blended) | G8: $ 000s | H8: =Val!F41 -> 28243.56 | J8: =IF(ABS(K8) > CHK_TOL, 1, 0) -> 1 | K8: =H8 - INDEX(M8:O8, $J$5) -> 28243.56 | L8: =IF(ABS(K8) > CHK_TOL, IF(INDEX(M8:O8, $J$5) = 0, 0, H8 / INDEX(M8:O8, $J$5) - 1), 0) -> 0 | M8: 28243.56 | N8: -7230.7246 | O8: 53023.72
E9: Sponsor IRR (XIRR, blended) | G9: % p.a. | H9: =Val!F51 -> 0.43033599 | J9: =IF(ABS(K9) > CHK_TOL, 1, 0) -> 1 | K9: =H9 - INDEX(M9:O9, $J$5) -> 0.43033599 | L9: =IF(ABS(K9) > CHK_TOL, IF(INDEX(M9:O9, $J$5) = 0, 0, H9 / INDEX(M9:O9, $J$5) - 1), 0) -> 0 | M9: 0.43033599 | N9: 0.22341088 | O9: 0.66902968
E10: Total CFADS (20 years) | G10: $ 000s | H10: =FinStat!H39 -> 591529.28 | J10: =IF(ABS(K10) > CHK_TOL, 1, 0) -> 1 | K10: =H10 - INDEX(M10:O10, $J$5) -> 591529.28 | L10: =IF(ABS(K10) > CHK_TOL, IF(INDEX(M10:O10, $J$5) = 0, 0, H10 / INDEX(M10:O10, $J$5) - 1), 0) -> 0 | M10: 591529.28 | N10: 449171.59 | O10: 727308.46
E11: Minimum DSCR | G11: x | H11: =Ratios!F13 -> 2.2966072 | J11: =IF(ABS(K11) > CHK_TOL, 1, 0) -> 1 | K11: =H11 - INDEX(M11:O11, $J$5) -> 2.2966072 | L11: =IF(ABS(K11) > CHK_TOL, IF(INDEX(M11:O11, $J$5) = 0, 0, H11 / INDEX(M11:O11, $J$5) - 1), 0) -> 0 | M11: 2.2966072 | N11: 2.3424559 | O11: 2.6820116
E12: Senior debt at financial close | G12: $ 000s | H12: =Debt!F11 -> 72154.225 | J12: =IF(ABS(K12) > CHK_TOL, 1, 0) -> 1 | K12: =H12 - INDEX(M12:O12, $J$5) -> 72154.225 | L12: =IF(ABS(K12) > CHK_TOL, IF(INDEX(M12:O12, $J$5) = 0, 0, H12 / INDEX(M12:O12, $J$5) - 1), 0) -> 0 | M12: 72154.225 | N12: 53910.521 | O12: 76052.238
A13: PROFIT & LOSS
E14: Operating revenue | G14: $ 000s | H14: =FinStat!H9 -> 1941568.6 | J14: =IF(ABS(K14) > CHK_TOL, 1, 0) -> 1 | K14: =H14 - INDEX(M14:O14, $J$5) -> 1941568.6 | L14: =IF(ABS(K14) > CHK_TOL, IF(INDEX(M14:O14, $J$5) = 0, 0, H14 / INDEX(M14:O14, $J$5) - 1), 0) -> 0 | M14: 1941568.6 | N14: 1747411.8 | O14: 2135725.5
E15: Operating cost | G15: $ 000s | H15: =FinStat!H10 -> -1152373.4 | J15: =IF(ABS(K15) > CHK_TOL, 1, 0) -> 1 | K15: =H15 - INDEX(M15:O15, $J$5) -> -1152373.4 | L15: =IF(ABS(K15) > CHK_TOL, IF(INDEX(M15:O15, $J$5) = 0, 0, H15 / INDEX(M15:O15, $J$5) - 1), 0) -> 0 | M15: -1152373.4 | N15: -1162860.9 | O15: -1152373.4
E16: EBITDA | G16: $ 000s | H16: =FinStat!H11 -> 789195.2 | J16: =IF(ABS(K16) > CHK_TOL, 1, 0) -> 1 | K16: =H16 - INDEX(M16:O16, $J$5) -> 789195.2 | L16: =IF(ABS(K16) > CHK_TOL, IF(INDEX(M16:O16, $J$5) = 0, 0, H16 / INDEX(M16:O16, $J$5) - 1), 0) -> 0 | M16: 789195.2 | N16: 584550.9 | O16: 983352.06
E17: EBITDA margin | G17: % | H17: =IF(H14=0,0,H16/H14) -> 0.40647299 | J17: =IF(ABS(K17) > CHK_TOL, 1, 0) -> 1 | K17: =H17 - INDEX(M17:O17, $J$5) -> 0.40647299 | L17: =IF(ABS(K17) > CHK_TOL, IF(INDEX(M17:O17, $J$5) = 0, 0, H17 / INDEX(M17:O17, $J$5) - 1), 0) -> 0 | M17: 0.40647299 | N17: 0.33452384 | O17: 0.46042999
E18: Accounting depreciation | G18: $ 000s | H18: =FinStat!H13 -> -109067.8 | J18: =IF(ABS(K18) > CHK_TOL, 1, 0) -> 1 | K18: =H18 - INDEX(M18:O18, $J$5) -> -109067.8 | L18: =IF(ABS(K18) > CHK_TOL, IF(INDEX(M18:O18, $J$5) = 0, 0, H18 / INDEX(M18:O18, $J$5) - 1), 0) -> 0 | M18: -109067.8 | N18: -107498.17 | O18: -109402.98
E19: Senior debt interest | G19: $ 000s | H19: =FinStat!H14 -> -29083.355 | J19: =IF(ABS(K19) > CHK_TOL, 1, 0) -> 1 | K19: =H19 - INDEX(M19:O19, $J$5) -> -29083.355 | L19: =IF(ABS(K19) > CHK_TOL, IF(INDEX(M19:O19, $J$5) = 0, 0, H19 / INDEX(M19:O19, $J$5) - 1), 0) -> 0 | M19: -29083.355 | N19: -21609.716 | O19: -30771.769
E20: Profit before tax | G20: $ 000s | H20: =FinStat!H16 -> 632219.75 | J20: =IF(ABS(K20) > CHK_TOL, 1, 0) -> 1 | K20: =H20 - INDEX(M20:O20, $J$5) -> 632219.75 | L20: =IF(ABS(K20) > CHK_TOL, IF(INDEX(M20:O20, $J$5) = 0, 0, H20 / INDEX(M20:O20, $J$5) - 1), 0) -> 0 | M20: 632219.75 | N20: 424597.7 | O20: 826812.03
E21: Tax expense | G21: $ 000s | H21: =FinStat!H18 -> -189665.92 | J21: =IF(ABS(K21) > CHK_TOL, 1, 0) -> 1 | K21: =H21 - INDEX(M21:O21, $J$5) -> -189665.92 | L21: =IF(ABS(K21) > CHK_TOL, IF(INDEX(M21:O21, $J$5) = 0, 0, H21 / INDEX(M21:O21, $J$5) - 1), 0) -> 0 | M21: -189665.92 | N21: -127379.31 | O21: -248043.61
E22: Profit after tax | G22: $ 000s | H22: =FinStat!H19 -> 442553.82 | J22: =IF(ABS(K22) > CHK_TOL, 1, 0) -> 1 | K22: =H22 - INDEX(M22:O22, $J$5) -> 442553.82 | L22: =IF(ABS(K22) > CHK_TOL, IF(INDEX(M22:O22, $J$5) = 0, 0, H22 / INDEX(M22:O22, $J$5) - 1), 0) -> 0 | M22: 442553.82 | N22: 297218.39 | O22: 578768.42
E23: Effective tax rate | G23: % | H23: =IF(H20=0,0,-H21/H20) -> 0.3 | J23: =IF(ABS(K23) > CHK_TOL, 1, 0) -> 1 | K23: =H23 - INDEX(M23:O23, $J$5) -> 0.3 | L23: =IF(ABS(K23) > CHK_TOL, IF(INDEX(M23:O23, $J$5) = 0, 0, H23 / INDEX(M23:O23, $J$5) - 1), 0) -> 0 | M23: 0.3 | N23: 0.3 | O23: 0.3
E24: ="Operating revenue FY"&F24 -> Operating revenue FY2022 | F24: 2022 | G24: $ 000s | H24: =SUMIFS(FinStat!$J$9:$CO$9,FinStat!$J$4:$CO$4,$F24) -> 62837.028 | J24: =IF(ABS(K24) > CHK_TOL, 1, 0) -> 1 | K24: =H24 - INDEX(M24:O24, $J$5) -> 62837.028 | L24: =IF(ABS(K24) > CHK_TOL, IF(INDEX(M24:O24, $J$5) = 0, 0, H24 / INDEX(M24:O24, $J$5) - 1), 0) -> 0 | M24: 62837.028 | N24: 56553.326 | O24: 69120.731
E25: ="Operating revenue FY"&F25 -> Operating revenue FY2023 | F25: 2023 | G25: $ 000s | H25: =SUMIFS(FinStat!$J$9:$CO$9,FinStat!$J$4:$CO$4,$F25) -> 66458.897 | J25: =IF(ABS(K25) > CHK_TOL, 1, 0) -> 1 | K25: =H25 - INDEX(M25:O25, $J$5) -> 66458.897 | L25: =IF(ABS(K25) > CHK_TOL, IF(INDEX(M25:O25, $J$5) = 0, 0, H25 / INDEX(M25:O25, $J$5) - 1), 0) -> 0 | M25: 66458.897 | N25: 59813.007 | O25: 73104.787
E26: ="Operating revenue FY"&F26 -> Operating revenue FY2024 | F26: 2024 | G26: $ 000s | H26: =SUMIFS(FinStat!$J$9:$CO$9,FinStat!$J$4:$CO$4,$F26) -> 70598.708 | J26: =IF(ABS(K26) > CHK_TOL, 1, 0) -> 1 | K26: =H26 - INDEX(M26:O26, $J$5) -> 70598.708 | L26: =IF(ABS(K26) > CHK_TOL, IF(INDEX(M26:O26, $J$5) = 0, 0, H26 / INDEX(M26:O26, $J$5) - 1), 0) -> 0 | M26: 70598.708 | N26: 63538.837 | O26: 77658.579
E27: ="Operating revenue FY"&F27 -> Operating revenue FY2025 | F27: 2025 | G27: $ 000s | H27: =SUMIFS(FinStat!$J$9:$CO$9,FinStat!$J$4:$CO$4,$F27) -> 72981.116 | J27: =IF(ABS(K27) > CHK_TOL, 1, 0) -> 1 | K27: =H27 - INDEX(M27:O27, $J$5) -> 72981.116 | L27: =IF(ABS(K27) > CHK_TOL, IF(INDEX(M27:O27, $J$5) = 0, 0, H27 / INDEX(M27:O27, $J$5) - 1), 0) -> 0 | M27: 72981.116 | N27: 65683.004 | O27: 80279.228
E28: ="Operating revenue FY"&F28 -> Operating revenue FY2026 | F28: 2026 | G28: $ 000s | H28: =SUMIFS(FinStat!$J$9:$CO$9,FinStat!$J$4:$CO$4,$F28) -> 76493.107 | J28: =IF(ABS(K28) > CHK_TOL, 1, 0) -> 1 | K28: =H28 - INDEX(M28:O28, $J$5) -> 76493.107 | L28: =IF(ABS(K28) > CHK_TOL, IF(INDEX(M28:O28, $J$5) = 0, 0, H28 / INDEX(M28:O28, $J$5) - 1), 0) -> 0 | M28: 76493.107 | N28: 68843.796 | O28: 84142.418
E29: ="Operating revenue FY"&F29 -> Operating revenue FY2027 | F29: 2027 | G29: $ 000s | H29: =SUMIFS(FinStat!$J$9:$CO$9,FinStat!$J$4:$CO$4,$F29) -> 80130.149 | J29: =IF(ABS(K29) > CHK_TOL, 1, 0) -> 1 | K29: =H29 - INDEX(M29:O29, $J$5) -> 80130.149 | L29: =IF(ABS(K29) > CHK_TOL, IF(INDEX(M29:O29, $J$5) = 0, 0, H29 / INDEX(M29:O29, $J$5) - 1), 0) -> 0 | M29: 80130.149 | N29: 72117.134 | O29: 88143.164
A30: CASH FLOW CASCADE
E31: Operating revenue received | G31: $ 000s | H31: =FinStat!H31 -> 1941568.6 | J31: =IF(ABS(K31) > CHK_TOL, 1, 0) -> 1 | K31: =H31 - INDEX(M31:O31, $J$5) -> 1941568.6 | L31: =IF(ABS(K31) > CHK_TOL, IF(INDEX(M31:O31, $J$5) = 0, 0, H31 / INDEX(M31:O31, $J$5) - 1), 0) -> 0 | M31: 1941568.6 | N31: 1747411.8 | O31: 2135725.5
E32: Operating cost paid | G32: $ 000s | H32: =FinStat!H32 -> -1152373.4 | J32: =IF(ABS(K32) > CHK_TOL, 1, 0) -> 1 | K32: =H32 - INDEX(M32:O32, $J$5) -> -1152373.4 | L32: =IF(ABS(K32) > CHK_TOL, IF(INDEX(M32:O32, $J$5) = 0, 0, H32 / INDEX(M32:O32, $J$5) - 1), 0) -> 0 | M32: -1152373.4 | N32: -1162860.9 | O32: -1152373.4
E33: Operating cash flow | G33: $ 000s | H33: =FinStat!H33 -> 789195.2 | J33: =IF(ABS(K33) > CHK_TOL, 1, 0) -> 1 | K33: =H33 - INDEX(M33:O33, $J$5) -> 789195.2 | L33: =IF(ABS(K33) > CHK_TOL, IF(INDEX(M33:O33, $J$5) = 0, 0, H33 / INDEX(M33:O33, $J$5) - 1), 0) -> 0 | M33: 789195.2 | N33: 584550.9 | O33: 983352.06
E34: Capital expenditure | G34: $ 000s | H34: =FinStat!H35 -> -8000 | J34: =IF(ABS(K34) > CHK_TOL, 1, 0) -> 1 | K34: =H34 - INDEX(M34:O34, $J$5) -> -8000 | L34: =IF(ABS(K34) > CHK_TOL, IF(INDEX(M34:O34, $J$5) = 0, 0, H34 / INDEX(M34:O34, $J$5) - 1), 0) -> 0 | M34: -8000 | N34: -8000 | O34: -8000
E35: Pre-tax pre-financing cash flow | G35: $ 000s | H35: =FinStat!H36 -> 781195.2 | J35: =IF(ABS(K35) > CHK_TOL, 1, 0) -> 1 | K35: =H35 - INDEX(M35:O35, $J$5) -> 781195.2 | L35: =IF(ABS(K35) > CHK_TOL, IF(INDEX(M35:O35, $J$5) = 0, 0, H35 / INDEX(M35:O35, $J$5) - 1), 0) -> 0 | M35: 781195.2 | N35: 576550.9 | O35: 975352.06
E36: Tax paid | G36: $ 000s | H36: =FinStat!H38 -> -189665.92 | J36: =IF(ABS(K36) > CHK_TOL, 1, 0) -> 1 | K36: =H36 - INDEX(M36:O36, $J$5) -> -189665.92 | L36: =IF(ABS(K36) > CHK_TOL, IF(INDEX(M36:O36, $J$5) = 0, 0, H36 / INDEX(M36:O36, $J$5) - 1), 0) -> 0 | M36: -189665.92 | N36: -127379.31 | O36: -248043.61
E37: CFADS | G37: $ 000s | H37: =FinStat!H39 -> 591529.28 | J37: =IF(ABS(K37) > CHK_TOL, 1, 0) -> 1 | K37: =H37 - INDEX(M37:O37, $J$5) -> 591529.28 | L37: =IF(ABS(K37) > CHK_TOL, IF(INDEX(M37:O37, $J$5) = 0, 0, H37 / INDEX(M37:O37, $J$5) - 1), 0) -> 0 | M37: 591529.28 | N37: 449171.59 | O37: 727308.46
E38: Senior debt interest paid | G38: $ 000s | H38: =FinStat!H41 -> -29083.355 | J38: =IF(ABS(K38) > CHK_TOL, 1, 0) -> 1 | K38: =H38 - INDEX(M38:O38, $J$5) -> -29083.355 | L38: =IF(ABS(K38) > CHK_TOL, IF(INDEX(M38:O38, $J$5) = 0, 0, H38 / INDEX(M38:O38, $J$5) - 1), 0) -> 0 | M38: -29083.355 | N38: -21609.716 | O38: -30771.769
E39: Senior debt principal repaid | G39: $ 000s | H39: =FinStat!H42 -> -72154.225 | J39: =IF(ABS(K39) > CHK_TOL, 1, 0) -> 1 | K39: =H39 - INDEX(M39:O39, $J$5) -> -72154.225 | L39: =IF(ABS(K39) > CHK_TOL, IF(INDEX(M39:O39, $J$5) = 0, 0, H39 / INDEX(M39:O39, $J$5) - 1), 0) -> 0 | M39: -72154.225 | N39: -53910.521 | O39: -76052.238
E40: Cash flow available to shareholders | G40: $ 000s | H40: =FinStat!H43 -> 490291.7 | J40: =IF(ABS(K40) > CHK_TOL, 1, 0) -> 1 | K40: =H40 - INDEX(M40:O40, $J$5) -> 490291.7 | L40: =IF(ABS(K40) > CHK_TOL, IF(INDEX(M40:O40, $J$5) = 0, 0, H40 / INDEX(M40:O40, $J$5) - 1), 0) -> 0 | M40: 490291.7 | N40: 373651.35 | O40: 620484.45
E41: Share capital redemption | G41: $ 000s | H41: =FinStat!H48 -> -11565.43 | J41: =IF(ABS(K41) > CHK_TOL, 1, 0) -> 1 | K41: =H41 - INDEX(M41:O41, $J$5) -> -11565.43 | L41: =IF(ABS(K41) > CHK_TOL, IF(INDEX(M41:O41, $J$5) = 0, 0, H41 / INDEX(M41:O41, $J$5) - 1), 0) -> 0 | M41: -11565.43 | N41: -18235.06 | O41: -10140.298
E42: Cash flow available for dividends | G42: $ 000s | H42: =FinStat!H49 -> 442553.82 | J42: =IF(ABS(K42) > CHK_TOL, 1, 0) -> 1 | K42: =H42 - INDEX(M42:O42, $J$5) -> 442553.82 | L42: =IF(ABS(K42) > CHK_TOL, IF(INDEX(M42:O42, $J$5) = 0, 0, H42 / INDEX(M42:O42, $J$5) - 1), 0) -> 0 | M42: 442553.82 | N42: 297218.39 | O42: 578768.42
E43: Dividends paid | G43: $ 000s | H43: =FinStat!H51 -> -442553.82 | J43: =IF(ABS(K43) > CHK_TOL, 1, 0) -> 1 | K43: =H43 - INDEX(M43:O43, $J$5) -> -442553.82 | L43: =IF(ABS(K43) > CHK_TOL, IF(INDEX(M43:O43, $J$5) = 0, 0, H43 / INDEX(M43:O43, $J$5) - 1), 0) -> 0 | M43: -442553.82 | N43: -297218.39 | O43: -578768.42
E44: Net cash flow | G44: $ 000s | H44: =FinStat!H52 -> -6.1355924e-12 | J44: =IF(ABS(K44) > CHK_TOL, 1, 0) -> 0 | K44: =H44 - INDEX(M44:O44, $J$5) -> -6.1355924e-12 | L44: =IF(ABS(K44) > CHK_TOL, IF(INDEX(M44:O44, $J$5) = 0, 0, H44 / INDEX(M44:O44, $J$5) - 1), 0) -> 0 | M44: -6.1355924e-12 | N44: -3.4165216e-13 | O44: -1.0115033e-12
E45: ="CFADS FY"&F45 -> CFADS FY2022 | F45: 2022 | G45: $ 000s | H45: =SUMIFS(FinStat!$J$39:$CO$39,FinStat!$J$4:$CO$4,$F45) -> 22641.77 | J45: =IF(ABS(K45) > CHK_TOL, 1, 0) -> 1 | K45: =H45 - INDEX(M45:O45, $J$5) -> 22641.77 | L45: =IF(ABS(K45) > CHK_TOL, IF(INDEX(M45:O45, $J$5) = 0, 0, H45 / INDEX(M45:O45, $J$5) - 1), 0) -> 0 | M45: 22641.77 | N45: 18308.272 | O45: 26645.845
E46: ="CFADS FY"&F46 -> CFADS FY2023 | F46: 2023 | G46: $ 000s | H46: =SUMIFS(FinStat!$J$39:$CO$39,FinStat!$J$4:$CO$4,$F46) -> 20599.828 | J46: =IF(ABS(K46) > CHK_TOL, 1, 0) -> 1 | K46: =H46 - INDEX(M46:O46, $J$5) -> 20599.828 | L46: =IF(ABS(K46) > CHK_TOL, IF(INDEX(M46:O46, $J$5) = 0, 0, H46 / INDEX(M46:O46, $J$5) - 1), 0) -> 0 | M46: 20599.828 | N46: 15595.585 | O46: 25257.879
E47: ="CFADS FY"&F47 -> CFADS FY2024 | F47: 2024 | G47: $ 000s | H47: =SUMIFS(FinStat!$J$39:$CO$39,FinStat!$J$4:$CO$4,$F47) -> 22274.917 | J47: =IF(ABS(K47) > CHK_TOL, 1, 0) -> 1 | K47: =H47 - INDEX(M47:O47, $J$5) -> 22274.917 | L47: =IF(ABS(K47) > CHK_TOL, IF(INDEX(M47:O47, $J$5) = 0, 0, H47 / INDEX(M47:O47, $J$5) - 1), 0) -> 0 | M47: 22274.917 | N47: 17015.882 | O47: 27209.394
E48: ="CFADS FY"&F48 -> CFADS FY2025 | F48: 2025 | G48: $ 000s | H48: =SUMIFS(FinStat!$J$39:$CO$39,FinStat!$J$4:$CO$4,$F48) -> 21693.19 | J48: =IF(ABS(K48) > CHK_TOL, 1, 0) -> 1 | K48: =H48 - INDEX(M48:O48, $J$5) -> 21693.19 | L48: =IF(ABS(K48) > CHK_TOL, IF(INDEX(M48:O48, $J$5) = 0, 0, H48 / INDEX(M48:O48, $J$5) - 1), 0) -> 0 | M48: 21693.19 | N48: 16282.784 | O48: 26798.148
E49: ="CFADS FY"&F49 -> CFADS FY2026 | F49: 2026 | G49: $ 000s | H49: =SUMIFS(FinStat!$J$39:$CO$39,FinStat!$J$4:$CO$4,$F49) -> 22880.839 | J49: =IF(ABS(K49) > CHK_TOL, 1, 0) -> 1 | K49: =H49 - INDEX(M49:O49, $J$5) -> 22880.839 | L49: =IF(ABS(K49) > CHK_TOL, IF(INDEX(M49:O49, $J$5) = 0, 0, H49 / INDEX(M49:O49, $J$5) - 1), 0) -> 0 | M49: 22880.839 | N49: 17272.406 | O49: 28203.597
E50: ="CFADS FY"&F50 -> CFADS FY2027 | F50: 2027 | G50: $ 000s | H50: =SUMIFS(FinStat!$J$39:$CO$39,FinStat!$J$4:$CO$4,$F50) -> 24514.231 | J50: =IF(ABS(K50) > CHK_TOL, 1, 0) -> 1 | K50: =H50 - INDEX(M50:O50, $J$5) -> 24514.231 | L50: =IF(ABS(K50) > CHK_TOL, IF(INDEX(M50:O50, $J$5) = 0, 0, H50 / INDEX(M50:O50, $J$5) - 1), 0) -> 0 | M50: 24514.231 | N50: 18667.196 | O50: 30098.212
E51: Debt capacity (DSCR test) | G51: $ 000s | H51: =Sculpt!F26 -> 72154.225 | J51: =IF(ABS(K51) > CHK_TOL, 1, 0) -> 1 | K51: =H51 - INDEX(M51:O51, $J$5) -> 72154.225 | L51: =IF(ABS(K51) > CHK_TOL, IF(INDEX(M51:O51, $J$5) = 0, 0, H51 / INDEX(M51:O51, $J$5) - 1), 0) -> 0 | M51: 72154.225 | N51: 53910.521 | O51: 89309.584
E52: Minimum LLCR at COD | G52: x | H52: =Ratios!F22 -> 2.3998574 | J52: =IF(ABS(K52) > CHK_TOL, 1, 0) -> 1 | K52: =H52 - INDEX(M52:O52, $J$5) -> 2.3998574 | L52: =IF(ABS(K52) > CHK_TOL, IF(INDEX(M52:O52, $J$5) = 0, 0, H52 / INDEX(M52:O52, $J$5) - 1), 0) -> 0 | M52: 2.3998574 | N52: 2.4605143 | O52: 2.783283
A53: BALANCE SHEET | E53: Balance sheet date | G53: date | H53: 46387 | M53: 46387 | N53: 46387 | O53: 46387
E54: Non-current assets | G54: $ 000s | H54: =INDEX(FinStat!$J$62:$CO$62,MATCH($H$53,FinStat!$J$2:$CO$2,0)) -> 70978.533 | J54: =IF(ABS(K54) > CHK_TOL, 1, 0) -> 1 | K54: =H54 - INDEX(M54:O54, $J$5) -> 70978.533 | L54: =IF(ABS(K54) > CHK_TOL, IF(INDEX(M54:O54, $J$5) = 0, 0, H54 / INDEX(M54:O54, $J$5) - 1), 0) -> 0 | M54: 70978.533 | N54: 69932.114 | O54: 71201.99
E55: Receivables | G55: $ 000s | H55: =INDEX(FinStat!$J$63:$CO$63,MATCH($H$53,FinStat!$J$2:$CO$2,0)) -> 5199.0308 | J55: =IF(ABS(K55) > CHK_TOL, 1, 0) -> 1 | K55: =H55 - INDEX(M55:O55, $J$5) -> 5199.0308 | L55: =IF(ABS(K55) > CHK_TOL, IF(INDEX(M55:O55, $J$5) = 0, 0, H55 / INDEX(M55:O55, $J$5) - 1), 0) -> 0 | M55: 5199.0308 | N55: 4679.1277 | O55: 5718.9339
E56: Retained cash | G56: $ 000s | H56: =INDEX(FinStat!$J$64:$CO$64,MATCH($H$53,FinStat!$J$2:$CO$2,0)) -> 8932.722 | J56: =IF(ABS(K56) > CHK_TOL, 1, 0) -> 1 | K56: =H56 - INDEX(M56:O56, $J$5) -> 8932.722 | L56: =IF(ABS(K56) > CHK_TOL, IF(INDEX(M56:O56, $J$5) = 0, 0, H56 / INDEX(M56:O56, $J$5) - 1), 0) -> 0 | M56: 8932.722 | N56: 16788.974 | O56: 7021.7676
E57: Total assets | G57: $ 000s | H57: =INDEX(FinStat!$J$66:$CO$66,MATCH($H$53,FinStat!$J$2:$CO$2,0)) -> 90340.918 | J57: =IF(ABS(K57) > CHK_TOL, 1, 0) -> 1 | K57: =H57 - INDEX(M57:O57, $J$5) -> 90340.918 | L57: =IF(ABS(K57) > CHK_TOL, IF(INDEX(M57:O57, $J$5) = 0, 0, H57 / INDEX(M57:O57, $J$5) - 1), 0) -> 0 | M57: 90340.918 | N57: 95322.764 | O57: 89446.677
E58: Payables | G58: $ 000s | H58: =INDEX(FinStat!$J$69:$CO$69,MATCH($H$53,FinStat!$J$2:$CO$2,0)) -> 4537.0619 | J58: =IF(ABS(K58) > CHK_TOL, 1, 0) -> 1 | K58: =H58 - INDEX(M58:O58, $J$5) -> 4537.0619 | L58: =IF(ABS(K58) > CHK_TOL, IF(INDEX(M58:O58, $J$5) = 0, 0, H58 / INDEX(M58:O58, $J$5) - 1), 0) -> 0 | M58: 4537.0619 | N58: 4579.4 | O58: 4537.0619
E59: Senior debt | G59: $ 000s | H59: =INDEX(FinStat!$J$70:$CO$70,MATCH($H$53,FinStat!$J$2:$CO$2,0)) -> 47222.203 | J59: =IF(ABS(K59) > CHK_TOL, 1, 0) -> 1 | K59: =H59 - INDEX(M59:O59, $J$5) -> 47222.203 | L59: =IF(ABS(K59) > CHK_TOL, IF(INDEX(M59:O59, $J$5) = 0, 0, H59 / INDEX(M59:O59, $J$5) - 1), 0) -> 0 | M59: 47222.203 | N59: 35168.808 | O59: 49913.244
E60: Deferred tax | G60: $ 000s | H60: =INDEX(FinStat!$J$72:$CO$72,MATCH($H$53,FinStat!$J$2:$CO$2,0)) -> 9234.3749 | J60: =IF(ABS(K60) > CHK_TOL, 1, 0) -> 1 | K60: =H60 - INDEX(M60:O60, $J$5) -> 9234.3749 | L60: =IF(ABS(K60) > CHK_TOL, IF(INDEX(M60:O60, $J$5) = 0, 0, H60 / INDEX(M60:O60, $J$5) - 1), 0) -> 0 | M60: 9234.3749 | N60: 9089.2561 | O60: 9265.3642
E61: Share capital | G61: $ 000s | H61: =INDEX(FinStat!$J$73:$CO$73,MATCH($H$53,FinStat!$J$2:$CO$2,0)) -> 11565.43 | J61: =IF(ABS(K61) > CHK_TOL, 1, 0) -> 1 | K61: =H61 - INDEX(M61:O61, $J$5) -> 11565.43 | L61: =IF(ABS(K61) > CHK_TOL, IF(INDEX(M61:O61, $J$5) = 0, 0, H61 / INDEX(M61:O61, $J$5) - 1), 0) -> 0 | M61: 11565.43 | N61: 18235.06 | O61: 10140.298
E62: Retained earnings | G62: $ 000s | H62: =INDEX(FinStat!$J$74:$CO$74,MATCH($H$53,FinStat!$J$2:$CO$2,0)) -> 0 | J62: =IF(ABS(K62) > CHK_TOL, 1, 0) -> 0 | K62: =H62 - INDEX(M62:O62, $J$5) -> 0 | L62: =IF(ABS(K62) > CHK_TOL, IF(INDEX(M62:O62, $J$5) = 0, 0, H62 / INDEX(M62:O62, $J$5) - 1), 0) -> 0 | M62: 0 | N62: 0 | O62: 0
E63: Total liabilities and shareholder funds | G63: $ 000s | H63: =INDEX(FinStat!$J$75:$CO$75,MATCH($H$53,FinStat!$J$2:$CO$2,0)) -> 90340.918 | J63: =IF(ABS(K63) > CHK_TOL, 1, 0) -> 1 | K63: =H63 - INDEX(M63:O63, $J$5) -> 90340.918 | L63: =IF(ABS(K63) > CHK_TOL, IF(INDEX(M63:O63, $J$5) = 0, 0, H63 / INDEX(M63:O63, $J$5) - 1), 0) -> 0 | M63: 90340.918 | N63: 95322.764 | O63: 89446.677
E64: Balance check (assets less funding) | G64: $ 000s | H64: =H57-H63 -> 1.3096724e-10 | J64: =IF(ABS(K64) > CHK_TOL, 1, 0) -> 0 | K64: =H64 - INDEX(M64:O64, $J$5) -> 1.3096724e-10 | L64: =IF(ABS(K64) > CHK_TOL, IF(INDEX(M64:O64, $J$5) = 0, 0, H64 / INDEX(M64:O64, $J$5) - 1), 0) -> 0 | M64: 1.3096724e-10 | N64: -1.4551915e-11 | O64: -4.3655746e-11
